{
  "type": "Feature",
  "properties": {
    "gn:admin1_code":"03",
    "gn:admin2_code":"380258.0",
    "gn:asciiname":"Silaciems",
    "gn:country_code":"LV",
    "gn:dem":108,
    "gn:feature_class":"P",
    "gn:feature_code":"PPL",
    "gn:name":"Silaciems",
    "gn:population":0,
    "gn:timezone":"Europe/Riga",
    "iso:country":"LV",
    "name:und_x_variant":[
        "Silatsiems",
        "Silaciems"
    ],
    "wof:name":"Silaciems",
    "wof:placetype":"locality"
},
  "geometry": {"coordinates":[27.15415,57.1427],"type":"Point"}
}