{
  "type": "Feature",
  "properties": {
    "gn:admin1_code":"28",
    "gn:admin2_code":"880270.0",
    "gn:asciiname":"Fridrikmuiza",
    "gn:country_code":"LV",
    "gn:dem":43,
    "gn:feature_class":"P",
    "gn:feature_code":"PPL",
    "gn:name":"Fridri\u0137mui\u017ea",
    "gn:population":0,
    "gn:timezone":"Europe/Riga",
    "iso:country":"LV",
    "name:und_x_variant":[
        "Pridri\u0137i",
        "Fridri\u0137i",
        "Fridrichmui\u017ea",
        "Fridrikhmuyzha",
        "Fridri\u0137i Pusmui\u017eas Centrs",
        "Fridrihmui\u017ea",
        "Fridri\u0137mui\u017ea"
    ],
    "wof:name":"Fridrikmuiza",
    "wof:placetype":"locality"
},
  "geometry": {"coordinates":[22.89455,57.22844],"type":"Point"}
}