{
  "type": "Feature",
  "properties": {
    "gn:admin1_code":"09",
    "gn:admin2_code":"500284.0",
    "gn:asciiname":"Sejatas",
    "gn:country_code":"LV",
    "gn:dem":151,
    "gn:feature_class":"P",
    "gn:feature_code":"PPL",
    "gn:name":"Sejatas",
    "gn:population":0,
    "gn:timezone":"Europe/Riga",
    "iso:country":"LV",
    "name:und_x_variant":[
        "S\u0113jatas"
    ],
    "wof:name":"Sejatas",
    "wof:placetype":"locality"
},
  "geometry": {"coordinates":[26.15096,57.2471],"type":"Point"}
}