{
  "type": "Feature",
  "properties": {
    "gn:admin1_code":"07",
    "gn:admin2_code":"440270.0",
    "gn:asciiname":"Zalumi",
    "gn:country_code":"LV",
    "gn:dem":118,
    "gn:feature_class":"P",
    "gn:feature_code":"PPL",
    "gn:name":"Za\u013cumi",
    "gn:population":0,
    "gn:timezone":"Europe/Riga",
    "iso:country":"LV",
    "name:und_x_variant":[
        "Veca Za\u013c\u0101 Pu\u0161\u010da",
        "Zalpu\u0161\u010das",
        "Za\u013c\u0101-Pu\u0161\u010da",
        "Zalya-Pushcha",
        "Jaun\u0101 Za\u013c\u0101 Pu\u0161\u010da",
        "Za\u013cumi"
    ],
    "wof:name":"Zalumi",
    "wof:placetype":"locality"
},
  "geometry": {"coordinates":[26.62616,55.99038],"type":"Point"}
}