{
  "type": "Feature",
  "properties": {
    "gn:admin1_code":"46",
    "gn:admin2_code":"800625.0",
    "gn:asciiname":"Mencendarbe",
    "gn:country_code":"LV",
    "gn:dem":36,
    "gn:feature_class":"P",
    "gn:feature_code":"PPL",
    "gn:name":"Mencendarbe",
    "gn:population":0,
    "gn:timezone":"Europe/Riga",
    "iso:country":"LV",
    "name:und_x_variant":[
        "Mertsendarbe",
        "Mercendarbe",
        "Mencendarbe"
    ],
    "wof:name":"Mencendarbe",
    "wof:placetype":"locality"
},
  "geometry": {"coordinates":[24.43159,56.7655],"type":"Point"}
}