{
  "type": "Feature",
  "properties": {
    "iso:country":"LV",
    "name:lav_x_preferred":[
        "Su\u017ei"
    ],
    "name:ukr_x_preferred":[
        "\u0421\u044e\u0437\u0456"
    ],
    "wof:name":"Suzi",
    "wof:placetype":"neighbourhood"
},
  "geometry": {"coordinates":[24.20597783295577,57.01619279199581],"type":"Point"}
}