{
  "type": "Feature",
  "properties": {
    "gn:admin1_code":"44",
    "gn:admin2_code":"460894.0",
    "gn:asciiname":"Karli",
    "gn:country_code":"LV",
    "gn:dem":86,
    "gn:feature_class":"P",
    "gn:feature_code":"PPL",
    "gn:name":"K\u0101r\u013ci",
    "gn:population":0,
    "gn:timezone":"Europe/Riga",
    "iso:country":"LV",
    "name:und_x_variant":[
        "K\u0101rle",
        "K\u0101r\u013ci",
        "K\u0101rkli"
    ],
    "wof:name":"Karli",
    "wof:placetype":"locality"
},
  "geometry": {"coordinates":[22.95,56.43333000000001],"type":"Point"}
}