{
  "type": "Feature",
  "properties": {
    "gn:admin1_code":"35",
    "gn:admin2_code":"604394.0",
    "gn:asciiname":"Prusaki",
    "gn:country_code":"LV",
    "gn:dem":170,
    "gn:feature_class":"P",
    "gn:feature_code":"PPL",
    "gn:name":"Prusaki",
    "gn:population":0,
    "gn:timezone":"Europe/Riga",
    "iso:country":"LV",
    "wof:name":"Prusaki",
    "wof:placetype":"locality"
},
  "geometry": {"coordinates":[27.06241,56.06875],"type":"Point"}
}