{
  "type": "Feature",
  "properties": {
    "gn:admin1_code":"22",
    "gn:admin2_code":"760258.0",
    "gn:asciiname":"Maskvina",
    "gn:cc2":"LV",
    "gn:country_code":"LV",
    "gn:dem":113,
    "gn:feature_class":"P",
    "gn:feature_code":"PPL",
    "gn:name":"Maskvina",
    "gn:population":0,
    "gn:timezone":"Europe/Riga",
    "iso:country":"LV",
    "name:und_x_variant":[
        "Moskvina",
        "Maskvina"
    ],
    "wof:name":"Maskvina",
    "wof:placetype":"locality"
},
  "geometry": {"coordinates":[26.65215,56.30473000000001],"type":"Point"}
}