{
  "type": "Feature",
  "properties": {
    "gn:admin1_code":"28",
    "gn:asciiname":"Usi",
    "gn:cc2":"LV",
    "gn:country_code":"LV",
    "gn:dem":13,
    "gn:feature_class":"P",
    "gn:feature_code":"PPL",
    "gn:name":"U\u0161i",
    "gn:population":0,
    "gn:timezone":"Europe/Riga",
    "iso:country":"LV",
    "name:und_x_variant":[
        "Ushi",
        "U\u0161i"
    ],
    "wof:name":"Usi",
    "wof:placetype":"locality"
},
  "geometry": {"coordinates":[22.56836,57.70094],"type":"Point"}
}