{
  "type": "Feature",
  "properties": {
    "gn:admin1_code":"27",
    "gn:admin2_code":"840248.0",
    "gn:asciiname":"Grivaisi",
    "gn:cc2":"LV",
    "gn:country_code":"LV",
    "gn:dem":69,
    "gn:feature_class":"P",
    "gn:feature_code":"PPL",
    "gn:name":"Gr\u012bvai\u0161i",
    "gn:population":0,
    "gn:timezone":"Europe/Riga",
    "iso:country":"LV",
    "name:und_x_variant":[
        "Celmenieki",
        "Grivayshi",
        "Gr\u012bvai\u0161i"
    ],
    "wof:name":"Grivaisi",
    "wof:placetype":"locality"
},
  "geometry": {"coordinates":[22.43799,56.42404000000001],"type":"Point"}
}