{
  "type": "Feature",
  "properties": {
    "gn:admin1_code":"12",
    "gn:admin2_code":"540274.0",
    "gn:asciiname":"Klavi",
    "gn:country_code":"LV",
    "gn:dem":36,
    "gn:feature_class":"P",
    "gn:feature_code":"PPL",
    "gn:name":"Kl\u0101vi",
    "gn:population":0,
    "gn:timezone":"Europe/Riga",
    "iso:country":"LV",
    "name:lav_x_preferred":[
        "Kl\u0101vi"
    ],
    "wof:name":"Klavi",
    "wof:placetype":"locality"
},
  "geometry": {"coordinates":[23.84247,56.37308],"type":"Point"}
}