{
  "type": "Feature",
  "properties": {
    "gn:admin1_code":"12",
    "gn:admin2_code":"540252.0",
    "gn:asciiname":"Gluda",
    "gn:country_code":"LV",
    "gn:dem":11,
    "gn:feature_class":"P",
    "gn:feature_code":"PPL",
    "gn:name":"Gl\u016bda",
    "gn:population":0,
    "gn:timezone":"Europe/Riga",
    "iso:country":"LV",
    "name:und_x_variant":[
        "Gl\u016bda",
        "Gludas Mui\u017ea",
        "Falcgr\u0101ves Mui\u017ea",
        "Falcgr\u0101ve"
    ],
    "wof:name":"Gluda",
    "wof:placetype":"locality"
},
  "geometry": {"coordinates":[23.49185,56.59987],"type":"Point"}
}