{
  "type": "Feature",
  "properties": {
    "gn:admin1_code":"27",
    "gn:admin2_code":"840286.0",
    "gn:asciiname":"Namiki",
    "gn:country_code":"LV",
    "gn:dem":116,
    "gn:feature_class":"P",
    "gn:feature_code":"PPL",
    "gn:name":"Nami\u0137i",
    "gn:population":0,
    "gn:timezone":"Europe/Riga",
    "iso:country":"LV",
    "wof:name":"Namiki",
    "wof:placetype":"locality"
},
  "geometry": {"coordinates":[22.3956,56.71944000000001],"type":"Point"}
}