{
  "type": "Feature",
  "properties": {
    "gn:admin1_code":"56",
    "gn:admin2_code":"684990.0",
    "gn:asciiname":"Nuraugi",
    "gn:country_code":"LV",
    "gn:dem":146,
    "gn:feature_class":"P",
    "gn:feature_code":"PPL",
    "gn:name":"N\u016braugi",
    "gn:population":0,
    "gn:timezone":"Europe/Riga",
    "iso:country":"LV",
    "wof:name":"Nuraugi",
    "wof:placetype":"locality"
},
  "geometry": {"coordinates":[27.74387,56.63591],"type":"Point"}
}