{
  "type": "Feature",
  "properties": {
    "gn:admin1_code":"20",
    "gn:admin2_code":"700268.0",
    "gn:asciiname":"Lubeja",
    "gn:country_code":"LV",
    "gn:dem":230,
    "gn:feature_class":"P",
    "gn:feature_code":"PPL",
    "gn:name":"Lubeja",
    "gn:population":0,
    "gn:timezone":"Europe/Riga",
    "iso:country":"LV",
    "wof:name":"Lubeja",
    "wof:placetype":"locality"
},
  "geometry": {"coordinates":[25.96189,56.9387],"type":"Point"}
}