{
  "type": "Feature",
  "properties": {
    "gn:admin1_code":"27",
    "gn:admin2_code":"840294.0",
    "gn:asciiname":"Gobdzinas",
    "gn:country_code":"LV",
    "gn:dem":66,
    "gn:feature_class":"P",
    "gn:feature_code":"PPL",
    "gn:name":"Gobdzi\u0146as",
    "gn:population":0,
    "gn:timezone":"Europe/Riga",
    "iso:country":"LV",
    "name:und_x_variant":[
        "Gobzdi\u0146i",
        "Gobdzi\u0146i",
        "Gobzi\u0146i",
        "Gobdzi\u0146as"
    ],
    "wof:name":"Gobdzinas",
    "wof:placetype":"locality"
},
  "geometry": {"coordinates":[22.13995,56.48252],"type":"Point"}
}