{
  "type": "Feature",
  "properties": {
    "gn:admin1_code":"D1",
    "gn:admin2_code":"941690.0",
    "gn:asciiname":"Grosli",
    "gn:country_code":"LV",
    "gn:dem":139,
    "gn:feature_class":"P",
    "gn:feature_code":"PPL",
    "gn:name":"Gro\u0161\u013ci",
    "gn:population":0,
    "gn:timezone":"Europe/Riga",
    "iso:country":"LV",
    "wof:name":"Grosli",
    "wof:placetype":"locality"
},
  "geometry": {"coordinates":[26.15819,57.30202],"type":"Point"}
}