{
  "type": "Feature",
  "properties": {
    "gn:admin1_code":"77",
    "gn:admin2_code":"901292.0",
    "gn:asciiname":"Zante",
    "gn:country_code":"LV",
    "gn:dem":149,
    "gn:feature_class":"P",
    "gn:feature_code":"PPL",
    "gn:name":"Zante",
    "gn:population":0,
    "gn:timezone":"Europe/Riga",
    "iso:country":"LV",
    "name:und_x_variant":[
        "Zantes Mui\u017ea",
        "Zante"
    ],
    "wof:name":"Zante",
    "wof:placetype":"locality"
},
  "geometry": {"coordinates":[22.73825,56.83743000000001],"type":"Point"}
}