{
  "type": "Feature",
  "properties": {
    "gn:admin1_code":"04",
    "gn:asciiname":"Kiri",
    "gn:cc2":"LV",
    "gn:country_code":"LV",
    "gn:dem":40,
    "gn:feature_class":"P",
    "gn:feature_code":"PPL",
    "gn:name":"\u0136iri",
    "gn:population":0,
    "gn:timezone":"Europe/Riga",
    "iso:country":"LV",
    "name:ceb_x_preferred":[
        "Kiri"
    ],
    "name:deu_x_preferred":[
        "Kiri"
    ],
    "name:est_x_preferred":[
        "Kiri"
    ],
    "name:fas_x_preferred":[
        "\u06a9\u06cc\u0631\u06cc"
    ],
    "name:fin_x_preferred":[
        "Kiri"
    ],
    "name:fra_x_preferred":[
        "Kiri"
    ],
    "name:ind_x_preferred":[
        "Kiri"
    ],
    "name:ron_x_preferred":[
        "Kiri"
    ],
    "name:spa_x_preferred":[
        "Kiri"
    ],
    "name:swe_x_preferred":[
        "Kiri"
    ],
    "name:ukr_x_preferred":[
        "\u041a\u0456\u0440\u0456"
    ],
    "name:und_x_variant":[
        "\u0136eiri"
    ],
    "wof:name":"Kiri",
    "wof:placetype":"locality"
},
  "geometry": {"coordinates":[24.61667000000001,56.56667],"type":"Point"}
}