{
  "type": "Feature",
  "properties": {
    "gn:admin1_code":"18",
    "gn:asciiname":"Mernieki",
    "gn:cc2":"LV",
    "gn:country_code":"LV",
    "gn:dem":33,
    "gn:feature_class":"P",
    "gn:feature_code":"PPL",
    "gn:name":"M\u0113rnieki",
    "gn:population":0,
    "gn:timezone":"Europe/Riga",
    "iso:country":"LV",
    "name:und_x_variant":[
        "Merniyeki",
        "M\u0113rnieki"
    ],
    "wof:name":"Mernieki",
    "wof:placetype":"locality"
},
  "geometry": {"coordinates":[24.51303,57.85704000000001],"type":"Point"}
}