{
  "type": "Feature",
  "properties": {
    "gn:admin1_code":"72",
    "gn:admin2_code":"425756.0",
    "gn:asciiname":"Abrupe",
    "gn:country_code":"LV",
    "gn:dem":179,
    "gn:feature_class":"P",
    "gn:feature_code":"PPL",
    "gn:name":"Abrupe",
    "gn:population":0,
    "gn:timezone":"Europe/Riga",
    "iso:country":"LV",
    "name:und_x_variant":[
        "Abrup\u2019i",
        "Abtupe",
        "Abrupji",
        "Abrupe"
    ],
    "wof:name":"Abrupe",
    "wof:placetype":"locality"
},
  "geometry": {"coordinates":[25.98804,57.14431999999999],"type":"Point"}
}