{
  "type": "Feature",
  "properties": {
    "gn:admin1_code":"51",
    "gn:admin2_code":"840652.0",
    "gn:asciiname":"Satiki",
    "gn:country_code":"LV",
    "gn:dem":123,
    "gn:feature_class":"P",
    "gn:feature_code":"PPL",
    "gn:name":"Sati\u0137i",
    "gn:population":0,
    "gn:timezone":"Europe/Riga",
    "iso:country":"LV",
    "name:und_x_variant":[
        "Myza Vyatssatyti",
        "Vecsati\u0137u Mui\u017ea",
        "Vecs\u0101ti\u0137i",
        "Sati\u0137i"
    ],
    "wof:name":"Satiki",
    "wof:placetype":"locality"
},
  "geometry": {"coordinates":[22.52685,56.80654000000001],"type":"Point"}
}