{
  "type": "Feature",
  "properties": {
    "gn:admin1_code":"24",
    "gn:admin2_code":"780278.0",
    "gn:asciiname":"Ozolmuiza",
    "gn:country_code":"LV",
    "gn:dem":159,
    "gn:feature_class":"P",
    "gn:feature_code":"PPL",
    "gn:name":"Ozolmui\u017ea",
    "gn:population":0,
    "gn:timezone":"Europe/Riga",
    "iso:country":"LV",
    "wof:name":"Ozolmuiza",
    "wof:placetype":"locality"
},
  "geometry": {"coordinates":[27.22481,56.49131],"type":"Point"}
}