{
  "type": "Feature",
  "properties": {
    "gn:admin1_code":"44",
    "gn:admin2_code":"460876.0",
    "gn:asciiname":"Galauce",
    "gn:country_code":"LV",
    "gn:dem":115,
    "gn:feature_class":"P",
    "gn:feature_code":"PPL",
    "gn:name":"Galauce",
    "gn:population":0,
    "gn:timezone":"Europe/Riga",
    "iso:country":"LV",
    "name:und_x_variant":[
        "Galautse",
        "Galauces Pusmui\u017ea",
        "Galauce"
    ],
    "wof:name":"Galauce",
    "wof:placetype":"locality"
},
  "geometry": {"coordinates":[22.78333,56.53333000000001],"type":"Point"}
}