{
  "type": "Feature",
  "properties": {
    "gn:admin1_code":"C3",
    "gn:admin2_code":"801231.0",
    "gn:asciiname":"Bajari",
    "gn:country_code":"LV",
    "gn:dem":23,
    "gn:feature_class":"P",
    "gn:feature_code":"PPL",
    "gn:name":"Baj\u0101ri",
    "gn:population":0,
    "gn:timezone":"Europe/Riga",
    "iso:country":"LV",
    "name:und_x_variant":[
        "Bayary",
        "Akerma\u0146i",
        "Baj\u0101ri"
    ],
    "wof:name":"Bajari",
    "wof:placetype":"locality"
},
  "geometry": {"coordinates":[24.42613,56.8648],"type":"Point"}
}