{
  "type": "Feature",
  "properties": {
    "gn:admin1_code":"57",
    "gn:admin2_code":"601092.0",
    "gn:asciiname":"Peickova",
    "gn:country_code":"LV",
    "gn:dem":169,
    "gn:feature_class":"P",
    "gn:feature_code":"PPL",
    "gn:name":"Peickova",
    "gn:population":0,
    "gn:timezone":"Europe/Riga",
    "iso:country":"LV",
    "wof:name":"Peickova",
    "wof:placetype":"locality"
},
  "geometry": {"coordinates":[27.90601,56.16791],"type":"Point"}
}