{
  "type": "Feature",
  "properties": {
    "gn:admin1_code":"14",
    "gn:admin2_code":"600274.0",
    "gn:asciiname":"Romuli",
    "gn:country_code":"LV",
    "gn:dem":204,
    "gn:feature_class":"P",
    "gn:feature_code":"PPL",
    "gn:name":"Romu\u013ci",
    "gn:population":0,
    "gn:timezone":"Europe/Riga",
    "iso:country":"LV",
    "name:eng_x_preferred":[
        "Romu\u013ci"
    ],
    "name:rus_x_preferred":[
        "\u041a\u043e\u043c\u0431\u0443\u043b\u0438"
    ],
    "name:und_x_variant":[
        "Romu\u013ci"
    ],
    "wof:name":"Romuli",
    "wof:placetype":"locality"
},
  "geometry": {"coordinates":[27.15127,55.98413000000001],"type":"Point"}
}