{
  "type": "Feature",
  "properties": {
    "gn:admin1_code":"14",
    "gn:admin2_code":"600274.0",
    "gn:asciiname":"Romuli",
    "gn:country_code":"LV",
    "gn:dem":204,
    "gn:feature_class":"P",
    "gn:feature_code":"PPL",
    "gn:name":"Romu\u013ci",
    "gn:population":0,
    "gn:timezone":"Europe/Riga",
    "iso:country":"LV",
    "name:ceb_x_preferred":[
        "Comuna Romuli"
    ],
    "name:deu_x_preferred":[
        "Romuli"
    ],
    "name:eng_x_preferred":[
        "Romu\u013ci"
    ],
    "name:epo_x_preferred":[
        "Romuli"
    ],
    "name:ita_x_preferred":[
        "Romuli"
    ],
    "name:msa_x_preferred":[
        "Romuli"
    ],
    "name:nld_x_preferred":[
        "Romuli"
    ],
    "name:por_x_preferred":[
        "Romuli"
    ],
    "name:ron_x_preferred":[
        "Comuna Romuli"
    ],
    "name:rus_x_preferred":[
        "\u041a\u043e\u043c\u0431\u0443\u043b\u0438"
    ],
    "name:spa_x_preferred":[
        "Romuli"
    ],
    "name:sqi_x_preferred":[
        "Romuli"
    ],
    "name:srp_x_preferred":[
        "\u041e\u043f\u0448\u0442\u0438\u043d\u0430 \u0420\u043e\u043c\u0443\u043b\u0438"
    ],
    "name:ukr_x_preferred":[
        "\u0420\u043e\u043c\u0443\u043b\u044c"
    ],
    "name:vie_x_preferred":[
        "Romuli"
    ],
    "name:vol_x_preferred":[
        "Romuli"
    ],
    "name:zho_x_preferred":[
        "\u7f85\u7a46\u5229\u9109"
    ],
    "wof:name":"Romuli",
    "wof:placetype":"locality"
},
  "geometry": {"coordinates":[27.15127,55.98413000000001],"type":"Point"}
}