{
  "type": "Feature",
  "properties": {
    "gn:admin1_code":"30",
    "gn:asciiname":"Drand",
    "gn:country_code":"LV",
    "gn:dem":75,
    "gn:feature_class":"P",
    "gn:feature_code":"PPL",
    "gn:name":"Drand",
    "gn:population":0,
    "gn:timezone":"Europe/Riga",
    "iso:country":"LV",
    "wof:name":"Drand",
    "wof:placetype":"locality"
},
  "geometry": {"coordinates":[25.70852,57.44661],"type":"Point"}
}