{
  "type": "Feature",
  "properties": {
    "gn:admin1_code":"15",
    "gn:admin2_code":"620296.0",
    "gn:asciiname":"Briezi",
    "gn:country_code":"LV",
    "gn:dem":66,
    "gn:feature_class":"P",
    "gn:feature_code":"PPL",
    "gn:name":"Brie\u017ei",
    "gn:population":0,
    "gn:timezone":"Europe/Riga",
    "iso:country":"LV",
    "wof:name":"Briezi",
    "wof:placetype":"locality"
},
  "geometry": {"coordinates":[22.26667,56.86666999999999],"type":"Point"}
}