{
  "type": "Feature",
  "properties": {
    "gn:admin1_code":"12",
    "gn:admin2_code":"540292.0",
    "gn:asciiname":"Kauvuzas",
    "gn:cc2":"LV",
    "gn:country_code":"LV",
    "gn:dem":12,
    "gn:feature_class":"P",
    "gn:feature_code":"PPL",
    "gn:name":"Kauvu\u017eas",
    "gn:population":0,
    "gn:timezone":"Europe/Riga",
    "iso:country":"LV",
    "name:und_x_variant":[
        "Kavuzhas"
    ],
    "wof:name":"Kauvuzas",
    "wof:placetype":"locality"
},
  "geometry": {"coordinates":[23.86278,56.52611],"type":"Point"}
}