{
  "type": "Feature",
  "properties": {
    "gn:admin1_code":"29",
    "gn:asciiname":"Valdeki",
    "gn:country_code":"LV",
    "gn:dem":67,
    "gn:feature_class":"P",
    "gn:feature_code":"PPL",
    "gn:name":"Valde\u0137i",
    "gn:population":0,
    "gn:timezone":"Europe/Riga",
    "iso:country":"LV",
    "wof:name":"Valdeki",
    "wof:placetype":"locality"
},
  "geometry": {"coordinates":[22.77298,56.99903000000001],"type":"Point"}
}