{
  "type": "Feature",
  "properties": {
    "gn:admin1_code":"72",
    "gn:admin2_code":"425756.0",
    "gn:asciiname":"Paupi",
    "gn:country_code":"LV",
    "gn:dem":183,
    "gn:feature_class":"P",
    "gn:feature_code":"PPL",
    "gn:name":"Paupi",
    "gn:population":0,
    "gn:timezone":"Europe/Riga",
    "iso:country":"LV",
    "name:und_x_variant":[
        "Paupji",
        "Paup\u2019i",
        "Paupi"
    ],
    "wof:name":"Paupi",
    "wof:placetype":"locality"
},
  "geometry": {"coordinates":[25.96612,57.18609],"type":"Point"}
}