{
  "type": "Feature",
  "properties": {
    "gn:admin1_code":"12",
    "gn:admin2_code":"540258.0",
    "gn:asciiname":"Valgundes Ciems",
    "gn:cc2":"LV",
    "gn:country_code":"LV",
    "gn:dem":3,
    "gn:feature_class":"P",
    "gn:feature_code":"PPL",
    "gn:name":"Valgundes Ciems",
    "gn:population":0,
    "gn:timezone":"Europe/Riga",
    "iso:country":"LV",
    "name:und_x_variant":[
        "Valguntestsiyem",
        "Valguntes-Ciems",
        "Valguntes-Tsiems"
    ],
    "wof:name":"Valgundes Ciems",
    "wof:placetype":"locality"
},
  "geometry": {"coordinates":[23.61667000000001,56.76667],"type":"Point"}
}