{
  "type": "Feature",
  "properties": {
    "gn:admin1_code":"B7",
    "gn:admin2_code":"387564.0",
    "gn:asciiname":"Pilsnieki",
    "gn:country_code":"LV",
    "gn:dem":97,
    "gn:feature_class":"P",
    "gn:feature_code":"PPL",
    "gn:name":"Pilsnieki",
    "gn:population":0,
    "gn:timezone":"Europe/Riga",
    "iso:country":"LV",
    "wof:name":"Pilsnieki",
    "wof:placetype":"locality"
},
  "geometry": {"coordinates":[27.06034,56.9425],"type":"Point"}
}