{
  "type": "Feature",
  "properties": {
    "gn:admin1_code":"E1",
    "gn:admin2_code":"701894.0",
    "gn:asciiname":"Justi",
    "gn:country_code":"LV",
    "gn:dem":93,
    "gn:feature_class":"P",
    "gn:feature_code":"PPL",
    "gn:name":"Justi",
    "gn:population":0,
    "gn:timezone":"Europe/Riga",
    "iso:country":"LV",
    "wof:name":"Justi",
    "wof:placetype":"locality"
},
  "geometry": {"coordinates":[26.76598,56.64043],"type":"Point"}
}