{
  "type": "Feature",
  "properties": {
    "gn:admin1_code":"28",
    "gn:admin2_code":"880270.0",
    "gn:asciiname":"Plavmuiza",
    "gn:cc2":"LV",
    "gn:country_code":"LV",
    "gn:dem":47,
    "gn:feature_class":"P",
    "gn:feature_code":"PPL",
    "gn:name":"P\u013cavmui\u017ea",
    "gn:population":0,
    "gn:timezone":"Europe/Riga",
    "iso:country":"LV",
    "name:und_x_variant":[
        "Plevas",
        "P\u013cavmui\u017ea"
    ],
    "wof:name":"Plavmuiza",
    "wof:placetype":"locality"
},
  "geometry": {"coordinates":[22.86736,57.25157],"type":"Point"}
}