{
  "type": "Feature",
  "properties": {
    "gn:admin1_code":"B7",
    "gn:admin2_code":"387574.0",
    "gn:asciiname":"Medni",
    "gn:country_code":"LV",
    "gn:dem":105,
    "gn:feature_class":"P",
    "gn:feature_code":"PPL",
    "gn:name":"Med\u0146i",
    "gn:population":0,
    "gn:timezone":"Europe/Riga",
    "iso:country":"LV",
    "name:eng_x_preferred":[
        "Med\u0146i"
    ],
    "name:rus_x_preferred":[
        "\u041c\u0435\u0434\u043d\u0438"
    ],
    "name:und_x_variant":[
        "Medni Pervyye"
    ],
    "wof:name":"Medni",
    "wof:placetype":"locality"
},
  "geometry": {"coordinates":[27.19372000000001,57.04481],"type":"Point"}
}