{
  "type": "Feature",
  "properties": {
    "gn:admin1_code":"38",
    "gn:admin2_code":"560825.0",
    "gn:asciiname":"Kudrasi",
    "gn:country_code":"LV",
    "gn:dem":107,
    "gn:feature_class":"P",
    "gn:feature_code":"PPLL",
    "gn:name":"Kudra\u0161i",
    "gn:population":0,
    "gn:timezone":"Europe/Riga",
    "iso:country":"LV",
    "name:und_x_variant":[
        "Kudrash",
        "Kudra\u0161i"
    ],
    "wof:name":"Kudrasi",
    "wof:placetype":"locality"
},
  "geometry": {"coordinates":[25.81462,56.19953],"type":"Point"}
}