{
  "type": "Feature",
  "properties": {
    "gn:admin1_code":"15",
    "gn:admin2_code":"620292.0",
    "gn:asciiname":"Maras",
    "gn:country_code":"LV",
    "gn:dem":59,
    "gn:feature_class":"P",
    "gn:feature_code":"PPL",
    "gn:name":"Maras",
    "gn:population":0,
    "gn:timezone":"Europe/Riga",
    "iso:country":"LV",
    "name:deu_x_preferred":[
        "Maras"
    ],
    "name:fra_x_preferred":[
        "Maras"
    ],
    "name:ita_x_preferred":[
        "Maras"
    ],
    "name:jpn_x_preferred":[
        "\u30de\u30e9\u30b9"
    ],
    "name:nld_x_preferred":[
        "Maras"
    ],
    "name:pol_x_preferred":[
        "Maras"
    ],
    "name:und_x_variant":[
        "Mara"
    ],
    "wof:name":"Maras",
    "wof:placetype":"locality"
},
  "geometry": {"coordinates":[21.67197,56.86283],"type":"Point"}
}