{
  "type": "Feature",
  "properties": {
    "gn:admin1_code":"15",
    "gn:admin2_code":"620250.0",
    "gn:asciiname":"Vitoli",
    "gn:country_code":"LV",
    "gn:dem":55,
    "gn:feature_class":"P",
    "gn:feature_code":"PPL",
    "gn:name":"V\u012btoli",
    "gn:population":0,
    "gn:timezone":"Europe/Riga",
    "iso:country":"LV",
    "wof:name":"Vitoli",
    "wof:placetype":"locality"
},
  "geometry": {"coordinates":[21.65,56.91667],"type":"Point"}
}