{
  "type": "Feature",
  "properties": {
    "gn:admin1_code":"65",
    "gn:admin2_code":"641076.0",
    "gn:asciiname":"Medze",
    "gn:cc2":"LV",
    "gn:country_code":"LV",
    "gn:dem":28,
    "gn:feature_class":"P",
    "gn:feature_code":"PPL",
    "gn:name":"Medze",
    "gn:population":0,
    "gn:timezone":"Europe/Riga",
    "iso:country":"LV",
    "name:und_x_variant":[
        "Medzes Mui\u017ea",
        "Myza Medze",
        "Medsen",
        "Medze"
    ],
    "wof:name":"Medze",
    "wof:placetype":"locality"
},
  "geometry": {"coordinates":[21.13137,56.65505],"type":"Point"}
}