{
  "type": "Feature",
  "properties": {
    "gn:admin1_code":"03",
    "gn:admin2_code":"380250.0",
    "gn:asciiname":"Silamuiza",
    "gn:country_code":"LV",
    "gn:dem":96,
    "gn:feature_class":"P",
    "gn:feature_code":"PPL",
    "gn:name":"Silamui\u017ea",
    "gn:population":0,
    "gn:timezone":"Europe/Riga",
    "iso:country":"LV",
    "name:und_x_variant":[
        "Silamui\u017ea",
        "Selomyzki",
        "Selamiski"
    ],
    "wof:name":"Silamuiza",
    "wof:placetype":"locality"
},
  "geometry": {"coordinates":[27.09428,56.82642],"type":"Point"}
}