{
  "type": "Feature",
  "properties": {
    "gn:admin1_code":"24",
    "gn:admin2_code":"780284.0",
    "gn:asciiname":"Kucinas",
    "gn:country_code":"LV",
    "gn:dem":130,
    "gn:feature_class":"P",
    "gn:feature_code":"PPL",
    "gn:name":"Kuci\u0146as",
    "gn:population":0,
    "gn:timezone":"Europe/Riga",
    "iso:country":"LV",
    "name:und_x_variant":[
        "Kuc\u0113ni",
        "Kucini",
        "Kuci\u0146as"
    ],
    "wof:name":"Kucinas",
    "wof:placetype":"locality"
},
  "geometry": {"coordinates":[27.29843,56.70901],"type":"Point"}
}