{
  "type": "Feature",
  "properties": {
    "gn:admin1_code":"12",
    "gn:admin2_code":"540296.0",
    "gn:asciiname":"Gaurini",
    "gn:country_code":"LV",
    "gn:dem":40,
    "gn:feature_class":"P",
    "gn:feature_code":"PPL",
    "gn:name":"Gauri\u0146i",
    "gn:population":0,
    "gn:timezone":"Europe/Riga",
    "iso:country":"LV",
    "name:und_x_variant":[
        "Labeni",
        "Gauri\u0146i",
        "Gai\u013cu S\u0101d\u017ea"
    ],
    "wof:name":"Gaurini",
    "wof:placetype":"locality"
},
  "geometry": {"coordinates":[23.4564,56.48006],"type":"Point"}
}