{
  "type": "Feature",
  "properties": {
    "gn:admin1_code":"28",
    "gn:asciiname":"Gipka",
    "gn:cc2":"LV",
    "gn:country_code":"LV",
    "gn:dem":7,
    "gn:feature_class":"P",
    "gn:feature_code":"PPL",
    "gn:name":"\u0122ipka",
    "gn:population":0,
    "gn:timezone":"Europe/Riga",
    "iso:country":"LV",
    "name:und_x_variant":[
        "Dipka",
        "\u0122ipka"
    ],
    "wof:name":"Gipka",
    "wof:placetype":"locality"
},
  "geometry": {"coordinates":[22.65347,57.57057],"type":"Point"}
}