{
  "type": "Feature",
  "properties": {
    "gn:admin1_code":"72",
    "gn:admin2_code":"425756.0",
    "gn:asciiname":"Kanazi",
    "gn:country_code":"LV",
    "gn:dem":188,
    "gn:feature_class":"P",
    "gn:feature_code":"PPL",
    "gn:name":"Kan\u0101\u017ei",
    "gn:population":0,
    "gn:timezone":"Europe/Riga",
    "iso:country":"LV",
    "name:und_x_variant":[
        "Myza Druviena",
        "Druvienas Mui\u017ea",
        "Druviena",
        "Kan\u0101\u017ei"
    ],
    "wof:name":"Kanazi",
    "wof:placetype":"locality"
},
  "geometry": {"coordinates":[26.14348,57.12461],"type":"Point"}
}