{
  "type": "Feature",
  "properties": {
    "gn:admin1_code":"33",
    "gn:admin2_code":"980256.0",
    "gn:asciiname":"Topciems",
    "gn:country_code":"LV",
    "gn:dem":27,
    "gn:feature_class":"P",
    "gn:feature_code":"PPL",
    "gn:name":"Topciems",
    "gn:population":0,
    "gn:timezone":"Europe/Riga",
    "iso:country":"LV",
    "wof:name":"Topciems",
    "wof:placetype":"locality"
},
  "geometry": {"coordinates":[21.9512,57.39143000000001],"type":"Point"}
}