{
  "type": "Feature",
  "properties": {
    "gn:admin1_code":"77",
    "gn:admin2_code":"901292.0",
    "gn:asciiname":"Jaundziras",
    "gn:country_code":"LV",
    "gn:dem":129,
    "gn:feature_class":"P",
    "gn:feature_code":"PPL",
    "gn:name":"Jaundziras",
    "gn:population":0,
    "gn:timezone":"Europe/Riga",
    "iso:country":"LV",
    "wof:name":"Jaundziras",
    "wof:placetype":"locality"
},
  "geometry": {"coordinates":[22.73472000000001,56.87245],"type":"Point"}
}