{
  "type": "Feature",
  "properties": {
    "gn:admin1_code":"56",
    "gn:admin2_code":"684998.0",
    "gn:asciiname":"Razanova",
    "gn:country_code":"LV",
    "gn:dem":135,
    "gn:feature_class":"P",
    "gn:feature_code":"PPL",
    "gn:name":"Ra\u017eanova",
    "gn:population":0,
    "gn:timezone":"Europe/Riga",
    "iso:country":"LV",
    "name:und_x_variant":[
        "Ra\u017eanova",
        "Ro\u017eanova"
    ],
    "wof:name":"Razanova",
    "wof:placetype":"locality"
},
  "geometry": {"coordinates":[27.83374,56.57958000000001],"type":"Point"}
}