{
  "type": "Feature",
  "properties": {
    "gn:admin1_code":"72",
    "gn:admin2_code":"425798.0",
    "gn:asciiname":"Melnbarzi",
    "gn:country_code":"LV",
    "gn:dem":180,
    "gn:feature_class":"P",
    "gn:feature_code":"PPL",
    "gn:name":"Melnb\u0101r\u017ei",
    "gn:population":0,
    "gn:timezone":"Europe/Riga",
    "iso:country":"LV",
    "name:und_x_variant":[
        "Melnb\u0101r\u017ei",
        "Melb\u0101rz"
    ],
    "wof:name":"Melnbarzi",
    "wof:placetype":"locality"
},
  "geometry": {"coordinates":[25.84116,57.17312],"type":"Point"}
}