{
  "type": "Feature",
  "properties": {
    "gn:admin1_code":"08",
    "gn:admin2_code":"460260.0",
    "gn:asciiname":"Berzbeke",
    "gn:country_code":"LV",
    "gn:dem":66,
    "gn:feature_class":"P",
    "gn:feature_code":"PPL",
    "gn:name":"B\u0113rzbe\u0137e",
    "gn:population":0,
    "gn:timezone":"Europe/Riga",
    "iso:country":"LV",
    "name:lav_x_preferred":[
        "B\u0113rzbe\u0137e"
    ],
    "name:und_x_variant":[
        "Plyavniyeki",
        "B\u0113rzbe\u0137e"
    ],
    "wof:name":"Berzbeke",
    "wof:placetype":"locality"
},
  "geometry": {"coordinates":[23.23518,56.66681],"type":"Point"}
}