{
  "type": "Feature",
  "properties": {
    "gn:admin1_code":"57",
    "gn:admin2_code":"601042.0",
    "gn:asciiname":"Pogulanovka",
    "gn:country_code":"LV",
    "gn:dem":197,
    "gn:feature_class":"P",
    "gn:feature_code":"PPL",
    "gn:name":"Pogu\u013canovka",
    "gn:population":0,
    "gn:timezone":"Europe/Riga",
    "iso:country":"LV",
    "wof:name":"Pogulanovka",
    "wof:placetype":"locality"
},
  "geometry": {"coordinates":[27.46667,56.11666999999999],"type":"Point"}
}