{
  "type": "Feature",
  "properties": {
    "gn:admin1_code":"18",
    "gn:asciiname":"Krumini",
    "gn:country_code":"LV",
    "gn:dem":11,
    "gn:feature_class":"P",
    "gn:feature_code":"PPL",
    "gn:name":"Krumini",
    "gn:population":0,
    "gn:timezone":"Europe/Riga",
    "iso:country":"LV",
    "wof:name":"Krumini",
    "wof:placetype":"locality"
},
  "geometry": {"coordinates":[24.40972,57.85806],"type":"Point"}
}