{
  "type": "Feature",
  "properties": {
    "gn:admin1_code":"A6",
    "gn:admin2_code":"321492.0",
    "gn:asciiname":"Vietalva",
    "gn:country_code":"LV",
    "gn:dem":164,
    "gn:feature_class":"P",
    "gn:feature_code":"PPL",
    "gn:name":"Vietalva",
    "gn:population":0,
    "gn:timezone":"Europe/Riga",
    "iso:country":"LV",
    "name:und_x_variant":[
        "Myza Vietalvas",
        "Vietalva"
    ],
    "wof:name":"Vietalva",
    "wof:placetype":"locality"
},
  "geometry": {"coordinates":[25.7667,56.73695],"type":"Point"}
}