{
  "type": "Feature",
  "properties": {
    "gn:admin1_code":"56",
    "gn:admin2_code":"684948.0",
    "gn:asciiname":"Voiti",
    "gn:country_code":"LV",
    "gn:dem":127,
    "gn:feature_class":"P",
    "gn:feature_code":"PPL",
    "gn:name":"Voiti",
    "gn:population":0,
    "gn:timezone":"Europe/Riga",
    "iso:country":"LV",
    "name:und_x_variant":[
        "Voity",
        "Voiti"
    ],
    "wof:name":"Voiti",
    "wof:placetype":"locality"
},
  "geometry": {"coordinates":[27.85486,56.56104000000001],"type":"Point"}
}