{
  "type": "Feature",
  "properties": {
    "gn:admin1_code":"33",
    "gn:admin2_code":"980284.0",
    "gn:asciiname":"Zuras",
    "gn:cc2":"LV",
    "gn:country_code":"LV",
    "gn:dem":4,
    "gn:feature_class":"P",
    "gn:feature_code":"PPL",
    "gn:name":"Z\u016bras",
    "gn:population":0,
    "gn:timezone":"Europe/Riga",
    "iso:country":"LV",
    "name:fra_x_preferred":[
        "Zuras"
    ],
    "name:ita_x_preferred":[
        "Zuras"
    ],
    "name:und_x_variant":[
        "Myza Zuras",
        "Z\u016bras"
    ],
    "wof:name":"Zuras",
    "wof:placetype":"locality"
},
  "geometry": {"coordinates":[21.60835,57.25653000000001],"type":"Point"}
}