{
  "type": "Feature",
  "properties": {
    "gn:admin1_code":"08",
    "gn:admin2_code":"460272.0",
    "gn:asciiname":"Akacijas",
    "gn:country_code":"LV",
    "gn:dem":26,
    "gn:feature_class":"P",
    "gn:feature_code":"PPL",
    "gn:name":"Ak\u0101cijas",
    "gn:population":0,
    "gn:timezone":"Europe/Riga",
    "iso:country":"LV",
    "name:und_x_variant":[
        "Kolkhoz Lenina",
        "Audze",
        "Audzi\u0146i",
        "Aud\u017ei",
        "Audzu",
        "Audzu Mui\u017ea",
        "Ak\u0101cijas"
    ],
    "wof:name":"Akacijas",
    "wof:placetype":"locality"
},
  "geometry": {"coordinates":[23.4175,56.55222],"type":"Point"}
}