{
  "type": "Feature",
  "properties": {
    "gn:admin1_code":"07",
    "gn:admin2_code":"440274.0",
    "gn:asciiname":"Vilusi",
    "gn:cc2":"LV",
    "gn:country_code":"LV",
    "gn:dem":136,
    "gn:feature_class":"P",
    "gn:feature_code":"PPL",
    "gn:name":"Vilu\u0161i",
    "gn:population":0,
    "gn:timezone":"Europe/Riga",
    "iso:country":"LV",
    "name:bos_x_preferred":[
        "Vilusi"
    ],
    "name:fra_x_preferred":[
        "Vilusi"
    ],
    "name:hrv_x_preferred":[
        "Vilusi"
    ],
    "name:und_x_variant":[
        "Vilyushi",
        "Vilu\u0161i",
        "Vi\u013cu\u0161i"
    ],
    "wof:name":"Vilusi",
    "wof:placetype":"locality"
},
  "geometry": {"coordinates":[26.69927,55.92906],"type":"Point"}
}