{
  "type": "Feature",
  "properties": {
    "gn:admin1_code":"14",
    "gn:asciiname":"Patmalnieki",
    "gn:cc2":"LV",
    "gn:country_code":"LV",
    "gn:dem":215,
    "gn:feature_class":"P",
    "gn:feature_code":"PPL",
    "gn:name":"Patmalnieki",
    "gn:population":0,
    "gn:timezone":"Europe/Riga",
    "iso:country":"LV",
    "name:und_x_variant":[
        "Patma\u013cn\u012bki",
        "Patmalniyeki",
        "Patmalnieki"
    ],
    "wof:name":"Patmalnieki",
    "wof:placetype":"locality"
},
  "geometry": {"coordinates":[27.61328,56.23257],"type":"Point"}
}