{
  "type": "Feature",
  "properties": {
    "gn:admin1_code":"19",
    "gn:admin2_code":"680246.0",
    "gn:asciiname":"Jauna Slobodka",
    "gn:country_code":"LV",
    "gn:dem":133,
    "gn:feature_class":"P",
    "gn:feature_code":"PPL",
    "gn:name":"Jaun\u0101 Slobodka",
    "gn:population":0,
    "gn:timezone":"Europe/Riga",
    "iso:country":"LV",
    "name:und_x_variant":[
        "Slobodka Kozinaya",
        "Kozinaja",
        "Jaunslobodka",
        "Jaun\u0101 Slobodka"
    ],
    "wof:name":"Jauna Slobodka",
    "wof:placetype":"locality"
},
  "geometry": {"coordinates":[28.00246,56.45636],"type":"Point"}
}