{
  "type": "Feature",
  "properties": {
    "gn:admin1_code":"22",
    "gn:admin2_code":"760274.0",
    "gn:asciiname":"Ozolini",
    "gn:country_code":"LV",
    "gn:dem":112,
    "gn:feature_class":"P",
    "gn:feature_code":"PPL",
    "gn:name":"Ozoli\u0146i",
    "gn:population":0,
    "gn:timezone":"Europe/Riga",
    "iso:country":"LV",
    "wof:name":"Ozolini",
    "wof:placetype":"locality"
},
  "geometry": {"coordinates":[26.65948,56.41878000000001],"type":"Point"}
}