{
  "type": "Feature",
  "properties": {
    "gn:admin1_code":"14",
    "gn:admin2_code":"600268.0",
    "gn:asciiname":"Pazauki",
    "gn:cc2":"LV",
    "gn:country_code":"LV",
    "gn:dem":132,
    "gn:feature_class":"P",
    "gn:feature_code":"PPL",
    "gn:name":"Pazauki",
    "gn:population":0,
    "gn:timezone":"Europe/Riga",
    "iso:country":"LV",
    "name:und_x_variant":[
        "Pa\u017eauka",
        "Pozhavka",
        "Pazauki"
    ],
    "wof:name":"Pazauki",
    "wof:placetype":"locality"
},
  "geometry": {"coordinates":[27.35,55.88333000000001],"type":"Point"}
}