{
  "type": "Feature",
  "properties": {
    "gn:admin1_code":"B6",
    "gn:admin2_code":"648552.0",
    "gn:asciiname":"Slamste",
    "gn:cc2":"LV",
    "gn:country_code":"LV",
    "gn:dem":19,
    "gn:feature_class":"P",
    "gn:feature_code":"PPL",
    "gn:name":"Slamste",
    "gn:population":0,
    "gn:timezone":"Europe/Riga",
    "iso:country":"LV",
    "name:und_x_variant":[
        "Slamsti",
        "Slamste"
    ],
    "wof:name":"Slamste",
    "wof:placetype":"locality"
},
  "geometry": {"coordinates":[21.20896,56.32493],"type":"Point"}
}