{
  "type": "Feature",
  "properties": {
    "gn:admin1_code":"37",
    "gn:admin2_code":"649354.0",
    "gn:asciiname":"Sepene",
    "gn:country_code":"LV",
    "gn:dem":103,
    "gn:feature_class":"P",
    "gn:feature_code":"PPL",
    "gn:name":"Sepene",
    "gn:population":0,
    "gn:timezone":"Europe/Riga",
    "iso:country":"LV",
    "name:und_x_variant":[
        "Sepenskrogs",
        "Sepe\u0146i",
        "Sepeneskrogs"
    ],
    "wof:name":"Sepene",
    "wof:placetype":"locality"
},
  "geometry": {"coordinates":[21.72781,56.55916],"type":"Point"}
}