{
  "type": "Feature",
  "properties": {
    "gn:admin1_code":"04",
    "gn:admin2_code":"400292.0",
    "gn:asciiname":"Likverteni",
    "gn:country_code":"LV",
    "gn:dem":30,
    "gn:feature_class":"P",
    "gn:feature_code":"PPL",
    "gn:name":"Likverteni",
    "gn:population":0,
    "gn:timezone":"Europe/Riga",
    "iso:country":"LV",
    "name:und_x_variant":[
        "Bayari",
        "Likverteni"
    ],
    "wof:name":"Likverteni",
    "wof:placetype":"locality"
},
  "geometry": {"coordinates":[24.29644,56.42737],"type":"Point"}
}