{
  "type": "Feature",
  "properties": {
    "gn:admin1_code":"33",
    "gn:admin2_code":"980256.0",
    "gn:asciiname":"Pope",
    "gn:cc2":"LV",
    "gn:country_code":"LV",
    "gn:dem":50,
    "gn:feature_class":"P",
    "gn:feature_code":"PPL",
    "gn:name":"Pope",
    "gn:population":0,
    "gn:timezone":"Europe/Riga",
    "iso:country":"LV",
    "name:und_x_variant":[
        "Myza Pope",
        "Pope"
    ],
    "wof:name":"Pope",
    "wof:placetype":"locality"
},
  "geometry": {"coordinates":[21.85241,57.39799],"type":"Point"}
}