{
  "type": "Feature",
  "properties": {
    "gn:admin1_code":"24",
    "gn:admin2_code":"780246.0",
    "gn:asciiname":"Knutova",
    "gn:country_code":"LV",
    "gn:dem":156,
    "gn:feature_class":"P",
    "gn:feature_code":"PPL",
    "gn:name":"Knutova",
    "gn:population":0,
    "gn:timezone":"Europe/Riga",
    "iso:country":"LV",
    "name:und_x_variant":[
        "Knutava",
        "Knutova"
    ],
    "wof:name":"Knutova",
    "wof:placetype":"locality"
},
  "geometry": {"coordinates":[27.42438,56.42175],"type":"Point"}
}