{
  "type": "Feature",
  "properties": {
    "gn:admin1_code":"22",
    "gn:admin2_code":"760274.0",
    "gn:asciiname":"Paunini",
    "gn:country_code":"LV",
    "gn:dem":106,
    "gn:feature_class":"P",
    "gn:feature_code":"PPL",
    "gn:name":"Pauni\u0146i",
    "gn:population":0,
    "gn:timezone":"Europe/Riga",
    "iso:country":"LV",
    "name:und_x_variant":[
        "Pauni\u0146i",
        "Pauni\u0146as"
    ],
    "wof:name":"Paunini",
    "wof:placetype":"locality"
},
  "geometry": {"coordinates":[26.59037,56.33773000000001],"type":"Point"}
}