{
  "type": "Feature",
  "properties": {
    "gn:admin1_code":"15",
    "gn:admin2_code":"620258.0",
    "gn:asciiname":"Visli",
    "gn:country_code":"LV",
    "gn:dem":93,
    "gn:feature_class":"P",
    "gn:feature_code":"PPL",
    "gn:name":"Vi\u0161\u013ci",
    "gn:population":0,
    "gn:timezone":"Europe/Riga",
    "iso:country":"LV",
    "wof:name":"Visli",
    "wof:placetype":"locality"
},
  "geometry": {"coordinates":[22.48841,57.00786],"type":"Point"}
}