{
  "type": "Feature",
  "properties": {
    "gn:admin1_code":"07",
    "gn:admin2_code":"440268.0",
    "gn:asciiname":"Auksteni",
    "gn:country_code":"LV",
    "gn:dem":94,
    "gn:feature_class":"P",
    "gn:feature_code":"PPLL",
    "gn:name":"Aukste\u0146i",
    "gn:population":0,
    "gn:timezone":"Europe/Riga",
    "iso:country":"LV",
    "name:und_x_variant":[
        "Aukste\u0146i",
        "Auk\u0161tinskaja"
    ],
    "wof:name":"Auksteni",
    "wof:placetype":"locality"
},
  "geometry": {"coordinates":[26.44509,55.9897],"type":"Point"}
}