{
  "type": "Feature",
  "properties": {
    "gn:admin1_code":"19",
    "gn:asciiname":"Naglani",
    "gn:country_code":"LV",
    "gn:dem":107,
    "gn:feature_class":"P",
    "gn:feature_code":"PPL",
    "gn:name":"Nagl\u0101ni",
    "gn:population":0,
    "gn:timezone":"Europe/Riga",
    "iso:country":"LV",
    "wof:name":"Naglani",
    "wof:placetype":"locality"
},
  "geometry": {"coordinates":[27.68503,56.74472],"type":"Point"}
}