{
  "type": "Feature",
  "properties": {
    "gn:admin1_code":"43",
    "gn:admin2_code":"360848.0",
    "gn:asciiname":"Gaujiena",
    "gn:country_code":"LV",
    "gn:dem":84,
    "gn:feature_class":"P",
    "gn:feature_code":"PPL",
    "gn:name":"Gaujiena",
    "gn:population":0,
    "gn:timezone":"Europe/Riga",
    "iso:country":"LV",
    "name:ceb_x_preferred":[
        "Gaujiena"
    ],
    "name:deu_x_preferred":[
        "Gaujiena"
    ],
    "name:eng_x_preferred":[
        "Gaujiena"
    ],
    "name:est_x_preferred":[
        "Koivaliina"
    ],
    "name:fas_x_preferred":[
        "\u06af\u0627\u0648\u06cc\u06cc\u0646\u0627"
    ],
    "name:fra_x_preferred":[
        "Gaujiena"
    ],
    "name:lav_x_preferred":[
        "Gaujiena"
    ],
    "name:pol_x_preferred":[
        "Gaujiena"
    ],
    "name:rus_x_preferred":[
        "\u0413\u0430\u0443\u0446\u0435\u043d\u0430"
    ],
    "name:rus_x_variant":[
        "\u0413\u0430\u0443\u0439\u0438\u0435\u043d\u0430"
    ],
    "name:swe_x_preferred":[
        "Gaujiena"
    ],
    "name:und_x_variant":[
        "Malaya Gauiena"
    ],
    "wof:name":"Gaujiena",
    "wof:placetype":"locality"
},
  "geometry": {"coordinates":[26.40349,57.51422],"type":"Point"}
}