{
  "type": "Feature",
  "properties": {
    "gn:country":"LV",
    "gn:fcode":"PPL",
    "gn:population":454,
    "iso:country":"LV",
    "name:ara_x_preferred":[
        "\u062f\u0648\u0631\u0628\u064a"
    ],
    "name:bel_x_preferred":[
        "\u0414\u0443\u0440\u0431\u044d"
    ],
    "name:bul_x_preferred":[
        "\u0414\u0443\u0440\u0431\u0435"
    ],
    "name:cat_x_preferred":[
        "Durbe"
    ],
    "name:ceb_x_preferred":[
        "Durbe"
    ],
    "name:ces_x_preferred":[
        "Durbe"
    ],
    "name:dan_x_preferred":[
        "Durbe"
    ],
    "name:deu_x_preferred":[
        "Durbe"
    ],
    "name:ell_x_preferred":[
        "\u039d\u03c4\u03bf\u03cd\u03c1\u03bc\u03c0\u03b5"
    ],
    "name:eng_x_preferred":[
        "Durbe"
    ],
    "name:epo_x_preferred":[
        "Durbe"
    ],
    "name:est_x_preferred":[
        "Durbe"
    ],
    "name:fas_x_preferred":[
        "\u062f\u0648\u0631\u0628\u0647\u060c \u0644\u062a\u0648\u0646\u06cc"
    ],
    "name:fas_x_variant":[
        "\u062f\u0648\u0631\u0628\u0647"
    ],
    "name:fin_x_preferred":[
        "Durbe"
    ],
    "name:fra_x_preferred":[
        "Durbe"
    ],
    "name:hsb_x_preferred":[
        "Durbe"
    ],
    "name:hun_x_preferred":[
        "Durbe"
    ],
    "name:hye_x_preferred":[
        "\u0534\u0578\u0582\u0580\u0562\u0565"
    ],
    "name:ita_x_preferred":[
        "Durbe"
    ],
    "name:jpn_x_preferred":[
        "\u30c9\u30a5\u30eb\u30d9"
    ],
    "name:kaz_x_preferred":[
        "\u0414\u0443\u0440\u0431\u0435"
    ],
    "name:lav_x_preferred":[
        "Durbe"
    ],
    "name:lit_x_preferred":[
        "Durb\u0117"
    ],
    "name:mdf_x_preferred":[
        "\u0414\u0443\u0440\u0431\u044d"
    ],
    "name:mkd_x_preferred":[
        "\u0414\u0443\u0440\u0431\u0435"
    ],
    "name:nld_x_preferred":[
        "Durbe"
    ],
    "name:pol_x_preferred":[
        "Durbe"
    ],
    "name:por_x_preferred":[
        "Durbe"
    ],
    "name:rus_x_preferred":[
        "\u0414\u0443\u0440\u0431\u0435"
    ],
    "name:sgs_x_preferred":[
        "Dorb\u0117"
    ],
    "name:smn_x_preferred":[
        "Durbe"
    ],
    "name:spa_x_preferred":[
        "Durbe"
    ],
    "name:swe_x_preferred":[
        "Durbe"
    ],
    "name:ukr_x_preferred":[
        "\u0414\u0443\u0440\u0431\u0435"
    ],
    "name:und_x_variant":[
        "Durben"
    ],
    "name:zho_x_preferred":[
        "\u675c\u723e\u8c9d"
    ],
    "qs_pg:aaroncc":"LV",
    "qs_pg:gn_country":"LV",
    "qs_pg:gn_fcode":"PPL",
    "qs_pg:gn_pop":454,
    "qs_pg:name":"Durbe",
    "qs_pg:photos_9r":0,
    "qs_pg:photos_sr":0,
    "qs_pg:pop_sr":2,
    "qs_pg:qs_pg_placetype":"locality",
    "wof:name":"Durbe",
    "wof:placetype":"locality",
    "wof:population":454
},
  "geometry": {"coordinates":[21.36978,56.5887],"type":"Point"}
}