{
  "type": "Feature",
  "properties": {
    "gn:gn_country":"LV",
    "gn:gn_fcode":"PPL",
    "gn:gn_pop":454,
    "gn:population":454,
    "iso:country":"LV",
    "name:ara_x_preferred":[
        "\u062f\u0648\u0631\u0628\u064a"
    ],
    "name:bul_x_preferred":[
        "\u0414\u0443\u0440\u0431\u0435"
    ],
    "name:cat_x_preferred":[
        "Durbe"
    ],
    "name:chi_x_preferred":[
        "\u675c\u723e\u8c9d"
    ],
    "name:cze_x_preferred":[
        "Durbe"
    ],
    "name:dan_x_preferred":[
        "Durbe"
    ],
    "name:dut_x_preferred":[
        "Durbe"
    ],
    "name:eng_x_preferred":[
        "Durbe"
    ],
    "name:est_x_preferred":[
        "Durbe"
    ],
    "name:fin_x_preferred":[
        "Durbe"
    ],
    "name:fre_x_preferred":[
        "Durbe"
    ],
    "name:ger_x_preferred":[
        "Durbe"
    ],
    "name:hun_x_preferred":[
        "Durbe"
    ],
    "name:ita_x_preferred":[
        "Durbe"
    ],
    "name:kaz_x_preferred":[
        "\u0414\u0443\u0440\u0431\u0435"
    ],
    "name:lav_x_preferred":[
        "Durbe"
    ],
    "name:lit_x_preferred":[
        "Durb\u0117"
    ],
    "name:per_x_preferred":[
        "\u062f\u0648\u0631\u0628\u0647\u060c \u0644\u062a\u0648\u0646\u06cc"
    ],
    "name:pol_x_preferred":[
        "Durbe"
    ],
    "name:por_x_preferred":[
        "Durbe"
    ],
    "name:rus_x_preferred":[
        "\u0414\u0443\u0440\u0431\u0435"
    ],
    "name:sgs_x_preferred":[
        "Dorb\u0117"
    ],
    "name:spa_x_preferred":[
        "Durbe"
    ],
    "name:swe_x_preferred":[
        "Durbe"
    ],
    "name:ukr_x_preferred":[
        "\u0414\u0443\u0440\u0431\u0435"
    ],
    "name:unk_x_variant":[
        "Durben"
    ],
    "qs_pg:aaroncc":"LV",
    "qs_pg:gn_country":"LV",
    "qs_pg:gn_fcode":"PPL",
    "qs_pg:gn_pop":454,
    "qs_pg:name":"Durbe",
    "qs_pg:photos_9r":0,
    "qs_pg:photos_sr":0,
    "qs_pg:pop_sr":2,
    "qs_pg:qs_pg_placetype":"locality",
    "wof:name":"Durbe",
    "wof:placetype":"locality",
    "wof:population":454
},
  "geometry": {"coordinates":[21.36978,56.5887],"type":"Point"}
}