{
  "type": "Feature",
  "properties": {
    "gn:admin1_code":"15",
    "gn:admin2_code":"620280.0",
    "gn:asciiname":"Priednieki",
    "gn:country_code":"LV",
    "gn:dem":56,
    "gn:feature_class":"P",
    "gn:feature_code":"PPL",
    "gn:name":"Priednieki",
    "gn:population":0,
    "gn:timezone":"Europe/Riga",
    "iso:country":"LV",
    "wof:name":"Priednieki",
    "wof:placetype":"locality"
},
  "geometry": {"coordinates":[22.31118,57.08974],"type":"Point"}
}