{
  "type": "Feature",
  "properties": {
    "gn:admin1_code":"27",
    "gn:admin2_code":"840270.0",
    "gn:asciiname":"Alsi",
    "gn:cc2":"LV",
    "gn:country_code":"LV",
    "gn:dem":70,
    "gn:feature_class":"P",
    "gn:feature_code":"PPL",
    "gn:name":"Al\u0161i",
    "gn:population":0,
    "gn:timezone":"Europe/Riga",
    "iso:country":"LV",
    "name:und_x_variant":[
        "Alshi",
        "Al\u0161i"
    ],
    "wof:name":"Alsi",
    "wof:placetype":"locality"
},
  "geometry": {"coordinates":[22.06231,56.49614],"type":"Point"}
}