{
  "type": "Feature",
  "properties": {
    "gn:admin1_code":"27",
    "gn:admin2_code":"840272.0",
    "gn:asciiname":"Korsi",
    "gn:cc2":"LV",
    "gn:country_code":"LV",
    "gn:dem":113,
    "gn:feature_class":"P",
    "gn:feature_code":"PPL",
    "gn:name":"Kor\u0161i",
    "gn:population":0,
    "gn:timezone":"Europe/Riga",
    "iso:country":"LV",
    "name:lav_x_preferred":[
        "Kur\u0161i"
    ],
    "name:und_x_variant":[
        "Korshi",
        "Kor\u0161i"
    ],
    "wof:name":"Korsi",
    "wof:placetype":"locality"
},
  "geometry": {"coordinates":[22.51021,56.64108],"type":"Point"}
}