{
  "type": "Feature",
  "properties": {
    "gn:admin1_code":"33",
    "gn:admin2_code":"980270.0",
    "gn:asciiname":"Veckuski",
    "gn:country_code":"LV",
    "gn:dem":59,
    "gn:feature_class":"P",
    "gn:feature_code":"PPL",
    "gn:name":"Vecku\u0161\u0137i",
    "gn:population":0,
    "gn:timezone":"Europe/Riga",
    "iso:country":"LV",
    "wof:name":"Veckuski",
    "wof:placetype":"locality"
},
  "geometry": {"coordinates":[22.03863,57.21934],"type":"Point"}
}