{
  "type": "Feature",
  "properties": {
    "gn:admin1_code":"70",
    "gn:admin2_code":"801864.0",
    "gn:asciiname":"Straujupes",
    "gn:country_code":"LV",
    "gn:dem":27,
    "gn:feature_class":"P",
    "gn:feature_code":"PPL",
    "gn:name":"Straujupes",
    "gn:population":0,
    "gn:timezone":"Europe/Riga",
    "iso:country":"LV",
    "name:und_x_variant":[
        "Strauyupes",
        "Straujupes"
    ],
    "wof:name":"Straujupes",
    "wof:placetype":"locality"
},
  "geometry": {"coordinates":[24.5725,57.08833000000001],"type":"Point"}
}