{
  "type": "Feature",
  "properties": {
    "gn:admin1_code":"56",
    "gn:admin2_code":"684944.0",
    "gn:asciiname":"Ierzelova",
    "gn:country_code":"LV",
    "gn:dem":134,
    "gn:feature_class":"P",
    "gn:feature_code":"PPL",
    "gn:name":"Ierze\u013cova",
    "gn:population":0,
    "gn:timezone":"Europe/Riga",
    "iso:country":"LV",
    "name:und_x_variant":[
        "Ierze\u013cova",
        "Kausakalmi"
    ],
    "wof:name":"Ierzelova",
    "wof:placetype":"locality"
},
  "geometry": {"coordinates":[27.78662000000001,56.60213],"type":"Point"}
}