{
  "type": "Feature",
  "properties": {
    "gn:admin1_code":"44",
    "gn:admin2_code":"460825.0",
    "gn:asciiname":"Strikeles",
    "gn:country_code":"LV",
    "gn:dem":95,
    "gn:feature_class":"P",
    "gn:feature_code":"PPL",
    "gn:name":"Strikeles",
    "gn:population":0,
    "gn:timezone":"Europe/Riga",
    "iso:country":"LV",
    "wof:name":"Strikeles",
    "wof:placetype":"locality"
},
  "geometry": {"coordinates":[22.95,56.48333],"type":"Point"}
}