{
  "type": "Feature",
  "properties": {
    "gn:admin1_code":"47",
    "gn:admin2_code":"384400.0",
    "gn:asciiname":"Punculova",
    "gn:country_code":"LV",
    "gn:dem":103,
    "gn:feature_class":"P",
    "gn:feature_code":"PPL",
    "gn:name":"Puncu\u013cova",
    "gn:population":0,
    "gn:timezone":"Europe/Riga",
    "iso:country":"LV",
    "name:und_x_variant":[
        "Puncu\u013cova",
        "Puncu\u013ceva"
    ],
    "wof:name":"Punculova",
    "wof:placetype":"locality"
},
  "geometry": {"coordinates":[27.62708,56.90156999999999],"type":"Point"}
}