{
  "type": "Feature",
  "properties": {
    "gn:admin1_code":"03",
    "gn:admin2_code":"380250.0",
    "gn:asciiname":"Augstori",
    "gn:country_code":"LV",
    "gn:dem":95,
    "gn:feature_class":"P",
    "gn:feature_code":"PPL",
    "gn:name":"Augstori",
    "gn:population":0,
    "gn:timezone":"Europe/Riga",
    "iso:country":"LV",
    "name:und_x_variant":[
        "Augstari"
    ],
    "wof:name":"Augstori",
    "wof:placetype":"locality"
},
  "geometry": {"coordinates":[27.06896,56.86314],"type":"Point"}
}