{
  "type": "Feature",
  "properties": {
    "gn:admin1_code":"27",
    "gn:admin2_code":"840296.0",
    "gn:asciiname":"Buki",
    "gn:country_code":"LV",
    "gn:dem":89,
    "gn:feature_class":"P",
    "gn:feature_code":"PPL",
    "gn:name":"Buki",
    "gn:population":0,
    "gn:timezone":"Europe/Riga",
    "iso:country":"LV",
    "wof:name":"Buki",
    "wof:placetype":"locality"
},
  "geometry": {"coordinates":[22.33333,56.65],"type":"Point"}
}