{
  "type": "Feature",
  "properties": {
    "gn:admin1_code":"27",
    "gn:admin2_code":"840296.0",
    "gn:asciiname":"Kupinas",
    "gn:country_code":"LV",
    "gn:dem":90,
    "gn:feature_class":"P",
    "gn:feature_code":"PPL",
    "gn:name":"K\u016bpi\u0146as",
    "gn:population":0,
    "gn:timezone":"Europe/Riga",
    "iso:country":"LV",
    "wof:name":"Kupinas",
    "wof:placetype":"locality"
},
  "geometry": {"coordinates":[22.31667,56.65],"type":"Point"}
}