{
  "type": "Feature",
  "properties": {
    "gn:admin1_code":"57",
    "gn:admin2_code":"601044.0",
    "gn:asciiname":"Krauli",
    "gn:country_code":"LV",
    "gn:dem":204,
    "gn:feature_class":"P",
    "gn:feature_code":"PPL",
    "gn:name":"Krau\u013ci",
    "gn:population":0,
    "gn:timezone":"Europe/Riga",
    "iso:country":"LV",
    "name:und_x_variant":[
        "Krau\u013ci",
        "Krauk\u013ci"
    ],
    "wof:name":"Krauli",
    "wof:placetype":"locality"
},
  "geometry": {"coordinates":[27.48728,56.16662],"type":"Point"}
}