{
  "type": "Feature",
  "properties": {
    "gn:admin1_code":"07",
    "gn:admin2_code":"440274.0",
    "gn:asciiname":"Krivani",
    "gn:country_code":"LV",
    "gn:dem":120,
    "gn:feature_class":"P",
    "gn:feature_code":"PPL",
    "gn:name":"Kr\u012bv\u0101ni",
    "gn:population":0,
    "gn:timezone":"Europe/Riga",
    "iso:country":"LV",
    "name:und_x_variant":[
        "Krivany",
        "Kriev\u0101ni",
        "Kr\u012bv\u0101ni"
    ],
    "wof:name":"Krivani",
    "wof:placetype":"locality"
},
  "geometry": {"coordinates":[26.66524,55.96023],"type":"Point"}
}