{
  "type": "Feature",
  "properties": {
    "gn:admin1_code":"07",
    "gn:admin2_code":"440294.0",
    "gn:asciiname":"Suti",
    "gn:country_code":"LV",
    "gn:dem":105,
    "gn:feature_class":"P",
    "gn:feature_code":"PPL",
    "gn:name":"\u0160uti",
    "gn:population":0,
    "gn:timezone":"Europe/Riga",
    "iso:country":"LV",
    "name:und_x_variant":[
        "Shuty",
        "\u0160uti"
    ],
    "wof:name":"Suti",
    "wof:placetype":"locality"
},
  "geometry": {"coordinates":[26.50981,56.0169],"type":"Point"}
}