{
  "type": "Feature",
  "properties": {
    "gn:admin1_code":"12",
    "gn:admin2_code":"540248.0",
    "gn:asciiname":"Daumanti",
    "gn:cc2":"LV",
    "gn:country_code":"LV",
    "gn:dem":35,
    "gn:feature_class":"P",
    "gn:feature_code":"PPL",
    "gn:name":"Daumanti",
    "gn:population":0,
    "gn:timezone":"Europe/Riga",
    "iso:country":"LV",
    "name:und_x_variant":[
        "Volf\u0101rte",
        "Dumanti",
        "Volf\u0101rti",
        "Daumanti"
    ],
    "wof:name":"Daumanti",
    "wof:placetype":"locality"
},
  "geometry": {"coordinates":[23.69704,56.39277],"type":"Point"}
}