{
  "type": "Feature",
  "properties": {
    "gn:admin1_code":"87",
    "gn:admin2_code":"741433.0",
    "gn:asciiname":"Kaibala",
    "gn:country_code":"LV",
    "gn:dem":54,
    "gn:feature_class":"P",
    "gn:feature_code":"PPL",
    "gn:name":"Kaibala",
    "gn:population":0,
    "gn:timezone":"Europe/Riga",
    "iso:country":"LV",
    "name:und_x_variant":[
        "Kaybala",
        "Kaibele",
        "Kaibala"
    ],
    "wof:name":"Kaibala",
    "wof:placetype":"locality"
},
  "geometry": {"coordinates":[24.87433,56.70184],"type":"Point"}
}