{
  "type": "Feature",
  "properties": {
    "gn:admin1_code":"E2",
    "gn:admin2_code":"769194.0",
    "gn:asciiname":"Dovale",
    "gn:country_code":"LV",
    "gn:dem":116,
    "gn:feature_class":"P",
    "gn:feature_code":"PPL",
    "gn:name":"Dovale",
    "gn:population":0,
    "gn:timezone":"Europe/Riga",
    "iso:country":"LV",
    "name:und_x_variant":[
        "Dovule",
        "Dovole",
        "Dovale"
    ],
    "wof:name":"Dovale",
    "wof:placetype":"locality"
},
  "geometry": {"coordinates":[26.66925,56.22816],"type":"Point"}
}