{
  "type": "Feature",
  "properties": {
    "gn:admin1_code":"34",
    "gn:admin2_code":"804400.0",
    "gn:asciiname":"Atari",
    "gn:country_code":"LV",
    "gn:dem":8,
    "gn:feature_class":"P",
    "gn:feature_code":"PPL",
    "gn:name":"Atari",
    "gn:population":0,
    "gn:timezone":"Europe/Riga",
    "iso:country":"LV",
    "name:est_x_preferred":[
        "Atari k\u00fcla"
    ],
    "name:lav_x_preferred":[
        "Atari"
    ],
    "name:pol_x_preferred":[
        "Atari"
    ],
    "name:und_x_variant":[
        "Polumyza Attari",
        "Attaru Pusmui\u017ea Centrs",
        "Attari Pusmui\u017eas Centrs",
        "Attari",
        "Atary"
    ],
    "wof:name":"Atari",
    "wof:placetype":"locality"
},
  "geometry": {"coordinates":[24.2705,57.06791],"type":"Point"}
}