{
  "type": "Feature",
  "properties": {
    "gn:admin1_code":"E1",
    "gn:admin2_code":"701894.0",
    "gn:asciiname":"Mazie Leimani",
    "gn:country_code":"LV",
    "gn:dem":104,
    "gn:feature_class":"P",
    "gn:feature_code":"PPL",
    "gn:name":"Mazie Leima\u0146i",
    "gn:population":0,
    "gn:timezone":"Europe/Riga",
    "iso:country":"LV",
    "name:und_x_variant":[
        "Mazie Leima\u0146i",
        "Leima\u0146i"
    ],
    "wof:name":"Mazie Leimani",
    "wof:placetype":"locality"
},
  "geometry": {"coordinates":[26.64776,56.58951],"type":"Point"}
}