{
  "type": "Feature",
  "properties": {
    "gn:admin1_code":"10",
    "gn:asciiname":"Mezarasas",
    "gn:country_code":"LV",
    "gn:dem":91,
    "gn:feature_class":"P",
    "gn:feature_code":"PPL",
    "gn:name":"Me\u017earasas",
    "gn:population":0,
    "gn:timezone":"Europe/Riga",
    "iso:country":"LV",
    "wof:name":"Mezarasas",
    "wof:placetype":"locality"
},
  "geometry": {"coordinates":[26.17012,56.50079],"type":"Point"}
}