{
  "type": "Feature",
  "properties": {
    "gn:admin1_code":"E7",
    "gn:admin2_code":"381682.0",
    "gn:asciiname":"Bakarova",
    "gn:country_code":"LV",
    "gn:dem":83,
    "gn:feature_class":"P",
    "gn:feature_code":"PPL",
    "gn:name":"B\u0101karova",
    "gn:population":0,
    "gn:timezone":"Europe/Riga",
    "iso:country":"LV",
    "name:und_x_variant":[
        "B\u0101karova",
        "Bahareva"
    ],
    "wof:name":"Bakarova",
    "wof:placetype":"locality"
},
  "geometry": {"coordinates":[27.73697,57.0709],"type":"Point"}
}