{
  "type": "Feature",
  "properties": {
    "gn:admin1_code":"24",
    "gn:admin2_code":"780284.0",
    "gn:asciiname":"Zalmuiza",
    "gn:country_code":"LV",
    "gn:dem":120,
    "gn:feature_class":"P",
    "gn:feature_code":"PPL",
    "gn:name":"Za\u013cmui\u017ea",
    "gn:population":0,
    "gn:timezone":"Europe/Riga",
    "iso:country":"LV",
    "name:und_x_variant":[
        "Myza Zal\u2019muyzha",
        "Za\u013cmui\u017ea"
    ],
    "wof:name":"Zalmuiza",
    "wof:placetype":"locality"
},
  "geometry": {"coordinates":[27.38617,56.73441],"type":"Point"}
}