{
  "type": "Feature",
  "properties": {
    "iso:country":"LV",
    "name:lav_x_preferred":[
        "M\u016bkupurvs"
    ],
    "wof:name":"Mukupurvs",
    "wof:placetype":"neighbourhood"
},
  "geometry": {"coordinates":[23.98921232014214,56.93736758066431],"type":"Point"}
}