{
  "type": "Feature",
  "properties": {
    "gn:admin1_code":"29",
    "gn:admin2_code":"900284.0",
    "gn:asciiname":"Ezerkauki",
    "gn:country_code":"LV",
    "gn:dem":64,
    "gn:feature_class":"P",
    "gn:feature_code":"PPL",
    "gn:name":"Ezerkau\u0137i",
    "gn:population":0,
    "gn:timezone":"Europe/Riga",
    "iso:country":"LV",
    "wof:name":"Ezerkauki",
    "wof:placetype":"locality"
},
  "geometry": {"coordinates":[23.13595,56.99308000000001],"type":"Point"}
}