{
  "type": "Feature",
  "properties": {
    "gn:admin1_code":"28",
    "gn:admin2_code":"880246.0",
    "gn:asciiname":"Raudzini",
    "gn:country_code":"LV",
    "gn:dem":38,
    "gn:feature_class":"P",
    "gn:feature_code":"PPL",
    "gn:name":"Raudzi\u0146i",
    "gn:population":0,
    "gn:timezone":"Europe/Riga",
    "iso:country":"LV",
    "wof:name":"Raudzini",
    "wof:placetype":"locality"
},
  "geometry": {"coordinates":[22.86073,57.20483],"type":"Point"}
}