{
  "type": "Feature",
  "properties": {
    "gn:admin1_code":"14",
    "gn:asciiname":"Lukseva",
    "gn:cc2":"LV",
    "gn:country_code":"LV",
    "gn:dem":147,
    "gn:feature_class":"P",
    "gn:feature_code":"PPL",
    "gn:name":"Luk\u0161eva",
    "gn:population":0,
    "gn:timezone":"Europe/Riga",
    "iso:country":"LV",
    "name:und_x_variant":[
        "Luksheva",
        "Luk\u0161eva"
    ],
    "wof:name":"Lukseva",
    "wof:placetype":"locality"
},
  "geometry": {"coordinates":[27.76477,56.02367],"type":"Point"}
}