{
  "type": "Feature",
  "properties": {
    "gn:admin1_code":"77",
    "gn:admin2_code":"901288.0",
    "gn:asciiname":"Varieba",
    "gn:country_code":"LV",
    "gn:dem":95,
    "gn:feature_class":"P",
    "gn:feature_code":"PPL",
    "gn:name":"Varieba",
    "gn:population":0,
    "gn:timezone":"Europe/Riga",
    "iso:country":"LV",
    "name:und_x_variant":[
        "Variebas Mui\u017ea",
        "Var\u2019yeba",
        "Varieba"
    ],
    "wof:name":"Varieba",
    "wof:placetype":"locality"
},
  "geometry": {"coordinates":[22.57859,56.86652],"type":"Point"}
}