{
  "type": "Feature",
  "properties": {
    "gn:admin1_code":"29",
    "gn:asciiname":"Puces",
    "gn:country_code":"LV",
    "gn:dem":76,
    "gn:feature_class":"P",
    "gn:feature_code":"PPL",
    "gn:name":"P\u016bces",
    "gn:population":0,
    "gn:timezone":"Europe/Riga",
    "iso:country":"LV",
    "wof:name":"Puces",
    "wof:placetype":"locality"
},
  "geometry": {"coordinates":[22.61724,56.96126],"type":"Point"}
}