{
  "type": "Feature",
  "properties": {
    "gn:admin1_code":"22",
    "gn:asciiname":"Rusini",
    "gn:country_code":"LV",
    "gn:dem":98,
    "gn:feature_class":"P",
    "gn:feature_code":"PPL",
    "gn:name":"R\u016bsi\u0146i",
    "gn:population":0,
    "gn:timezone":"Europe/Riga",
    "iso:country":"LV",
    "name:und_x_variant":[
        "Rusina",
        "R\u016bsi\u0146i"
    ],
    "wof:name":"Rusini",
    "wof:placetype":"locality"
},
  "geometry": {"coordinates":[26.38487000000001,56.36929],"type":"Point"}
}