{
  "type": "Feature",
  "properties": {
    "iso:country":"LV",
    "name:eng_x_preferred":[
        "Pociems"
    ],
    "name:rus_x_preferred":[
        "\u041f\u043e\u0446\u0438\u0435\u043c\u0441"
    ],
    "name:und_x_variant":[
        "Aplokciems",
        "Pociema Mui\u017ea"
    ],
    "qs:gn_adm0_cc":"LV",
    "qs:gn_fcode":"PPL",
    "qs:gn_local":456172,
    "qs:gn_namadm1":"18",
    "qs:gn_name":"Pociems",
    "qs:local_max":23404,
    "qs:local_sum":42602,
    "qs:localhoods":31,
    "qs:name":"Aplokciems",
    "qs:name_adm0":"Latvija",
    "qs:name_adm1":"R\u013cga",
    "qs:name_adm2":"R\u013cga",
    "qs:name_local":"R\u012bga",
    "qs:photo_max":19,
    "qs:photo_sum":58,
    "qs:placetype":"Suburb",
    "qs:quad_count":16,
    "qs:woe_adm0":23424874,
    "qs:woe_adm1":20070121,
    "qs:woe_adm2":55844479,
    "qs:woe_funk":"Grouping neighborhood",
    "qs:woe_lau":0,
    "qs:woe_local":854823,
    "qs:woe_ver":"7.10.0",
    "wof:lang":[
        "unk"
    ],
    "wof:name":"Aplokciems",
    "wof:placetype":"neighbourhood"
},
  "geometry": {"coordinates":[24.144781,57.023166],"type":"Point"}
}