{
  "type": "Feature",
  "properties": {
    "gn:admin1_code":"B9",
    "gn:admin2_code":"407796.0",
    "gn:asciiname":"Galzemji",
    "gn:country_code":"LV",
    "gn:dem":30,
    "gn:feature_class":"P",
    "gn:feature_code":"PPL",
    "gn:name":"Galzemji",
    "gn:population":0,
    "gn:timezone":"Europe/Riga",
    "iso:country":"LV",
    "name:und_x_variant":[
        "Galzem\u2019i",
        "Galzemji"
    ],
    "wof:name":"Galzemji",
    "wof:placetype":"locality"
},
  "geometry": {"coordinates":[23.95506,56.43775],"type":"Point"}
}