{
  "type": "Feature",
  "properties": {
    "gn:admin1_code":"10",
    "gn:asciiname":"Teili",
    "gn:country_code":"LV",
    "gn:dem":124,
    "gn:feature_class":"P",
    "gn:feature_code":"PPL",
    "gn:name":"Tei\u013ci",
    "gn:population":0,
    "gn:timezone":"Europe/Riga",
    "iso:country":"LV",
    "wof:name":"Teili",
    "wof:placetype":"locality"
},
  "geometry": {"coordinates":[26.03846,56.49974],"type":"Point"}
}