{
  "type": "Feature",
  "properties": {
    "gn:admin1_code":"E3",
    "gn:admin2_code":"429350.0",
    "gn:asciiname":"Klekeri",
    "gn:country_code":"LV",
    "gn:dem":237,
    "gn:feature_class":"P",
    "gn:feature_code":"PPL",
    "gn:name":"Kle\u0137eri",
    "gn:population":0,
    "gn:timezone":"Europe/Riga",
    "iso:country":"LV",
    "name:und_x_variant":[
        "Kleteri",
        "Kle\u0137eri"
    ],
    "wof:name":"Klekeri",
    "wof:placetype":"locality"
},
  "geometry": {"coordinates":[25.584,57.22253000000001],"type":"Point"}
}