{
  "type": "Feature",
  "properties": {
    "gn:admin1_code":"30",
    "gn:admin2_code":"940296.0",
    "gn:asciiname":"Mierkalns",
    "gn:country_code":"LV",
    "gn:dem":71,
    "gn:feature_class":"P",
    "gn:feature_code":"PPL",
    "gn:name":"Mierkalns",
    "gn:population":0,
    "gn:timezone":"Europe/Riga",
    "iso:country":"LV",
    "wof:name":"Mierkalns",
    "wof:placetype":"locality"
},
  "geometry": {"coordinates":[26.206,57.56451],"type":"Point"}
}