{
  "type": "Feature",
  "properties": {
    "gn:admin1_code":"38",
    "gn:admin2_code":"560825.0",
    "gn:asciiname":"Krankali",
    "gn:country_code":"LV",
    "gn:dem":104,
    "gn:feature_class":"P",
    "gn:feature_code":"PPL",
    "gn:name":"Kranka\u013ci",
    "gn:population":0,
    "gn:timezone":"Europe/Riga",
    "iso:country":"LV",
    "name:und_x_variant":[
        "Krankale",
        "Kranka\u013ci"
    ],
    "wof:name":"Krankali",
    "wof:placetype":"locality"
},
  "geometry": {"coordinates":[25.67986,56.16682],"type":"Point"}
}