{
  "type": "Feature",
  "properties": {
    "gn:admin1_code":"79",
    "gn:admin2_code":"741044.0",
    "gn:asciiname":"Lacplesis",
    "gn:country_code":"LV",
    "gn:dem":53,
    "gn:feature_class":"P",
    "gn:feature_code":"PPL",
    "gn:name":"L\u0101\u010dpl\u0113sis",
    "gn:population":0,
    "gn:timezone":"Europe/Riga",
    "iso:country":"LV",
    "name:und_x_variant":[
        "Lachplesis",
        "L\u0101\u010dpl\u0113sis"
    ],
    "wof:name":"Lacplesis",
    "wof:placetype":"locality"
},
  "geometry": {"coordinates":[24.79647000000001,56.57587],"type":"Point"}
}