{
  "type": "Feature",
  "properties": {
    "gn:admin1_code":"12",
    "gn:admin2_code":"540292.0",
    "gn:asciiname":"Oglaine",
    "gn:country_code":"LV",
    "gn:dem":19,
    "gn:feature_class":"P",
    "gn:feature_code":"PPL",
    "gn:name":"Oglaine",
    "gn:population":0,
    "gn:timezone":"Europe/Riga",
    "iso:country":"LV",
    "name:und_x_variant":[
        "Oglaines Mui\u017ea",
        "Oglayne",
        "Oglaine"
    ],
    "wof:name":"Oglaine",
    "wof:placetype":"locality"
},
  "geometry": {"coordinates":[23.82439,56.49172],"type":"Point"}
}