{
  "type": "Feature",
  "properties": {
    "gn:admin1_code":"07",
    "gn:admin2_code":"440250.0",
    "gn:asciiname":"Brigene",
    "gn:country_code":"LV",
    "gn:dem":155,
    "gn:feature_class":"P",
    "gn:feature_code":"PPL",
    "gn:name":"Bri\u0123ene",
    "gn:population":0,
    "gn:timezone":"Europe/Riga",
    "iso:country":"LV",
    "name:und_x_variant":[
        "Brigas Mui\u017ea",
        "Bri\u0123ene"
    ],
    "wof:name":"Brigene",
    "wof:placetype":"locality"
},
  "geometry": {"coordinates":[26.54984,55.74444],"type":"Point"}
}