{
  "type": "Feature",
  "properties": {
    "gn:admin1_code":"16",
    "gn:asciiname":"Skede",
    "gn:country_code":"LV",
    "gn:dem":123,
    "gn:feature_class":"P",
    "gn:feature_code":"PPL",
    "gn:name":"Skede",
    "gn:population":0,
    "gn:timezone":"Europe/Riga",
    "iso:country":"LV",
    "name:fra_x_preferred":[
        "\u0160\u0137\u0113de"
    ],
    "name:lav_x_preferred":[
        "\u0160\u0137\u0113de"
    ],
    "name:swe_x_preferred":[
        "\u0160\u0137\u0113de"
    ],
    "wof:name":"Skede",
    "wof:placetype":"locality"
},
  "geometry": {"coordinates":[21.751,56.6021],"type":"Point"}
}