{
  "type": "Feature",
  "properties": {
    "gn:admin1_code":"60",
    "gn:admin2_code":"885150.0",
    "gn:asciiname":"Dukas",
    "gn:country_code":"LV",
    "gn:dem":88,
    "gn:feature_class":"P",
    "gn:feature_code":"PPL",
    "gn:name":"D\u016bkas",
    "gn:population":0,
    "gn:timezone":"Europe/Riga",
    "iso:country":"LV",
    "wof:name":"Dukas",
    "wof:placetype":"locality"
},
  "geometry": {"coordinates":[22.35,57.58333],"type":"Point"}
}