{
  "type": "Feature",
  "properties": {
    "gn:admin1_code":"24",
    "gn:admin2_code":"780252.0",
    "gn:asciiname":"Ezergailisi",
    "gn:country_code":"LV",
    "gn:dem":155,
    "gn:feature_class":"P",
    "gn:feature_code":"PPL",
    "gn:name":"Ezergail\u012b\u0161i",
    "gn:population":0,
    "gn:timezone":"Europe/Riga",
    "iso:country":"LV",
    "name:und_x_variant":[
        "Ezergail\u012b\u0161i",
        "Azara Gailei\u0161i"
    ],
    "wof:name":"Ezergailisi",
    "wof:placetype":"locality"
},
  "geometry": {"coordinates":[27.02975,56.28438000000001],"type":"Point"}
}