{
  "type": "Feature",
  "properties": {
    "gn:admin1_code":"C9",
    "gn:admin2_code":"621229.0",
    "gn:asciiname":"Ikaisi",
    "gn:country_code":"LV",
    "gn:dem":39,
    "gn:feature_class":"P",
    "gn:feature_code":"PPL",
    "gn:name":"Ikai\u0161i",
    "gn:population":0,
    "gn:timezone":"Europe/Riga",
    "iso:country":"LV",
    "wof:name":"Ikaisi",
    "wof:placetype":"locality"
},
  "geometry": {"coordinates":[22.01709,56.79076],"type":"Point"}
}