{
  "type": "Feature",
  "properties": {
    "gn:admin1_code":"30",
    "gn:asciiname":"Zuldinas",
    "gn:country_code":"LV",
    "gn:dem":72,
    "gn:feature_class":"P",
    "gn:feature_code":"PPL",
    "gn:name":"\u017duldi\u0146as",
    "gn:population":0,
    "gn:timezone":"Europe/Riga",
    "iso:country":"LV",
    "name:und_x_variant":[
        "Zhuldini",
        "\u017duldi\u0146u",
        "\u017duldi\u0146i",
        "\u017duldi\u0146as"
    ],
    "wof:name":"Zuldinas",
    "wof:placetype":"locality"
},
  "geometry": {"coordinates":[26.14211,57.73363000000001],"type":"Point"}
}