{
  "type": "Feature",
  "properties": {
    "gn:admin1_code":"E7",
    "gn:admin2_code":"381670.0",
    "gn:asciiname":"Skandine",
    "gn:country_code":"LV",
    "gn:dem":112,
    "gn:feature_class":"P",
    "gn:feature_code":"PPL",
    "gn:name":"Skand\u012bne",
    "gn:population":0,
    "gn:timezone":"Europe/Riga",
    "iso:country":"LV",
    "name:und_x_variant":[
        "Skan\u0123ina",
        "Skandina",
        "Skand\u012bne"
    ],
    "wof:name":"Skandine",
    "wof:placetype":"locality"
},
  "geometry": {"coordinates":[27.61585,57.14925],"type":"Point"}
}