{
  "type": "Feature",
  "properties": {
    "iso:country":"LV",
    "name:eng_x_preferred":[
        "Lociki"
    ],
    "name:est_x_preferred":[
        "Lociki"
    ],
    "name:lav_x_preferred":[
        "Lociki"
    ],
    "name:lit_x_preferred":[
        "Locikiai"
    ],
    "name:lit_x_variant":[
        "Luocikiai"
    ],
    "name:nld_x_preferred":[
        "Lociki"
    ],
    "name:unk_x_variant":[
        "Lotsiki"
    ],
    "qs:a0":"Latvija",
    "qs:a1":"*Daugavpils novads",
    "qs:a1r":"0",
    "qs:adm0":"Latvija",
    "qs:la_lc":"*",
    "qs:level":"locality",
    "qs:loc":"Lociki",
    "qs:loc_alt":"Lociki",
    "qs:pop":0,
    "qs:type":"buffered point",
    "wd:population":1320,
    "wd:wordcount":167,
    "wof:name":"Lociki",
    "wof:placetype":"locality",
    "wof:population":1320
},
  "geometry": {"coordinates":[26.643507,55.936745],"type":"Point"}
}