{
  "type": "Feature",
  "properties": {
    "gn:admin1_code":"29",
    "gn:admin2_code":"900248.0",
    "gn:asciiname":"Macitajmuiza",
    "gn:country_code":"LV",
    "gn:dem":47,
    "gn:feature_class":"P",
    "gn:feature_code":"PPL",
    "gn:name":"M\u0101c\u012bt\u0101jmui\u017ea",
    "gn:population":0,
    "gn:timezone":"Europe/Riga",
    "iso:country":"LV",
    "name:und_x_variant":[
        "Berze",
        "M\u0101c\u012bt\u0101jmui\u017ea"
    ],
    "wof:name":"Macitajmuiza",
    "wof:placetype":"locality"
},
  "geometry": {"coordinates":[23.22267,56.78521],"type":"Point"}
}