{
  "type": "Feature",
  "properties": {
    "gn:admin1_code":"08",
    "gn:admin2_code":"460260.0",
    "gn:asciiname":"Bitenieki",
    "gn:country_code":"LV",
    "gn:dem":70,
    "gn:feature_class":"P",
    "gn:feature_code":"PPL",
    "gn:name":"Bitenieki",
    "gn:population":0,
    "gn:timezone":"Europe/Riga",
    "iso:country":"LV",
    "name:lav_x_preferred":[
        "Bitenieki"
    ],
    "name:und_x_variant":[
        "Besberty",
        "Jaun\u0101s M\u0101jas"
    ],
    "wof:name":"Bitenieki",
    "wof:placetype":"locality"
},
  "geometry": {"coordinates":[23.25504,56.67019000000001],"type":"Point"}
}