{
  "type": "Feature",
  "properties": {
    "gn:admin1_code":"09",
    "gn:admin2_code":"500276.0",
    "gn:asciiname":"Ligo",
    "gn:country_code":"LV",
    "gn:dem":113,
    "gn:feature_class":"P",
    "gn:feature_code":"PPL",
    "gn:name":"L\u012bgo",
    "gn:population":0,
    "gn:timezone":"Europe/Riga",
    "iso:country":"LV",
    "wof:name":"Ligo",
    "wof:placetype":"locality"
},
  "geometry": {"coordinates":[26.57829000000001,57.01694000000001],"type":"Point"}
}