{
  "type": "Feature",
  "properties": {
    "gn:admin1_code":"57",
    "gn:admin2_code":"601076.0",
    "gn:asciiname":"Nartisi",
    "gn:country_code":"LV",
    "gn:dem":168,
    "gn:feature_class":"P",
    "gn:feature_code":"PPL",
    "gn:name":"Narti\u0161i",
    "gn:population":0,
    "gn:timezone":"Europe/Riga",
    "iso:country":"LV",
    "name:und_x_variant":[
        "Blaideni",
        "Nartishi",
        "Narti\u0161i"
    ],
    "wof:name":"Nartisi",
    "wof:placetype":"locality"
},
  "geometry": {"coordinates":[27.43982,56.0834],"type":"Point"}
}