{
  "type": "Feature",
  "properties": {
    "gn:admin1_code":"04",
    "gn:admin2_code":"400292.0",
    "gn:asciiname":"Jaunsaule",
    "gn:country_code":"LV",
    "gn:dem":31,
    "gn:feature_class":"P",
    "gn:feature_code":"PPL",
    "gn:name":"Jaunsaule",
    "gn:population":0,
    "gn:timezone":"Europe/Riga",
    "iso:country":"LV",
    "name:eng_x_preferred":[
        "Jaunsaule"
    ],
    "name:rus_x_preferred":[
        "\u042f\u0443\u043d\u0441\u0430\u0443\u043b\u0435"
    ],
    "name:und_x_variant":[
        "Vecamui\u017ea",
        "Yaunsaule"
    ],
    "wof:name":"Jaunsaule",
    "wof:placetype":"locality"
},
  "geometry": {"coordinates":[24.4553,56.34591],"type":"Point"}
}