{
  "type": "Feature",
  "properties": {
    "gn:admin1_code":"35",
    "gn:admin2_code":"604342.0",
    "gn:asciiname":"Skujas",
    "gn:country_code":"LV",
    "gn:dem":165,
    "gn:feature_class":"P",
    "gn:feature_code":"PPL",
    "gn:name":"Skujas",
    "gn:population":0,
    "gn:timezone":"Europe/Riga",
    "iso:country":"LV",
    "name:und_x_variant":[
        "Zukuli",
        "Skuii",
        "Skuji",
        "Skujas"
    ],
    "wof:name":"Skujas",
    "wof:placetype":"locality"
},
  "geometry": {"coordinates":[27.01086,56.08755],"type":"Point"}
}