{
  "type": "Feature",
  "properties": {
    "gn:admin1_code":"19",
    "gn:admin2_code":"680278.0",
    "gn:asciiname":"Kusneri",
    "gn:country_code":"LV",
    "gn:dem":171,
    "gn:feature_class":"P",
    "gn:feature_code":"PPL",
    "gn:name":"Ku\u0161neri",
    "gn:population":0,
    "gn:timezone":"Europe/Riga",
    "iso:country":"LV",
    "wof:name":"Kusneri",
    "wof:placetype":"locality"
},
  "geometry": {"coordinates":[27.89992,56.37451],"type":"Point"}
}