{
  "type": "Feature",
  "properties": {
    "gn:admin1_code":"24",
    "gn:admin2_code":"780296.0",
    "gn:asciiname":"Vecborisova",
    "gn:country_code":"LV",
    "gn:dem":154,
    "gn:feature_class":"P",
    "gn:feature_code":"PPL",
    "gn:name":"Vecborisova",
    "gn:population":0,
    "gn:timezone":"Europe/Riga",
    "iso:country":"LV",
    "name:und_x_variant":[
        "Borisova",
        "Vecborisova"
    ],
    "wof:name":"Vecborisova",
    "wof:placetype":"locality"
},
  "geometry": {"coordinates":[27.38672,56.55243000000001],"type":"Point"}
}