{
  "type": "Feature",
  "properties": {
    "gn:admin1_code":"03",
    "gn:admin2_code":"380246.0",
    "gn:asciiname":"Reci",
    "gn:country_code":"LV",
    "gn:dem":106,
    "gn:feature_class":"P",
    "gn:feature_code":"PPL",
    "gn:name":"Re\u010di",
    "gn:population":0,
    "gn:timezone":"Europe/Riga",
    "iso:country":"LV",
    "name:ara_x_preferred":[
        "\u0631\u064a\u062a\u0634\u064a"
    ],
    "name:ceb_x_preferred":[
        "Comuna Reci"
    ],
    "name:epo_x_preferred":[
        "Reci"
    ],
    "name:fra_x_preferred":[
        "Reci"
    ],
    "name:ita_x_preferred":[
        "Reci"
    ],
    "name:msa_x_preferred":[
        "Reci"
    ],
    "name:nld_x_preferred":[
        "Reci"
    ],
    "name:por_x_preferred":[
        "Reci"
    ],
    "name:ron_x_preferred":[
        "Comuna Reci"
    ],
    "name:srp_x_preferred":[
        "\u041e\u043f\u0448\u0442\u0438\u043d\u0430 \u0420\u0435\u0447\u0438"
    ],
    "name:ukr_x_preferred":[
        "\u0420\u0435\u0447"
    ],
    "name:vie_x_preferred":[
        "Reci"
    ],
    "name:vol_x_preferred":[
        "Reci"
    ],
    "name:zho_x_preferred":[
        "\u96f7\u5947\u9109"
    ],
    "wof:name":"Reci",
    "wof:placetype":"locality"
},
  "geometry": {"coordinates":[27.18784,57.1016],"type":"Point"}
}