{
  "type": "Feature",
  "properties": {
    "gn:admin1_code":"03",
    "gn:admin2_code":"380246.0",
    "gn:asciiname":"Reci",
    "gn:country_code":"LV",
    "gn:dem":106,
    "gn:feature_class":"P",
    "gn:feature_code":"PPL",
    "gn:name":"Re\u010di",
    "gn:population":0,
    "gn:timezone":"Europe/Riga",
    "iso:country":"LV",
    "wof:name":"Reci",
    "wof:placetype":"locality"
},
  "geometry": {"coordinates":[27.18784,57.1016],"type":"Point"}
}