{
  "type": "Feature",
  "properties": {
    "gn:admin1_code":"20",
    "gn:admin2_code":"700244.0",
    "gn:asciiname":"Stalidzani",
    "gn:country_code":"LV",
    "gn:dem":95,
    "gn:feature_class":"P",
    "gn:feature_code":"PPL",
    "gn:name":"Stal\u012bdz\u0101ni",
    "gn:population":0,
    "gn:timezone":"Europe/Riga",
    "iso:country":"LV",
    "name:und_x_variant":[
        "Stoli",
        "Stalidz\u0113ni",
        "Stalidzany",
        "Stal\u012bdz\u0101ni"
    ],
    "wof:name":"Stalidzani",
    "wof:placetype":"locality"
},
  "geometry": {"coordinates":[26.54461,56.76912],"type":"Point"}
}