{
  "type": "Feature",
  "properties": {
    "gn:admin1_code":"20",
    "gn:admin2_code":"700242.0",
    "gn:asciiname":"Lode",
    "gn:cc2":"LV",
    "gn:country_code":"LV",
    "gn:dem":207,
    "gn:feature_class":"P",
    "gn:feature_code":"PPL",
    "gn:name":"Lode",
    "gn:population":0,
    "gn:timezone":"Europe/Riga",
    "iso:country":"LV",
    "name:und_x_variant":[
        "Lodes Mui\u017ea",
        "Myza Lode",
        "Lode"
    ],
    "wof:name":"Lode",
    "wof:placetype":"locality"
},
  "geometry": {"coordinates":[26.09849,56.91249000000001],"type":"Point"}
}