{
  "type": "Feature",
  "properties": {
    "gn:admin1_code":"24",
    "gn:admin2_code":"780268.0",
    "gn:asciiname":"Zosna",
    "gn:country_code":"LV",
    "gn:dem":174,
    "gn:feature_class":"P",
    "gn:feature_code":"PPL",
    "gn:name":"Zosna",
    "gn:population":0,
    "gn:timezone":"Europe/Riga",
    "iso:country":"LV",
    "wof:name":"Zosna",
    "wof:placetype":"locality"
},
  "geometry": {"coordinates":[27.33656,56.32839],"type":"Point"}
}