{
  "type": "Feature",
  "properties": {
    "gn:admin1_code":"D2",
    "gn:admin2_code":"809600.0",
    "gn:asciiname":"Lichi",
    "gn:country_code":"LV",
    "gn:dem":6,
    "gn:feature_class":"P",
    "gn:feature_code":"PPL",
    "gn:name":"Lichi",
    "gn:population":0,
    "gn:timezone":"Europe/Riga",
    "iso:country":"LV",
    "name:und_x_variant":[
        "L\u012b\u010di"
    ],
    "wof:name":"Lichi",
    "wof:placetype":"locality"
},
  "geometry": {"coordinates":[24.35383,56.94693],"type":"Point"}
}