{
  "type": "Feature",
  "properties": {
    "gn:admin1_code":"81",
    "gn:admin2_code":"960264.0",
    "gn:asciiname":"Rievinas",
    "gn:country_code":"LV",
    "gn:dem":66,
    "gn:feature_class":"P",
    "gn:feature_code":"PPL",
    "gn:name":"Rievi\u0146as",
    "gn:population":0,
    "gn:timezone":"Europe/Riga",
    "iso:country":"LV",
    "wof:name":"Rievinas",
    "wof:placetype":"locality"
},
  "geometry": {"coordinates":[25.36014,57.46478000000001],"type":"Point"}
}