{
  "type": "Feature",
  "properties": {
    "gn:admin1_code":"33",
    "gn:admin2_code":"980260.0",
    "gn:asciiname":"Daudzites",
    "gn:country_code":"LV",
    "gn:dem":42,
    "gn:feature_class":"P",
    "gn:feature_code":"PPL",
    "gn:name":"Daudz\u012btes",
    "gn:population":0,
    "gn:timezone":"Europe/Riga",
    "iso:country":"LV",
    "wof:name":"Daudzites",
    "wof:placetype":"locality"
},
  "geometry": {"coordinates":[22.03033,57.36061],"type":"Point"}
}