{
  "type": "Feature",
  "properties": {
    "gn:admin1_code":"80",
    "gn:admin2_code":"800870.0",
    "gn:asciiname":"Plakanciems",
    "gn:country_code":"LV",
    "gn:dem":12,
    "gn:feature_class":"P",
    "gn:feature_code":"PPL",
    "gn:name":"Plakanciems",
    "gn:population":0,
    "gn:timezone":"Europe/Riga",
    "iso:country":"LV",
    "name:eng_x_preferred":[
        "Plakanciems"
    ],
    "name:rus_x_preferred":[
        "\u041f\u043b\u0430\u043a\u0430\u043d\u0446\u0438\u0435\u043c\u0441"
    ],
    "name:und_x_variant":[
        "Plakantsiyems",
        "Plakaniyeshi",
        "Plakanie\u0161i",
        "Plakanieshi"
    ],
    "wof:name":"Plakanciems",
    "wof:placetype":"locality"
},
  "geometry": {"coordinates":[24.11007,56.77019],"type":"Point"}
}