{
  "type": "Feature",
  "properties": {
    "gn:admin1_code":"24",
    "gn:admin2_code":"780280.0",
    "gn:asciiname":"Svatova",
    "gn:country_code":"LV",
    "gn:dem":159,
    "gn:feature_class":"P",
    "gn:feature_code":"PPL",
    "gn:name":"Sv\u0101tova",
    "gn:population":0,
    "gn:timezone":"Europe/Riga",
    "iso:country":"LV",
    "wof:name":"Svatova",
    "wof:placetype":"locality"
},
  "geometry": {"coordinates":[27.12623,56.22367],"type":"Point"}
}