{
  "type": "Feature",
  "properties": {
    "gn:admin1_code":"55",
    "gn:admin2_code":"700827.0",
    "gn:asciiname":"Jukani",
    "gn:country_code":"LV",
    "gn:dem":132,
    "gn:feature_class":"P",
    "gn:feature_code":"PPL",
    "gn:name":"Juk\u0101ni",
    "gn:population":0,
    "gn:timezone":"Europe/Riga",
    "iso:country":"LV",
    "name:und_x_variant":[
        "Yukany",
        "Juk\u0101ni"
    ],
    "wof:name":"Jukani",
    "wof:placetype":"locality"
},
  "geometry": {"coordinates":[26.35509,57.03462],"type":"Point"}
}