{
  "type": "Feature",
  "properties": {
    "gn:admin1_code":"28",
    "gn:admin2_code":"880242.0",
    "gn:asciiname":"Sventes",
    "gn:country_code":"LV",
    "gn:dem":61,
    "gn:feature_class":"P",
    "gn:feature_code":"PPL",
    "gn:name":"Sventes",
    "gn:population":0,
    "gn:timezone":"Europe/Riga",
    "iso:country":"LV",
    "wof:name":"Sventes",
    "wof:placetype":"locality"
},
  "geometry": {"coordinates":[22.53162,57.08051],"type":"Point"}
}