{
  "type": "Feature",
  "properties": {
    "gn:admin1_code":"29",
    "gn:admin2_code":"900254.0",
    "gn:asciiname":"Dartsmuiza",
    "gn:country_code":"LV",
    "gn:dem":75,
    "gn:feature_class":"P",
    "gn:feature_code":"PPL",
    "gn:name":"D\u0101rtsmui\u017ea",
    "gn:population":0,
    "gn:timezone":"Europe/Riga",
    "iso:country":"LV",
    "name:und_x_variant":[
        "Strautleyas",
        "D\u0101rtsmui\u017ea"
    ],
    "wof:name":"Dartsmuiza",
    "wof:placetype":"locality"
},
  "geometry": {"coordinates":[23.03879,56.86221],"type":"Point"}
}