{
  "type": "Feature",
  "properties": {
    "gn:admin1_code":"57",
    "gn:admin2_code":"601056.0",
    "gn:asciiname":"Locglova",
    "gn:country_code":"LV",
    "gn:dem":168,
    "gn:feature_class":"P",
    "gn:feature_code":"PPL",
    "gn:name":"Locglova",
    "gn:population":0,
    "gn:timezone":"Europe/Riga",
    "iso:country":"LV",
    "name:und_x_variant":[
        "Lots-Glovy",
        "Locglovo",
        "Locglova"
    ],
    "wof:name":"Locglova",
    "wof:placetype":"locality"
},
  "geometry": {"coordinates":[27.7875,56.16071],"type":"Point"}
}