{
  "type": "Feature",
  "properties": {
    "gn:admin1_code":"57",
    "gn:admin2_code":"601076.0",
    "gn:asciiname":"Konstantinova",
    "gn:country_code":"LV",
    "gn:dem":179,
    "gn:feature_class":"P",
    "gn:feature_code":"PPL",
    "gn:name":"Konstantinova",
    "gn:population":0,
    "gn:timezone":"Europe/Riga",
    "iso:country":"LV",
    "wof:name":"Konstantinova",
    "wof:placetype":"locality"
},
  "geometry": {"coordinates":[27.43676,56.06052],"type":"Point"}
}