{
  "type": "Feature",
  "properties": {
    "iso:country":"LV",
    "name:est_x_preferred":[
        "Brek\u0161i"
    ],
    "name:lav_x_preferred":[
        "Breksi"
    ],
    "name:lav_x_variant":[
        "Brek\u0161i"
    ],
    "wof:name":"Brek\u0161i",
    "wof:placetype":"neighbourhood"
},
  "geometry": {"coordinates":[24.29318185632487,56.95976681836542],"type":"Point"}
}