{
  "type": "Feature",
  "properties": {
    "gn:admin1_code":"31",
    "gn:asciiname":"Vilpulka",
    "gn:country_code":"LV",
    "gn:dem":70,
    "gn:feature_class":"P",
    "gn:feature_code":"PPL",
    "gn:name":"Vilpulka",
    "gn:population":0,
    "gn:timezone":"Europe/Riga",
    "iso:country":"LV",
    "wof:name":"Vilpulka",
    "wof:placetype":"locality"
},
  "geometry": {"coordinates":[25.23345,57.96496],"type":"Point"}
}