{
  "type": "Feature",
  "properties": {
    "gn:admin1_code":"28",
    "gn:asciiname":"Dizciems",
    "gn:country_code":"LV",
    "gn:dem":6,
    "gn:feature_class":"P",
    "gn:feature_code":"PPL",
    "gn:name":"Di\u017eciems",
    "gn:population":0,
    "gn:timezone":"Europe/Riga",
    "iso:country":"LV",
    "wof:name":"Dizciems",
    "wof:placetype":"locality"
},
  "geometry": {"coordinates":[23.12073,57.36487],"type":"Point"}
}