{
  "type": "Feature",
  "properties": {
    "gn:admin1_code":"99",
    "gn:admin2_code":"647978.0",
    "gn:asciiname":"Pape",
    "gn:country_code":"LV",
    "gn:dem":-1,
    "gn:feature_class":"P",
    "gn:feature_code":"PPL",
    "gn:name":"Pape",
    "gn:population":0,
    "gn:timezone":"Europe/Riga",
    "iso:country":"LV",
    "name:bos_x_preferred":[
        "Pape"
    ],
    "name:ceb_x_preferred":[
        "Pape"
    ],
    "name:deu_x_preferred":[
        "Pape"
    ],
    "name:fra_x_preferred":[
        "Pape"
    ],
    "name:glg_x_preferred":[
        "Pape"
    ],
    "name:hrv_x_preferred":[
        "Pape"
    ],
    "name:por_x_preferred":[
        "Pape"
    ],
    "name:rus_x_preferred":[
        "\u041f\u0430\u043f\u0435"
    ],
    "name:swe_x_preferred":[
        "Pape"
    ],
    "name:ukr_x_preferred":[
        "\u041f\u0430\u043f\u0435"
    ],
    "name:und_x_variant":[
        "Pape Mui\u017eas Centrs",
        "Myza Pape"
    ],
    "wof:name":"Pape",
    "wof:placetype":"locality"
},
  "geometry": {"coordinates":[21.06667,56.23333],"type":"Point"}
}