{
  "type": "Feature",
  "properties": {
    "gn:admin1_code":"91",
    "gn:admin2_code":"701458.0",
    "gn:asciiname":"Gundegas",
    "gn:country_code":"LV",
    "gn:dem":94,
    "gn:feature_class":"P",
    "gn:feature_code":"PPL",
    "gn:name":"Gundegas",
    "gn:population":0,
    "gn:timezone":"Europe/Riga",
    "iso:country":"LV",
    "wof:name":"Gundegas",
    "wof:placetype":"locality"
},
  "geometry": {"coordinates":[26.69378,56.89078000000001],"type":"Point"}
}