{
  "type": "Feature",
  "properties": {
    "gn:admin1_code":"14",
    "gn:admin2_code":"600262.0",
    "gn:asciiname":"Semeski",
    "gn:cc2":"LV",
    "gn:country_code":"LV",
    "gn:dem":155,
    "gn:feature_class":"P",
    "gn:feature_code":"PPL",
    "gn:name":"Seme\u0161ki",
    "gn:population":0,
    "gn:timezone":"Europe/Riga",
    "iso:country":"LV",
    "name:und_x_variant":[
        "Semeshki",
        "Seme\u0161ki"
    ],
    "wof:name":"Semeski",
    "wof:placetype":"locality"
},
  "geometry": {"coordinates":[27.56912,55.91571],"type":"Point"}
}