{
  "type": "Feature",
  "properties": {
    "gn:admin1_code":"02",
    "gn:asciiname":"Fjuki",
    "gn:country_code":"LV",
    "gn:dem":154,
    "gn:feature_class":"P",
    "gn:feature_code":"PPL",
    "gn:name":"Fjuki",
    "gn:population":0,
    "gn:timezone":"Europe/Riga",
    "iso:country":"LV",
    "name:und_x_variant":[
        "Fiki"
    ],
    "wof:name":"Fjuki",
    "wof:placetype":"locality"
},
  "geometry": {"coordinates":[27.46247,57.50796999999999],"type":"Point"}
}