{
  "type": "Feature",
  "properties": {
    "gn:admin1_code":"09",
    "gn:admin2_code":"500288.0",
    "gn:asciiname":"Stameriena",
    "gn:cc2":"LV",
    "gn:country_code":"LV",
    "gn:dem":126,
    "gn:feature_class":"P",
    "gn:feature_code":"PPL",
    "gn:name":"St\u0101meriena",
    "gn:population":0,
    "gn:timezone":"Europe/Riga",
    "iso:country":"LV",
    "name:und_x_variant":[
        "Myza Stameriena",
        "St\u0101meriene",
        "Stameriyena",
        "St\u0101meriena"
    ],
    "wof:name":"Stameriena",
    "wof:placetype":"locality"
},
  "geometry": {"coordinates":[26.88354,57.23526999999999],"type":"Point"}
}