{
  "type": "Feature",
  "properties": {
    "gn:admin1_code":"64",
    "gn:admin2_code":"806000.0",
    "gn:asciiname":"Langstini",
    "gn:cc2":"LV",
    "gn:country_code":"LV",
    "gn:dem":11,
    "gn:feature_class":"P",
    "gn:feature_code":"PPL",
    "gn:name":"Langsti\u0146i",
    "gn:population":0,
    "gn:timezone":"Europe/Riga",
    "iso:country":"LV",
    "name:und_x_variant":[
        "Eylenburga",
        "Lanksti\u0146i",
        "Eilenburga",
        "Langsti\u0146i"
    ],
    "wof:name":"Langstini",
    "wof:placetype":"locality"
},
  "geometry": {"coordinates":[24.33146,57.00714],"type":"Point"}
}