{
  "type": "Feature",
  "properties": {
    "gn:admin1_code":"99",
    "gn:admin2_code":"647978.0",
    "gn:asciiname":"Brusviti",
    "gn:cc2":"LV",
    "gn:country_code":"LV",
    "gn:dem":2,
    "gn:feature_class":"P",
    "gn:feature_code":"PPL",
    "gn:name":"Bru\u0161v\u012bti",
    "gn:population":0,
    "gn:timezone":"Europe/Riga",
    "iso:country":"LV",
    "name:und_x_variant":[
        "Brusv\u012b\u0161i",
        "Bru\u0161vituciems",
        "Brushvits",
        "Bru\u0161v\u012bti"
    ],
    "wof:name":"Brusviti",
    "wof:placetype":"locality"
},
  "geometry": {"coordinates":[21.08641,56.19255],"type":"Point"}
}