{
  "type": "Feature",
  "properties": {
    "gn:admin1_code":"21",
    "gn:admin2_code":"740260.0",
    "gn:asciiname":"Ozoli",
    "gn:cc2":"LV",
    "gn:country_code":"LV",
    "gn:dem":92,
    "gn:feature_class":"P",
    "gn:feature_code":"PPL",
    "gn:name":"Ozoli",
    "gn:population":0,
    "gn:timezone":"Europe/Riga",
    "iso:country":"LV",
    "name:und_x_variant":[
        "Ozolmui\u017ea",
        "Ozoli Mui\u017ea Centrs",
        "Ozolmuyzha",
        "Ozoli"
    ],
    "wof:name":"Ozoli",
    "wof:placetype":"locality"
},
  "geometry": {"coordinates":[25.03333,56.86666999999999],"type":"Point"}
}