{
  "type": "Feature",
  "properties": {
    "gn:admin1_code":"72",
    "gn:admin2_code":"425756.0",
    "gn:asciiname":"Jaunzemi",
    "gn:country_code":"LV",
    "gn:dem":164,
    "gn:feature_class":"P",
    "gn:feature_code":"PPL",
    "gn:name":"Jaunzemi",
    "gn:population":0,
    "gn:timezone":"Europe/Riga",
    "iso:country":"LV",
    "name:und_x_variant":[
        "Jaunzemji",
        "Jaunzemi"
    ],
    "wof:name":"Jaunzemi",
    "wof:placetype":"locality"
},
  "geometry": {"coordinates":[26.02476,57.19251],"type":"Point"}
}