{
  "type": "Feature",
  "properties": {
    "gn:admin1_code":"E2",
    "gn:admin2_code":"769194.0",
    "gn:asciiname":"Stabulniki",
    "gn:country_code":"LV",
    "gn:dem":106,
    "gn:feature_class":"P",
    "gn:feature_code":"PPL",
    "gn:name":"Stabu\u013cn\u012bki",
    "gn:population":0,
    "gn:timezone":"Europe/Riga",
    "iso:country":"LV",
    "name:und_x_variant":[
        "Stabu\u013cn\u012bki",
        "Stabulnieki"
    ],
    "wof:name":"Stabulniki",
    "wof:placetype":"locality"
},
  "geometry": {"coordinates":[26.64583,56.20861],"type":"Point"}
}