{
  "type": "Feature",
  "properties": {
    "gn:admin1_code":"B7",
    "gn:admin2_code":"387574.0",
    "gn:asciiname":"Dzelzupe",
    "gn:country_code":"LV",
    "gn:dem":105,
    "gn:feature_class":"P",
    "gn:feature_code":"PPL",
    "gn:name":"Dzelzupe",
    "gn:population":0,
    "gn:timezone":"Europe/Riga",
    "iso:country":"LV",
    "name:und_x_variant":[
        "Dzel\u017eupe"
    ],
    "wof:name":"Dzelzupe",
    "wof:placetype":"locality"
},
  "geometry": {"coordinates":[26.91029,57.03791999999999],"type":"Point"}
}