{
  "type": "Feature",
  "properties": {
    "gn:admin1_code":"03",
    "gn:admin2_code":"380258.0",
    "gn:asciiname":"Paulani",
    "gn:country_code":"LV",
    "gn:dem":117,
    "gn:feature_class":"P",
    "gn:feature_code":"PPL",
    "gn:name":"Paul\u0101ni",
    "gn:population":0,
    "gn:timezone":"Europe/Riga",
    "iso:country":"LV",
    "wof:name":"Paulani",
    "wof:placetype":"locality"
},
  "geometry": {"coordinates":[27.19036,57.2176],"type":"Point"}
}