{
  "type": "Feature",
  "properties": {
    "gn:admin1_code":"29",
    "gn:asciiname":"Matkule",
    "gn:cc2":"LV",
    "gn:country_code":"LV",
    "gn:dem":84,
    "gn:feature_class":"P",
    "gn:feature_code":"PPL",
    "gn:name":"Matkule",
    "gn:population":0,
    "gn:timezone":"Europe/Riga",
    "iso:country":"LV",
    "name:und_x_variant":[
        "Matkules",
        "Malkule",
        "Myza M\u0101tkule",
        "Matkules Mui\u017ea",
        "Matkule"
    ],
    "wof:name":"Matkule",
    "wof:placetype":"locality"
},
  "geometry": {"coordinates":[22.58961,56.97909],"type":"Point"}
}