{
  "type": "Feature",
  "properties": {
    "gn:admin1_code":"27",
    "gn:admin2_code":"840270.0",
    "gn:asciiname":"Kalni",
    "gn:country_code":"LV",
    "gn:dem":59,
    "gn:feature_class":"P",
    "gn:feature_code":"PPL",
    "gn:name":"Kalni",
    "gn:population":0,
    "gn:timezone":"Europe/Riga",
    "iso:country":"LV",
    "name:und_x_variant":[
        "Lejnieki",
        "Kalni"
    ],
    "wof:name":"Kalni",
    "wof:placetype":"locality"
},
  "geometry": {"coordinates":[22.12672,56.44468000000001],"type":"Point"}
}