{
  "type": "Feature",
  "properties": {
    "gn:admin1_code":"15",
    "gn:admin2_code":"620284.0",
    "gn:asciiname":"Edas",
    "gn:country_code":"LV",
    "gn:dem":58,
    "gn:feature_class":"P",
    "gn:feature_code":"PPL",
    "gn:name":"\u0112das",
    "gn:population":0,
    "gn:timezone":"Europe/Riga",
    "iso:country":"LV",
    "wof:name":"Edas",
    "wof:placetype":"locality"
},
  "geometry": {"coordinates":[22.11384,56.88165],"type":"Point"}
}