{
  "type": "Feature",
  "properties": {
    "gn:country":"LV",
    "gn:fcode":"PPL",
    "gn:population":30,
    "iso:country":"LV",
    "name:und_x_variant":[
        "Myza Vilksali"
    ],
    "qs_pg:aaroncc":"LV",
    "qs_pg:gn_country":"LV",
    "qs_pg:gn_fcode":"PPL",
    "qs_pg:gn_pop":30,
    "qs_pg:name":"Vilkasala",
    "qs_pg:name_adm0":"Latvija",
    "qs_pg:name_adm1":"Tukums Novads",
    "qs_pg:photos_9k":1,
    "qs_pg:photos_9r":1,
    "qs_pg:photos_all":2,
    "qs_pg:photos_sr":0,
    "qs_pg:pop_sr":1,
    "qs_pg:qs_pg_placetype":"locality",
    "qs_pg:qs_pg_placetype_gp":"Town",
    "qs_pg:woe_adm0":23424874,
    "woe:adm0_id":23424874,
    "woe:name_adm0":"Latvija",
    "woe:name_adm1":"Tukums Novads",
    "woe:placetype":"Town",
    "wof:name":"Vilkasala",
    "wof:placetype":"locality",
    "wof:population":30
},
  "geometry": {"coordinates":[23.01056,57.03306],"type":"Point"}
}