{
  "type": "Feature",
  "properties": {
    "gn:admin1_code":"15",
    "gn:admin2_code":"620246.0",
    "gn:asciiname":"Matras",
    "gn:cc2":"LV",
    "gn:country_code":"LV",
    "gn:dem":45,
    "gn:feature_class":"P",
    "gn:feature_code":"PPL",
    "gn:name":"M\u0101tras",
    "gn:population":0,
    "gn:timezone":"Europe/Riga",
    "iso:country":"LV",
    "name:und_x_variant":[
        "Kli\u0146\u0123i",
        "M\u0101tras"
    ],
    "wof:name":"Matras",
    "wof:placetype":"locality"
},
  "geometry": {"coordinates":[21.65731,57.03372],"type":"Point"}
}