{
  "type": "Feature",
  "properties": {
    "gn:admin1_code":"24",
    "gn:admin2_code":"780270.0",
    "gn:asciiname":"Mostovaja",
    "gn:country_code":"LV",
    "gn:dem":143,
    "gn:feature_class":"P",
    "gn:feature_code":"PPL",
    "gn:name":"Mostovaja",
    "gn:population":0,
    "gn:timezone":"Europe/Riga",
    "iso:country":"LV",
    "name:eng_x_preferred":[
        "Baravaja"
    ],
    "name:rus_x_preferred":[
        "\u041c\u0430\u043b\u0442\u0430"
    ],
    "name:und_x_variant":[
        "Malta",
        "Borovaja",
        "Baravaya",
        "Borovaya",
        "Baravaja",
        "Mostovaja"
    ],
    "wof:name":"Mostovaja",
    "wof:placetype":"locality"
},
  "geometry": {"coordinates":[27.16095,56.35689],"type":"Point"}
}