{
  "type": "Feature",
  "properties": {
    "gn:admin1_code":"28",
    "gn:asciiname":"Dumele",
    "gn:country_code":"LV",
    "gn:dem":17,
    "gn:feature_class":"P",
    "gn:feature_code":"PPL",
    "gn:name":"D\u016bmele",
    "gn:population":0,
    "gn:timezone":"Europe/Riga",
    "iso:country":"LV",
    "wof:name":"Dumele",
    "wof:placetype":"locality"
},
  "geometry": {"coordinates":[22.47202,57.66326],"type":"Point"}
}