{
  "type": "Feature",
  "properties": {
    "gn:admin1_code":"22",
    "gn:admin2_code":"760258.0",
    "gn:asciiname":"Otrie Bluzmi",
    "gn:country_code":"LV",
    "gn:dem":139,
    "gn:feature_class":"P",
    "gn:feature_code":"PPL",
    "gn:name":"Otrie Bluzmi",
    "gn:population":0,
    "gn:timezone":"Europe/Riga",
    "iso:country":"LV",
    "name:und_x_variant":[
        "Bl\u016bzny",
        "Bluzmi",
        "Bl\u016bz\u0146i",
        "Otrie Bluzmi"
    ],
    "wof:name":"Otrie Bluzmi",
    "wof:placetype":"locality"
},
  "geometry": {"coordinates":[26.71872,56.24714],"type":"Point"}
}