{
  "type": "Feature",
  "properties": {
    "gn:admin1_code":"27",
    "gn:admin2_code":"840296.0",
    "gn:asciiname":"Zirni",
    "gn:cc2":"LV",
    "gn:country_code":"LV",
    "gn:dem":77,
    "gn:feature_class":"P",
    "gn:feature_code":"PPL",
    "gn:name":"Zir\u0146i",
    "gn:population":0,
    "gn:timezone":"Europe/Riga",
    "iso:country":"LV",
    "name:und_x_variant":[
        "Zirnyumuyzha",
        "Zir\u0146umui\u017ea",
        "Zirnenieki",
        "Zir\u0146i"
    ],
    "wof:name":"Zirni",
    "wof:placetype":"locality"
},
  "geometry": {"coordinates":[22.21616,56.67453],"type":"Point"}
}