{
  "type": "Feature",
  "properties": {
    "gn:admin1_code":"18",
    "gn:admin2_code":"660288.0",
    "gn:asciiname":"Skirstini",
    "gn:country_code":"LV",
    "gn:dem":55,
    "gn:feature_class":"P",
    "gn:feature_code":"PPL",
    "gn:name":"\u0160\u0137irsti\u0146i",
    "gn:population":0,
    "gn:timezone":"Europe/Riga",
    "iso:country":"LV",
    "wof:name":"Skirstini",
    "wof:placetype":"locality"
},
  "geometry": {"coordinates":[24.6644,57.61208000000001],"type":"Point"}
}