{
  "type": "Feature",
  "properties": {
    "gn:admin1_code":"24",
    "gn:admin2_code":"780280.0",
    "gn:asciiname":"Liuki",
    "gn:country_code":"LV",
    "gn:dem":184,
    "gn:feature_class":"P",
    "gn:feature_code":"PPL",
    "gn:name":"Liuki",
    "gn:population":0,
    "gn:timezone":"Europe/Riga",
    "iso:country":"LV",
    "name:und_x_variant":[
        "L\u016b\u0137i"
    ],
    "wof:name":"Liuki",
    "wof:placetype":"locality"
},
  "geometry": {"coordinates":[27.27082,56.22585],"type":"Point"}
}