{
  "type": "Feature",
  "properties": {
    "gn:admin1_code":"51",
    "gn:admin2_code":"840652.0",
    "gn:asciiname":"Vecgaiki",
    "gn:country_code":"LV",
    "gn:dem":136,
    "gn:feature_class":"P",
    "gn:feature_code":"PPL",
    "gn:name":"Vecgai\u0137i",
    "gn:population":0,
    "gn:timezone":"Europe/Riga",
    "iso:country":"LV",
    "name:und_x_variant":[
        "Gayki",
        "Gaiti",
        "Gai\u0137u Mui\u017ea",
        "Gai\u0137i",
        "Vecgai\u0137i"
    ],
    "wof:name":"Vecgaiki",
    "wof:placetype":"locality"
},
  "geometry": {"coordinates":[22.56541,56.78554000000001],"type":"Point"}
}