{
  "type": "Feature",
  "properties": {
    "gn:admin1_code":"07",
    "gn:asciiname":"Dvorcani",
    "gn:cc2":"LV",
    "gn:country_code":"LV",
    "gn:dem":120,
    "gn:feature_class":"P",
    "gn:feature_code":"PPL",
    "gn:name":"Dvor\u010dani",
    "gn:population":0,
    "gn:timezone":"Europe/Riga",
    "iso:country":"LV",
    "name:und_x_variant":[
        "Dvorchany",
        "Dvor\u010dani"
    ],
    "wof:name":"Dvorcani",
    "wof:placetype":"locality"
},
  "geometry": {"coordinates":[27.56144,55.7883],"type":"Point"}
}