{
  "type": "Feature",
  "properties": {
    "gn:country":"LV",
    "gn:fcode":"PPL",
    "gn:population":0,
    "iso:country":"LV",
    "name:eng_x_preferred":[
        "Kro\u0146auce"
    ],
    "name:lav_x_preferred":[
        "Kro\u0146auce"
    ],
    "name:lit_x_preferred":[
        "Kruonauc\u0117"
    ],
    "name:nld_x_preferred":[
        "Kro\u0146auce"
    ],
    "name:rus_x_preferred":[
        "\u041a\u0440\u043e\u043d\u044c\u0430\u0443\u0446\u0435"
    ],
    "name:und_x_variant":[
        "Myza Autse"
    ],
    "qs_pg:aaroncc":"LV",
    "qs_pg:gn_country":"LV",
    "qs_pg:gn_fcode":"PPL",
    "qs_pg:gn_pop":0,
    "qs_pg:name":"Kro\u0146auce",
    "qs_pg:name_adm0":"Latvija",
    "qs_pg:name_adm1":"T\u0157rvetes Novads",
    "qs_pg:photos":5,
    "qs_pg:photos_1k":1,
    "qs_pg:photos_9k":1,
    "qs_pg:photos_9r":1,
    "qs_pg:photos_all":5,
    "qs_pg:photos_sr":1,
    "qs_pg:pop_sr":0,
    "qs_pg:qs_pg_placetype":"locality",
    "qs_pg:qs_pg_placetype_gp":"Town",
    "qs_pg:woe_adm0":23424874,
    "woe:adm0_id":23424874,
    "woe:name_adm0":"Latvija",
    "woe:name_adm1":"T\u0157rvetes Novads",
    "woe:placetype":"Town",
    "wof:name":"Kro\u0146auce",
    "wof:placetype":"locality"
},
  "geometry": {"coordinates":[23.33917,56.51],"type":"Point"}
}