{
  "type": "Feature",
  "properties": {
    "gn:admin1_code":"33",
    "gn:admin2_code":"980266.0",
    "gn:asciiname":"Mikelciems",
    "gn:cc2":"LV",
    "gn:country_code":"LV",
    "gn:dem":6,
    "gn:feature_class":"P",
    "gn:feature_code":"PPL",
    "gn:name":"Mi\u0137e\u013cciems",
    "gn:population":0,
    "gn:timezone":"Europe/Riga",
    "iso:country":"LV",
    "name:und_x_variant":[
        "Piza",
        "Mitel\u2019baka",
        "Pissen",
        "Dvor Pissen",
        "Mi\u0137e\u013cciems"
    ],
    "wof:name":"Mikelciems",
    "wof:placetype":"locality"
},
  "geometry": {"coordinates":[21.97523,57.59925],"type":"Point"}
}