{
  "type": "Feature",
  "properties": {
    "gn:admin1_code":"81",
    "gn:admin2_code":"427372.0",
    "gn:asciiname":"Kuki",
    "gn:country_code":"LV",
    "gn:dem":70,
    "gn:feature_class":"P",
    "gn:feature_code":"PPL",
    "gn:name":"\u0136\u016b\u0137i",
    "gn:population":0,
    "gn:timezone":"Europe/Riga",
    "iso:country":"LV",
    "name:ceb_x_preferred":[
        "Kuki"
    ],
    "name:deu_x_preferred":[
        "Kuki"
    ],
    "name:fas_x_preferred":[
        "\u06a9\u0648\u06a9\u06cc"
    ],
    "name:ita_x_preferred":[
        "Kuki"
    ],
    "name:rus_x_preferred":[
        "\u041a\u0443\u043a\u0438"
    ],
    "name:swe_x_preferred":[
        "Kuki"
    ],
    "name:tgl_x_preferred":[
        "Kuki"
    ],
    "name:ukr_x_preferred":[
        "\u041a\u0443\u043a\u0456"
    ],
    "name:und_x_variant":[
        "\u0136\u016b\u0137i",
        "\u0136\u0101\u0137i"
    ],
    "wof:name":"Kuki",
    "wof:placetype":"locality"
},
  "geometry": {"coordinates":[25.33567,57.43036],"type":"Point"}
}