{
  "type": "Feature",
  "properties": {
    "gn:admin1_code":"81",
    "gn:admin2_code":"427372.0",
    "gn:asciiname":"Kuki",
    "gn:country_code":"LV",
    "gn:dem":70,
    "gn:feature_class":"P",
    "gn:feature_code":"PPL",
    "gn:name":"\u0136\u016b\u0137i",
    "gn:population":0,
    "gn:timezone":"Europe/Riga",
    "iso:country":"LV",
    "name:und_x_variant":[
        "\u0136\u016b\u0137i",
        "\u0136\u0101\u0137i"
    ],
    "wof:name":"Kuki",
    "wof:placetype":"locality"
},
  "geometry": {"coordinates":[25.33567,57.43036],"type":"Point"}
}