{
  "type": "Feature",
  "properties": {
    "gn:admin1_code":"33",
    "gn:admin2_code":"980244.0",
    "gn:asciiname":"Ance",
    "gn:cc2":"LV",
    "gn:country_code":"LV",
    "gn:dem":21,
    "gn:feature_class":"P",
    "gn:feature_code":"PPL",
    "gn:name":"Ance",
    "gn:population":0,
    "gn:timezone":"Europe/Riga",
    "iso:country":"LV",
    "name:deu_x_preferred":[
        "Ance"
    ],
    "name:fra_x_preferred":[
        "Ance"
    ],
    "name:ita_x_preferred":[
        "Ance"
    ],
    "name:lav_x_preferred":[
        "Ance"
    ],
    "name:und_x_variant":[
        "Volostnoye Pravleniye Antse",
        "Antse",
        "Ance Mui\u017eas Centrs"
    ],
    "wof:name":"Ance",
    "wof:placetype":"locality"
},
  "geometry": {"coordinates":[22.02295,57.51379],"type":"Point"}
}