{
  "type": "Feature",
  "properties": {
    "gn:admin1_code":"56",
    "gn:admin2_code":"684948.0",
    "gn:asciiname":"Cibla",
    "gn:country_code":"LV",
    "gn:dem":118,
    "gn:feature_class":"P",
    "gn:feature_code":"PPLA",
    "gn:name":"Cibla",
    "gn:population":0,
    "gn:timezone":"Europe/Riga",
    "iso:country":"LV",
    "name:eng_x_preferred":[
        "Eversmui\u017ea"
    ],
    "name:rus_x_preferred":[
        "\u0426\u0438\u0431\u043b\u0430"
    ],
    "name:und_x_variant":[
        "Tsibla",
        "Cibla",
        "Eversmui\u017ea"
    ],
    "wof:name":"Cibla",
    "wof:placetype":"locality"
},
  "geometry": {"coordinates":[27.8837,56.5498],"type":"Point"}
}