{
  "type": "Feature",
  "properties": {
    "gn:admin1_code":"29",
    "gn:admin2_code":"900268.0",
    "gn:asciiname":"Burtnieki",
    "gn:country_code":"LV",
    "gn:dem":63,
    "gn:feature_class":"P",
    "gn:feature_code":"PPL",
    "gn:name":"Burtnieki",
    "gn:population":0,
    "gn:timezone":"Europe/Riga",
    "iso:country":"LV",
    "name:und_x_variant":[
        "Burtniyeki",
        "Burtnieki"
    ],
    "wof:name":"Burtnieki",
    "wof:placetype":"locality"
},
  "geometry": {"coordinates":[23.06923,56.79397],"type":"Point"}
}