{
  "type": "Feature",
  "properties": {
    "gn:admin1_code":"05",
    "gn:asciiname":"Bringi",
    "gn:country_code":"LV",
    "gn:dem":193,
    "gn:feature_class":"P",
    "gn:feature_code":"PPL",
    "gn:name":"Bri\u0146\u0123i",
    "gn:population":0,
    "gn:timezone":"Europe/Riga",
    "iso:country":"LV",
    "wof:name":"Bringi",
    "wof:placetype":"locality"
},
  "geometry": {"coordinates":[25.88495,57.00268000000001],"type":"Point"}
}