{
  "type": "Feature",
  "properties": {
    "gn:admin1_code":"90",
    "gn:admin2_code":"761286.0",
    "gn:asciiname":"Zundani",
    "gn:country_code":"LV",
    "gn:dem":92,
    "gn:feature_class":"P",
    "gn:feature_code":"PPL",
    "gn:name":"Zund\u0101ni",
    "gn:population":0,
    "gn:timezone":"Europe/Riga",
    "iso:country":"LV",
    "wof:name":"Zundani",
    "wof:placetype":"locality"
},
  "geometry": {"coordinates":[26.21774000000001,56.42543000000001],"type":"Point"}
}