{
  "type": "Feature",
  "properties": {
    "gn:admin1_code":"02",
    "gn:admin2_code":"360280.0",
    "gn:asciiname":"Pededze",
    "gn:country_code":"LV",
    "gn:dem":151,
    "gn:feature_class":"P",
    "gn:feature_code":"PPL",
    "gn:name":"Pededze",
    "gn:population":0,
    "gn:timezone":"Europe/Riga",
    "iso:country":"LV",
    "name:deu_x_preferred":[
        "Pededze"
    ],
    "name:est_x_preferred":[
        "Pedetsi j\u00f5gi"
    ],
    "name:fra_x_preferred":[
        "Pededze"
    ],
    "name:hye_x_preferred":[
        "\u054a\u0565\u0564\u0565\u0564\u0566\u0565"
    ],
    "name:ina_x_preferred":[
        "Fluvio Pededze"
    ],
    "name:ita_x_preferred":[
        "Pededze"
    ],
    "name:kat_x_preferred":[
        "\u10de\u10d4\u10d3\u10d4\u10eb\u10d4"
    ],
    "name:lav_x_preferred":[
        "Pededze"
    ],
    "name:lit_x_preferred":[
        "Pededz\u0117"
    ],
    "name:ltg_x_preferred":[
        "Pededze"
    ],
    "name:pol_x_preferred":[
        "Pededze"
    ],
    "name:rus_x_preferred":[
        "\u041f\u0435\u0434\u0435\u0434\u0437\u0435"
    ],
    "name:swe_x_preferred":[
        "Pededze"
    ],
    "wof:name":"Pededze",
    "wof:placetype":"locality"
},
  "geometry": {"coordinates":[27.44016,57.4762],"type":"Point"}
}