{
  "type": "Feature",
  "properties": {
    "gn:admin1_code":"02",
    "gn:admin2_code":"360280.0",
    "gn:asciiname":"Pededze",
    "gn:country_code":"LV",
    "gn:dem":151,
    "gn:feature_class":"P",
    "gn:feature_code":"PPL",
    "gn:name":"Pededze",
    "gn:population":0,
    "gn:timezone":"Europe/Riga",
    "iso:country":"LV",
    "wof:name":"Pededze",
    "wof:placetype":"locality"
},
  "geometry": {"coordinates":[27.44016,57.4762],"type":"Point"}
}