{
  "type": "Feature",
  "properties": {
    "gn:admin1_code":"C1",
    "gn:admin2_code":"661435.0",
    "gn:asciiname":"Lauvas",
    "gn:country_code":"LV",
    "gn:dem":37,
    "gn:feature_class":"P",
    "gn:feature_code":"PPL",
    "gn:name":"Lauvas",
    "gn:population":0,
    "gn:timezone":"Europe/Riga",
    "iso:country":"LV",
    "name:eng_x_preferred":[
        "Lauvas"
    ],
    "name:rus_x_preferred":[
        "\u041b\u0430\u0443\u0432\u0430"
    ],
    "name:und_x_variant":[
        "Lauva"
    ],
    "wof:name":"Lauvas",
    "wof:placetype":"locality"
},
  "geometry": {"coordinates":[24.55206,57.70301],"type":"Point"}
}