{
  "type": "Feature",
  "properties": {
    "gn:admin1_code":"31",
    "gn:asciiname":"Mujani",
    "gn:country_code":"LV",
    "gn:dem":64,
    "gn:feature_class":"P",
    "gn:feature_code":"PPL",
    "gn:name":"Muj\u0101ni",
    "gn:population":0,
    "gn:timezone":"Europe/Riga",
    "iso:country":"LV",
    "wof:name":"Mujani",
    "wof:placetype":"locality"
},
  "geometry": {"coordinates":[25.28121,57.52186],"type":"Point"}
}