{
  "type": "Feature",
  "properties": {
    "gn:admin1_code":"A8",
    "gn:admin2_code":"641646.0",
    "gn:asciiname":"Krote",
    "gn:cc2":"LV",
    "gn:country_code":"LV",
    "gn:dem":74,
    "gn:feature_class":"P",
    "gn:feature_code":"PPL",
    "gn:name":"Krote",
    "gn:population":0,
    "gn:timezone":"Europe/Riga",
    "iso:country":"LV",
    "name:und_x_variant":[
        "Krotes",
        "Klote",
        "Krote"
    ],
    "wof:name":"Krote",
    "wof:placetype":"locality"
},
  "geometry": {"coordinates":[21.54689,56.54205],"type":"Point"}
}