{
  "type": "Feature",
  "properties": {
    "gn:admin1_code":"C1",
    "gn:admin2_code":"661460.0",
    "gn:asciiname":"Metagmuiza",
    "gn:country_code":"LV",
    "gn:dem":37,
    "gn:feature_class":"P",
    "gn:feature_code":"PPL",
    "gn:name":"M\u0113tagmui\u017ea",
    "gn:population":0,
    "gn:timezone":"Europe/Riga",
    "iso:country":"LV",
    "name:und_x_variant":[
        "Polumyza Metaka",
        "M\u0113takas Pusmui\u017eas Centrs",
        "M\u0113taka",
        "M\u0113taki",
        "Metagi",
        "Me\u017eciems",
        "M\u0113tagmui\u017ea"
    ],
    "wof:name":"Metagmuiza",
    "wof:placetype":"locality"
},
  "geometry": {"coordinates":[24.52033,57.52093000000001],"type":"Point"}
}