{
  "type": "Feature",
  "properties": {
    "gn:admin1_code":"90",
    "gn:admin2_code":"761286.0",
    "gn:asciiname":"Speleskeiri",
    "gn:country_code":"LV",
    "gn:dem":90,
    "gn:feature_class":"P",
    "gn:feature_code":"PPL",
    "gn:name":"Sp\u0113les\u0137eiri",
    "gn:population":0,
    "gn:timezone":"Europe/Riga",
    "iso:country":"LV",
    "name:und_x_variant":[
        "Speles-T\u2019yeyri",
        "Sp\u0113les-\u0136eiri",
        "Sp\u0113les\u0137eiri"
    ],
    "wof:name":"Speleskeiri",
    "wof:placetype":"locality"
},
  "geometry": {"coordinates":[26.22526,56.43261],"type":"Point"}
}