{
  "type": "Feature",
  "properties": {
    "gn:admin1_code":"24",
    "gn:admin2_code":"780278.0",
    "gn:asciiname":"Greivuli",
    "gn:country_code":"LV",
    "gn:dem":140,
    "gn:feature_class":"P",
    "gn:feature_code":"PPL",
    "gn:name":"Greivu\u013ci",
    "gn:population":0,
    "gn:timezone":"Europe/Riga",
    "iso:country":"LV",
    "name:und_x_variant":[
        "Gr\u012bvu\u013ci",
        "Greivu\u013ci"
    ],
    "wof:name":"Greivuli",
    "wof:placetype":"locality"
},
  "geometry": {"coordinates":[27.2907,56.54148000000001],"type":"Point"}
}