{
  "type": "Feature",
  "properties": {
    "gn:admin1_code":"57",
    "gn:admin2_code":"601046.0",
    "gn:asciiname":"Asune",
    "gn:country_code":"LV",
    "gn:dem":151,
    "gn:feature_class":"P",
    "gn:feature_code":"PPL",
    "gn:name":"As\u016bne",
    "gn:population":0,
    "gn:timezone":"Europe/Riga",
    "iso:country":"LV",
    "name:eng_x_preferred":[
        "As\u016bne"
    ],
    "name:rus_x_preferred":[
        "\u0410\u0441\u0443\u043d\u0435"
    ],
    "name:und_x_variant":[
        "As\u016bne",
        "Osiuns"
    ],
    "wof:name":"Asune",
    "wof:placetype":"locality"
},
  "geometry": {"coordinates":[27.62144,56.02585],"type":"Point"}
}