{
  "type": "Feature",
  "properties": {
    "gn:admin1_code":"B3",
    "gn:admin2_code":"766376.0",
    "gn:asciiname":"Bikova",
    "gn:country_code":"LV",
    "gn:dem":143,
    "gn:feature_class":"P",
    "gn:feature_code":"PPL",
    "gn:name":"Bikova",
    "gn:population":0,
    "gn:timezone":"Europe/Riga",
    "iso:country":"LV",
    "name:und_x_variant":[
        "Bikava",
        "Bykova",
        "Bikova"
    ],
    "wof:name":"Bikova",
    "wof:placetype":"locality"
},
  "geometry": {"coordinates":[26.90478,56.3809],"type":"Point"}
}