{
  "type": "Feature",
  "properties": {
    "gn:admin1_code":"A9",
    "gn:admin2_code":"427372.0",
    "gn:asciiname":"Pieskalni",
    "gn:country_code":"LV",
    "gn:dem":70,
    "gn:feature_class":"P",
    "gn:feature_code":"PPL",
    "gn:name":"Pie\u0161kalni",
    "gn:population":0,
    "gn:timezone":"Europe/Riga",
    "iso:country":"LV",
    "name:und_x_variant":[
        "Pie\u0161kalni",
        "\u017dagari"
    ],
    "wof:name":"Pieskalni",
    "wof:placetype":"locality"
},
  "geometry": {"coordinates":[25.26294,57.35585],"type":"Point"}
}