{
  "type": "Feature",
  "properties": {
    "gn:admin1_code":"24",
    "gn:admin2_code":"780288.0",
    "gn:asciiname":"Dzeni",
    "gn:country_code":"LV",
    "gn:dem":147,
    "gn:feature_class":"P",
    "gn:feature_code":"PPL",
    "gn:name":"Dze\u0146i",
    "gn:population":0,
    "gn:timezone":"Europe/Riga",
    "iso:country":"LV",
    "name:und_x_variant":[
        "De\u0146i",
        "Dze\u0146i"
    ],
    "wof:name":"Dzeni",
    "wof:placetype":"locality"
},
  "geometry": {"coordinates":[27.14811,56.39189],"type":"Point"}
}