{
  "type": "Feature",
  "properties": {
    "gn:admin1_code":"18",
    "gn:admin2_code":"660288.0",
    "gn:asciiname":"Vilkene",
    "gn:country_code":"LV",
    "gn:dem":52,
    "gn:feature_class":"P",
    "gn:feature_code":"PPL",
    "gn:name":"Vi\u013c\u0137ene",
    "gn:population":0,
    "gn:timezone":"Europe/Riga",
    "iso:country":"LV",
    "name:eng_x_preferred":[
        "Vi\u013c\u0137ene"
    ],
    "name:rus_x_preferred":[
        "\u0412\u0438\u043b\u043a\u0435\u043d\u0435"
    ],
    "name:und_x_variant":[
        "Myza Vilteny",
        "Vi\u013c\u0137enu Mui\u017ea",
        "Vi\u013c\u0137ene"
    ],
    "wof:name":"Vilkene",
    "wof:placetype":"locality"
},
  "geometry": {"coordinates":[24.61085,57.61121],"type":"Point"}
}