{
  "type": "Feature",
  "properties": {
    "gn:admin1_code":"02",
    "gn:admin2_code":"360264.0",
    "gn:asciiname":"Kalncempji",
    "gn:country_code":"LV",
    "gn:dem":142,
    "gn:feature_class":"P",
    "gn:feature_code":"PPL",
    "gn:name":"Kalncempji",
    "gn:population":0,
    "gn:timezone":"Europe/Riga",
    "iso:country":"LV",
    "name:und_x_variant":[
        "Cempji",
        "Kalntsemp\u2019i",
        "Tsempi",
        "Kalncempi",
        "Kalncempji"
    ],
    "wof:name":"Kalncempji",
    "wof:placetype":"locality"
},
  "geometry": {"coordinates":[26.88561,57.32342],"type":"Point"}
}