{
  "type": "Feature",
  "properties": {
    "gn:admin1_code":"07",
    "gn:asciiname":"Berezki",
    "gn:cc2":"LV",
    "gn:country_code":"LV",
    "gn:dem":154,
    "gn:feature_class":"P",
    "gn:feature_code":"PPL",
    "gn:name":"Berezki",
    "gn:population":0,
    "gn:timezone":"Europe/Riga",
    "iso:country":"LV",
    "name:und_x_variant":[
        "B\u0113rzi\u0146i",
        "Berjozki",
        "Berozki",
        "Berezki"
    ],
    "wof:name":"Berezki",
    "wof:placetype":"locality"
},
  "geometry": {"coordinates":[27.44934000000001,55.82559000000001],"type":"Point"}
}