{
  "type": "Feature",
  "properties": {
    "gn:admin1_code":"24",
    "gn:admin2_code":"780250.0",
    "gn:asciiname":"Kaulaci",
    "gn:cc2":"LV",
    "gn:country_code":"LV",
    "gn:dem":153,
    "gn:feature_class":"P",
    "gn:feature_code":"PPL",
    "gn:name":"Kaula\u010di",
    "gn:population":0,
    "gn:timezone":"Europe/Riga",
    "iso:country":"LV",
    "name:und_x_variant":[
        "Kaulici",
        "Kaulachi",
        "Kaula\u010di"
    ],
    "wof:name":"Kaulaci",
    "wof:placetype":"locality"
},
  "geometry": {"coordinates":[27.19417,56.6272],"type":"Point"}
}