{
  "type": "Feature",
  "properties": {
    "gn:admin1_code":"27",
    "gn:admin2_code":"840248.0",
    "gn:asciiname":"Garozas",
    "gn:country_code":"LV",
    "gn:dem":83,
    "gn:feature_class":"P",
    "gn:feature_code":"PPL",
    "gn:name":"Garozas",
    "gn:population":0,
    "gn:timezone":"Europe/Riga",
    "iso:country":"LV",
    "wof:name":"Garozas",
    "wof:placetype":"locality"
},
  "geometry": {"coordinates":[22.31486,56.43203000000001],"type":"Point"}
}