{
  "type": "Feature",
  "properties": {
    "gn:admin1_code":"29",
    "gn:asciiname":"Rezesciems",
    "gn:cc2":"LV",
    "gn:country_code":"LV",
    "gn:dem":89,
    "gn:feature_class":"P",
    "gn:feature_code":"PPL",
    "gn:name":"R\u0113zesciems",
    "gn:population":0,
    "gn:timezone":"Europe/Riga",
    "iso:country":"LV",
    "name:und_x_variant":[
        "Rezestsiems",
        "R\u0113zes",
        "R\u0113zesciems"
    ],
    "wof:name":"Rezesciems",
    "wof:placetype":"locality"
},
  "geometry": {"coordinates":[22.67346,57.09588000000001],"type":"Point"}
}