{
  "type": "Feature",
  "properties": {
    "gn:country":"LV",
    "gn:fcode":"PPL",
    "gn:population":0,
    "iso:country":"LV",
    "name:und_x_variant":[
        "Saulayne"
    ],
    "qs_pg:aaroncc":"LV",
    "qs_pg:gn_country":"LV",
    "qs_pg:gn_fcode":"PPL",
    "qs_pg:gn_pop":0,
    "qs_pg:name":"Kaucminde",
    "qs_pg:name_adm0":"Latvija",
    "qs_pg:name_adm1":"Rund\u0105les Novads",
    "qs_pg:photos":52,
    "qs_pg:photos_1k":11,
    "qs_pg:photos_9k":1,
    "qs_pg:photos_9r":2,
    "qs_pg:photos_all":52,
    "qs_pg:photos_sr":2,
    "qs_pg:pop_sr":0,
    "qs_pg:qs_pg_placetype":"locality",
    "qs_pg:qs_pg_placetype_gp":"Town",
    "qs_pg:woe_adm0":23424874,
    "woe:adm0_id":23424874,
    "woe:name_adm0":"Latvija",
    "woe:name_adm1":"Rund\u0105les Novads",
    "woe:placetype":"Town",
    "wof:name":"Kaucminde",
    "wof:placetype":"locality"
},
  "geometry": {"coordinates":[24.12611,56.39417],"type":"Point"}
}