{
  "type": "Feature",
  "properties": {
    "gn:admin1_code":"10",
    "gn:admin2_code":"560298.0",
    "gn:asciiname":"Gerkani",
    "gn:country_code":"LV",
    "gn:dem":109,
    "gn:feature_class":"P",
    "gn:feature_code":"PPL",
    "gn:name":"\u0122\u0113r\u0137\u0101ni",
    "gn:population":0,
    "gn:timezone":"Europe/Riga",
    "iso:country":"LV",
    "name:und_x_variant":[
        "\u0122\u0113r\u0137\u0101ni",
        "G\u0113r\u0137\u0113ni"
    ],
    "wof:name":"Gerkani",
    "wof:placetype":"locality"
},
  "geometry": {"coordinates":[26.10585,56.27141],"type":"Point"}
}