{
  "type": "Feature",
  "properties": {
    "gn:admin1_code":"29",
    "gn:admin2_code":"900268.0",
    "gn:asciiname":"Blazma",
    "gn:country_code":"LV",
    "gn:dem":65,
    "gn:feature_class":"P",
    "gn:feature_code":"PPL",
    "gn:name":"Bl\u0101zma",
    "gn:population":0,
    "gn:timezone":"Europe/Riga",
    "iso:country":"LV",
    "name:und_x_variant":[
        "Bl\u0101zmas",
        "Bl\u0101zma"
    ],
    "wof:name":"Blazma",
    "wof:placetype":"locality"
},
  "geometry": {"coordinates":[23.09177,56.78068],"type":"Point"}
}