{
  "type": "Feature",
  "properties": {
    "gn:admin1_code":"28",
    "gn:asciiname":"Pekelciems",
    "gn:country_code":"LV",
    "gn:dem":7,
    "gn:feature_class":"P",
    "gn:feature_code":"PPL",
    "gn:name":"Peke\u013cciems",
    "gn:population":0,
    "gn:timezone":"Europe/Riga",
    "iso:country":"LV",
    "wof:name":"Pekelciems",
    "wof:placetype":"locality"
},
  "geometry": {"coordinates":[23.11077,57.3639],"type":"Point"}
}