{
  "type": "Feature",
  "properties": {
    "iso:country":"LV",
    "name:est_x_preferred":[
        "Valteri"
    ],
    "name:lav_x_preferred":[
        "Valteri"
    ],
    "wof:name":"Valteri",
    "wof:placetype":"neighbourhood"
},
  "geometry": {"coordinates":[23.69465555419841,56.94388355004155],"type":"Point"}
}