{
  "type": "Feature",
  "properties": {
    "gn:admin1_code":"B7",
    "gn:admin2_code":"387564.0",
    "gn:asciiname":"Lielie Meroni",
    "gn:country_code":"LV",
    "gn:dem":103,
    "gn:feature_class":"P",
    "gn:feature_code":"PPL",
    "gn:name":"Lielie Meroni",
    "gn:population":0,
    "gn:timezone":"Europe/Riga",
    "iso:country":"LV",
    "name:und_x_variant":[
        "Mirony",
        "Lielmeiron",
        "Mironi",
        "Lielie Meroni"
    ],
    "wof:name":"Lielie Meroni",
    "wof:placetype":"locality"
},
  "geometry": {"coordinates":[27.09356,56.89058000000001],"type":"Point"}
}