{
  "type": "Feature",
  "properties": {
    "iso:country":"LV",
    "name:lav_x_preferred":[
        "D\u0101rzi\u0146i"
    ],
    "wof:name":"Darzini",
    "wof:placetype":"neighbourhood"
},
  "geometry": {"coordinates":[24.26617378609508,56.86693035761571],"type":"Point"}
}