{
  "type": "Feature",
  "properties": {
    "gn:admin1_code":"24",
    "gn:admin2_code":"780280.0",
    "gn:asciiname":"Vaciesi",
    "gn:country_code":"LV",
    "gn:dem":159,
    "gn:feature_class":"P",
    "gn:feature_code":"PPL",
    "gn:name":"V\u0101cie\u0161i",
    "gn:population":0,
    "gn:timezone":"Europe/Riga",
    "iso:country":"LV",
    "wof:name":"Vaciesi",
    "wof:placetype":"locality"
},
  "geometry": {"coordinates":[27.18333,56.25],"type":"Point"}
}