{
  "type": "Feature",
  "properties": {
    "gn:admin1_code":"63",
    "gn:admin2_code":"705560.0",
    "gn:asciiname":"Vejava",
    "gn:country_code":"LV",
    "gn:dem":224,
    "gn:feature_class":"P",
    "gn:feature_code":"PPL",
    "gn:name":"V\u0113java",
    "gn:population":0,
    "gn:timezone":"Europe/Riga",
    "iso:country":"LV",
    "name:und_x_variant":[
        "Veyavas",
        "Veyava",
        "V\u0113javas Mui\u017ea",
        "V\u0113java"
    ],
    "wof:name":"Vejava",
    "wof:placetype":"locality"
},
  "geometry": {"coordinates":[25.88252,56.92839],"type":"Point"}
}