{
  "type": "Feature",
  "properties": {
    "gn:admin1_code":"27",
    "gn:admin2_code":"840262.0",
    "gn:asciiname":"Kudras",
    "gn:country_code":"LV",
    "gn:dem":88,
    "gn:feature_class":"P",
    "gn:feature_code":"PPL",
    "gn:name":"K\u016bdras",
    "gn:population":0,
    "gn:timezone":"Europe/Riga",
    "iso:country":"LV",
    "name:und_x_variant":[
        "K\u016bdras",
        "P\u016bgas"
    ],
    "wof:name":"Kudras",
    "wof:placetype":"locality"
},
  "geometry": {"coordinates":[22.29091,56.51622],"type":"Point"}
}