{
  "type": "Feature",
  "properties": {
    "gn:admin1_code":"15",
    "gn:admin2_code":"620290.0",
    "gn:asciiname":"Princi",
    "gn:cc2":"LV",
    "gn:country_code":"LV",
    "gn:dem":64,
    "gn:feature_class":"P",
    "gn:feature_code":"PPL",
    "gn:name":"Prin\u010di",
    "gn:population":0,
    "gn:timezone":"Europe/Riga",
    "iso:country":"LV",
    "name:und_x_variant":[
        "Princmuiza",
        "Myza Printsmuyzha",
        "Prin\u010di"
    ],
    "wof:name":"Princi",
    "wof:placetype":"locality"
},
  "geometry": {"coordinates":[21.95,56.86666999999999],"type":"Point"}
}