{
  "type": "Feature",
  "properties": {
    "gn:admin1_code":"C7",
    "gn:admin2_code":"801642.0",
    "gn:asciiname":"Allazi",
    "gn:country_code":"LV",
    "gn:dem":104,
    "gn:feature_class":"P",
    "gn:feature_code":"PPL",
    "gn:name":"Alla\u017ei",
    "gn:population":0,
    "gn:timezone":"Europe/Riga",
    "iso:country":"LV",
    "name:und_x_variant":[
        "Grundu\u013ci",
        "Allazhi",
        "Alla\u017ei"
    ],
    "wof:name":"Allazi",
    "wof:placetype":"locality"
},
  "geometry": {"coordinates":[24.84465,57.0619],"type":"Point"}
}