{
  "type": "Feature",
  "properties": {
    "gn:admin1_code":"90",
    "gn:admin2_code":"761282.0",
    "gn:asciiname":"Tiltova",
    "gn:country_code":"LV",
    "gn:dem":104,
    "gn:feature_class":"P",
    "gn:feature_code":"PPL",
    "gn:name":"Tiltova",
    "gn:population":0,
    "gn:timezone":"Europe/Riga",
    "iso:country":"LV",
    "name:eng_x_preferred":[
        "Tiltova"
    ],
    "name:rus_x_preferred":[
        "\u0422\u0438\u043b\u0442\u0430\u0432\u0430"
    ],
    "name:und_x_variant":[
        "Tyltovo",
        "Tiltava",
        "Titova",
        "Tiltav\u012bta"
    ],
    "wof:name":"Tiltova",
    "wof:placetype":"locality"
},
  "geometry": {"coordinates":[26.50197,56.28609],"type":"Point"}
}