{
  "type": "Feature",
  "properties": {
    "gn:admin1_code":"15",
    "gn:admin2_code":"620246.0",
    "gn:asciiname":"Kapciems",
    "gn:country_code":"LV",
    "gn:dem":50,
    "gn:feature_class":"P",
    "gn:feature_code":"PPLL",
    "gn:name":"K\u0101pciems",
    "gn:population":0,
    "gn:timezone":"Europe/Riga",
    "iso:country":"LV",
    "name:und_x_variant":[
        "Polumyza Kapas",
        "K\u0101pas",
        "K\u0101pciems"
    ],
    "wof:name":"Kapciems",
    "wof:placetype":"locality"
},
  "geometry": {"coordinates":[21.71964,57.10104000000001],"type":"Point"}
}