{
  "type": "Feature",
  "properties": {
    "gn:admin1_code":"44",
    "gn:admin2_code":"460850.0",
    "gn:asciiname":"Vecsnikere",
    "gn:country_code":"LV",
    "gn:dem":82,
    "gn:feature_class":"P",
    "gn:feature_code":"PPL",
    "gn:name":"Vecsni\u0137ere",
    "gn:population":0,
    "gn:timezone":"Europe/Riga",
    "iso:country":"LV",
    "name:und_x_variant":[
        "Kukurumuyzha",
        "Snikere",
        "Kukuri",
        "Kukurumui\u017ea",
        "Vecsni\u0137ere"
    ],
    "wof:name":"Vecsnikere",
    "wof:placetype":"locality"
},
  "geometry": {"coordinates":[23.04694,56.40583],"type":"Point"}
}