{
  "type": "Feature",
  "properties": {
    "gn:admin1_code":"20",
    "gn:asciiname":"Incarnieki",
    "gn:cc2":"LV",
    "gn:country_code":"LV",
    "gn:dem":96,
    "gn:feature_class":"P",
    "gn:feature_code":"PPL",
    "gn:name":"In\u010d\u0101rnieki",
    "gn:population":0,
    "gn:timezone":"Europe/Riga",
    "iso:country":"LV",
    "name:und_x_variant":[
        "Incharnyeki",
        "In\u010dernieki",
        "In\u010darnieki"
    ],
    "wof:name":"Incarnieki",
    "wof:placetype":"locality"
},
  "geometry": {"coordinates":[26.60803,56.66764000000001],"type":"Point"}
}