{
  "type": "Feature",
  "properties": {
    "gn:admin1_code":"63",
    "gn:admin2_code":"705592.0",
    "gn:asciiname":"Apsukrogs",
    "gn:country_code":"LV",
    "gn:dem":152,
    "gn:feature_class":"P",
    "gn:feature_code":"PPL",
    "gn:name":"Ap\u0161ukrogs",
    "gn:population":0,
    "gn:timezone":"Europe/Riga",
    "iso:country":"LV",
    "wof:name":"Apsukrogs",
    "wof:placetype":"locality"
},
  "geometry": {"coordinates":[25.61667000000001,56.81667],"type":"Point"}
}