{
  "type": "Feature",
  "properties": {
    "gn:admin1_code":"20",
    "gn:admin2_code":"700282.0",
    "gn:asciiname":"Pauri",
    "gn:country_code":"LV",
    "gn:dem":93,
    "gn:feature_class":"P",
    "gn:feature_code":"PPL",
    "gn:name":"Pauri",
    "gn:population":0,
    "gn:timezone":"Europe/Riga",
    "iso:country":"LV",
    "name:und_x_variant":[
        "Jasmi\u0146i",
        "Pauri"
    ],
    "wof:name":"Pauri",
    "wof:placetype":"locality"
},
  "geometry": {"coordinates":[26.8172,56.81309],"type":"Point"}
}