{
  "type": "Feature",
  "properties": {
    "gn:admin1_code":"20",
    "gn:admin2_code":"700282.0",
    "gn:asciiname":"Pauri",
    "gn:country_code":"LV",
    "gn:dem":93,
    "gn:feature_class":"P",
    "gn:feature_code":"PPL",
    "gn:name":"Pauri",
    "gn:population":0,
    "gn:timezone":"Europe/Riga",
    "iso:country":"LV",
    "name:bel_x_preferred":[
        "\u041f\u0430\u045e\u0440\u044b"
    ],
    "name:bpy_x_preferred":[
        "\u09aa\u09be\u0989\u09b0\u09bf"
    ],
    "name:cat_x_preferred":[
        "Pauri"
    ],
    "name:ceb_x_preferred":[
        "Pauri"
    ],
    "name:guj_x_preferred":[
        "\u0aaa\u0acc\u0aa1\u0ac0"
    ],
    "name:hin_x_preferred":[
        "\u092a\u094c\u0921\u093c\u0940"
    ],
    "name:ita_x_preferred":[
        "Pauri"
    ],
    "name:mar_x_preferred":[
        "\u092a\u094c\u0921\u0940"
    ],
    "name:mlg_x_preferred":[
        "Pauri"
    ],
    "name:msa_x_preferred":[
        "Pauri"
    ],
    "name:nld_x_preferred":[
        "Pauri"
    ],
    "name:ori_x_preferred":[
        "\u0b2a\u0b3e\u0b09\u0b30\u0b3f"
    ],
    "name:pol_x_preferred":[
        "Pauri"
    ],
    "name:rus_x_preferred":[
        "\u041f\u0430\u0443\u0440\u0438"
    ],
    "name:san_x_preferred":[
        "\u092a\u094c\u0921\u0940"
    ],
    "name:swe_x_preferred":[
        "Pauri"
    ],
    "name:ukr_x_preferred":[
        "\u041f\u0430\u0443\u0440\u0456"
    ],
    "name:und_x_variant":[
        "Jasmi\u0146i"
    ],
    "name:urd_x_preferred":[
        "\u067e\u0648\u0691\u06cc"
    ],
    "name:vie_x_preferred":[
        "Pauri"
    ],
    "wof:name":"Pauri",
    "wof:placetype":"locality"
},
  "geometry": {"coordinates":[26.8172,56.81309],"type":"Point"}
}