{
  "type": "Feature",
  "properties": {
    "gn:admin1_code":"85",
    "gn:admin2_code":"566996.0",
    "gn:asciiname":"Polakas",
    "gn:country_code":"LV",
    "gn:dem":94,
    "gn:feature_class":"P",
    "gn:feature_code":"PPL",
    "gn:name":"Po\u013cakas",
    "gn:population":0,
    "gn:timezone":"Europe/Riga",
    "iso:country":"LV",
    "name:und_x_variant":[
        "Po\u013cakas",
        "Pa\u013cakas",
        "Palakao"
    ],
    "wof:name":"Polakas",
    "wof:placetype":"locality"
},
  "geometry": {"coordinates":[26.0887,56.47363000000001],"type":"Point"}
}