{
  "type": "Feature",
  "properties": {
    "gn:admin1_code":"77",
    "gn:admin2_code":"901292.0",
    "gn:asciiname":"Mazplani",
    "gn:country_code":"LV",
    "gn:dem":134,
    "gn:feature_class":"P",
    "gn:feature_code":"PPL",
    "gn:name":"Mazpl\u0101\u0146i",
    "gn:population":0,
    "gn:timezone":"Europe/Riga",
    "iso:country":"LV",
    "wof:name":"Mazplani",
    "wof:placetype":"locality"
},
  "geometry": {"coordinates":[22.709,56.82863],"type":"Point"}
}