{
  "type": "Feature",
  "properties": {
    "gn:admin1_code":"14",
    "gn:asciiname":"Timani",
    "gn:country_code":"LV",
    "gn:dem":160,
    "gn:feature_class":"P",
    "gn:feature_code":"PPL",
    "gn:name":"T\u012bma\u0146i",
    "gn:population":0,
    "gn:timezone":"Europe/Riga",
    "iso:country":"LV",
    "name:und_x_variant":[
        "Timinova"
    ],
    "wof:name":"Timani",
    "wof:placetype":"locality"
},
  "geometry": {"coordinates":[27.92373,56.14457],"type":"Point"}
}