{
  "type": "Feature",
  "properties": {
    "gn:admin1_code":"07",
    "gn:asciiname":"Krivoselci",
    "gn:cc2":"LV",
    "gn:country_code":"LV",
    "gn:dem":112,
    "gn:feature_class":"P",
    "gn:feature_code":"PPL",
    "gn:name":"Krivose\u013cci",
    "gn:population":0,
    "gn:timezone":"Europe/Riga",
    "iso:country":"LV",
    "name:und_x_variant":[
        "Saulie\u0161i",
        "Krivosel\u2019tsy",
        "Krivase\u013cci",
        "Krivose\u013cci"
    ],
    "wof:name":"Krivoselci",
    "wof:placetype":"locality"
},
  "geometry": {"coordinates":[27.36776,55.8259],"type":"Point"}
}