{
  "type": "Feature",
  "properties": {
    "gn:admin1_code":"14",
    "gn:admin2_code":"600274.0",
    "gn:asciiname":"Lielie Unguri",
    "gn:country_code":"LV",
    "gn:dem":172,
    "gn:feature_class":"P",
    "gn:feature_code":"PPL",
    "gn:name":"Lielie Unguri",
    "gn:population":0,
    "gn:timezone":"Europe/Riga",
    "iso:country":"LV",
    "wof:name":"Lielie Unguri",
    "wof:placetype":"locality"
},
  "geometry": {"coordinates":[27.25004,56.00471999999999],"type":"Point"}
}