{
  "type": "Feature",
  "properties": {
    "gn:admin1_code":"D2",
    "gn:admin2_code":"809600.0",
    "gn:asciiname":"Cekule",
    "gn:country_code":"LV",
    "gn:dem":10,
    "gn:feature_class":"P",
    "gn:feature_code":"PPL",
    "gn:name":"Cekule",
    "gn:population":0,
    "gn:timezone":"Europe/Riga",
    "iso:country":"LV",
    "name:lav_x_preferred":[
        "Cekule"
    ],
    "name:rus_x_preferred":[
        "\u0426\u0435\u043a\u0443\u043b\u0435"
    ],
    "name:und_x_variant":[
        "Jauncekule"
    ],
    "wof:name":"Cekule",
    "wof:placetype":"locality"
},
  "geometry": {"coordinates":[24.41921,56.92171],"type":"Point"}
}