{
  "type": "Feature",
  "properties": {
    "gn:admin1_code":"28",
    "gn:admin2_code":"880274.0",
    "gn:asciiname":"Markciems",
    "gn:country_code":"LV",
    "gn:dem":22,
    "gn:feature_class":"P",
    "gn:feature_code":"PPL",
    "gn:name":"M\u0101rkciems",
    "gn:population":0,
    "gn:timezone":"Europe/Riga",
    "iso:country":"LV",
    "name:und_x_variant":[
        "M\u0101rkas",
        "Maarktsiyems",
        "M\u0101rkciems"
    ],
    "wof:name":"Markciems",
    "wof:placetype":"locality"
},
  "geometry": {"coordinates":[22.72703,57.44371],"type":"Point"}
}