{
  "type": "Feature",
  "properties": {
    "gn:admin1_code":"19",
    "gn:asciiname":"Ranci",
    "gn:country_code":"LV",
    "gn:dem":119,
    "gn:feature_class":"P",
    "gn:feature_code":"PPL",
    "gn:name":"Ran\u010di",
    "gn:population":0,
    "gn:timezone":"Europe/Riga",
    "iso:country":"LV",
    "wof:name":"Ranci",
    "wof:placetype":"locality"
},
  "geometry": {"coordinates":[27.62847,56.73427],"type":"Point"}
}