{
  "type": "Feature",
  "properties": {
    "gn:admin1_code":"27",
    "gn:admin2_code":"840276.0",
    "gn:asciiname":"Veldres",
    "gn:country_code":"LV",
    "gn:dem":92,
    "gn:feature_class":"P",
    "gn:feature_code":"PPL",
    "gn:name":"Veldres",
    "gn:population":0,
    "gn:timezone":"Europe/Riga",
    "iso:country":"LV",
    "name:und_x_variant":[
        "P\u012bpes",
        "P\u012bpji",
        "Veldres"
    ],
    "wof:name":"Veldres",
    "wof:placetype":"locality"
},
  "geometry": {"coordinates":[22.24089,56.5847],"type":"Point"}
}