{
  "type": "Feature",
  "properties": {
    "gn:admin1_code":"E2",
    "gn:admin2_code":"769164.0",
    "gn:asciiname":"Augsmukti",
    "gn:country_code":"LV",
    "gn:dem":95,
    "gn:feature_class":"P",
    "gn:feature_code":"PPL",
    "gn:name":"Aug\u0161mukti",
    "gn:population":0,
    "gn:timezone":"Europe/Riga",
    "iso:country":"LV",
    "wof:name":"Augsmukti",
    "wof:placetype":"locality"
},
  "geometry": {"coordinates":[26.36868,56.26837],"type":"Point"}
}