{
  "type": "Feature",
  "properties": {
    "gn:admin1_code":"22",
    "gn:admin2_code":"760274.0",
    "gn:asciiname":"Prikuli",
    "gn:country_code":"LV",
    "gn:dem":107,
    "gn:feature_class":"P",
    "gn:feature_code":"PPL",
    "gn:name":"Priku\u013ci",
    "gn:population":0,
    "gn:timezone":"Europe/Riga",
    "iso:country":"LV",
    "wof:name":"Prikuli",
    "wof:placetype":"locality"
},
  "geometry": {"coordinates":[26.60065,56.35973000000001],"type":"Point"}
}