{
  "type": "Feature",
  "properties": {
    "gn:admin1_code":"07",
    "gn:admin2_code":"440250.0",
    "gn:asciiname":"Tarzeki",
    "gn:cc2":"LV",
    "gn:country_code":"LV",
    "gn:dem":147,
    "gn:feature_class":"P",
    "gn:feature_code":"PPL",
    "gn:name":"Tar\u017ee\u0137i",
    "gn:population":0,
    "gn:timezone":"Europe/Riga",
    "iso:country":"LV",
    "name:und_x_variant":[
        "Tarzhek",
        "Tar\u017eeks",
        "Tarzheka",
        "Tar\u017eeka",
        "Tar\u017ee\u0137i"
    ],
    "wof:name":"Tarzeki",
    "wof:placetype":"locality"
},
  "geometry": {"coordinates":[26.55,55.71666999999999],"type":"Point"}
}