{
  "type": "Feature",
  "properties": {
    "gn:admin1_code":"24",
    "gn:admin2_code":"780256.0",
    "gn:asciiname":"Starosciki",
    "gn:country_code":"LV",
    "gn:dem":177,
    "gn:feature_class":"P",
    "gn:feature_code":"PPL",
    "gn:name":"Staro\u0161\u010diki",
    "gn:population":0,
    "gn:timezone":"Europe/Riga",
    "iso:country":"LV",
    "wof:name":"Starosciki",
    "wof:placetype":"locality"
},
  "geometry": {"coordinates":[27.36821,56.47588],"type":"Point"}
}