{
  "type": "Feature",
  "properties": {
    "gn:admin1_code":"02",
    "gn:admin2_code":"360268.0",
    "gn:asciiname":"Purnava",
    "gn:country_code":"LV",
    "gn:dem":141,
    "gn:feature_class":"P",
    "gn:feature_code":"PPL",
    "gn:name":"Purnava",
    "gn:population":0,
    "gn:timezone":"Europe/Riga",
    "iso:country":"LV",
    "wof:name":"Purnava",
    "wof:placetype":"locality"
},
  "geometry": {"coordinates":[27.39063,57.37431],"type":"Point"}
}