{
  "type": "Feature",
  "properties": {
    "gn:admin1_code":"02",
    "gn:admin2_code":"360244.0",
    "gn:asciiname":"Anna",
    "gn:cc2":"LV",
    "gn:country_code":"LV",
    "gn:dem":140,
    "gn:feature_class":"P",
    "gn:feature_code":"PPL",
    "gn:name":"Anna",
    "gn:population":0,
    "gn:timezone":"Europe/Riga",
    "iso:country":"LV",
    "name:eng_x_preferred":[
        "Anna"
    ],
    "name:rus_x_preferred":[
        "\u0412\u0435\u0446\u0430\u043d\u043d\u0430"
    ],
    "name:und_x_variant":[
        "Annas",
        "Annas Mui\u017eas Centrs",
        "Anna"
    ],
    "wof:name":"Anna",
    "wof:placetype":"locality"
},
  "geometry": {"coordinates":[27.03333,57.33333],"type":"Point"}
}