{
  "type": "Feature",
  "properties": {
    "gn:admin1_code":"02",
    "gn:admin2_code":"360244.0",
    "gn:asciiname":"Anna",
    "gn:cc2":"LV",
    "gn:country_code":"LV",
    "gn:dem":140,
    "gn:feature_class":"P",
    "gn:feature_code":"PPL",
    "gn:name":"Anna",
    "gn:population":0,
    "gn:timezone":"Europe/Riga",
    "iso:country":"LV",
    "name:ara_x_preferred":[
        "\u0622\u0646\u0627"
    ],
    "name:aze_x_preferred":[
        "Anna"
    ],
    "name:cat_x_preferred":[
        "Anna"
    ],
    "name:ceb_x_preferred":[
        "Anna"
    ],
    "name:ces_x_preferred":[
        "Anna"
    ],
    "name:dan_x_preferred":[
        "Anna"
    ],
    "name:deu_x_preferred":[
        "Anna"
    ],
    "name:eng_x_preferred":[
        "Anna"
    ],
    "name:est_x_preferred":[
        "Anna"
    ],
    "name:fas_x_preferred":[
        "\u0622\u0646\u0627"
    ],
    "name:fin_x_preferred":[
        "Anna"
    ],
    "name:fra_x_preferred":[
        "Anna"
    ],
    "name:glg_x_preferred":[
        "Anna"
    ],
    "name:heb_x_preferred":[
        "\u05d0\u05e0\u05d4"
    ],
    "name:ina_x_preferred":[
        "Anna"
    ],
    "name:ind_x_preferred":[
        "Anna"
    ],
    "name:ita_x_preferred":[
        "Anna"
    ],
    "name:jpn_x_preferred":[
        "\u30a2\u30f3\u30ca"
    ],
    "name:lav_x_preferred":[
        "Anna"
    ],
    "name:nld_x_preferred":[
        "Anna"
    ],
    "name:pol_x_preferred":[
        "Anna"
    ],
    "name:por_x_preferred":[
        "Anna"
    ],
    "name:ron_x_preferred":[
        "Anna"
    ],
    "name:rus_x_preferred":[
        "\u0412\u0435\u0446\u0430\u043d\u043d\u0430"
    ],
    "name:slk_x_preferred":[
        "Anna"
    ],
    "name:spa_x_preferred":[
        "Anna"
    ],
    "name:swe_x_preferred":[
        "Anna"
    ],
    "name:und_x_variant":[
        "Annas",
        "Annas Mui\u017eas Centrs"
    ],
    "name:vie_x_preferred":[
        "Anna"
    ],
    "name:vol_x_preferred":[
        "Anna"
    ],
    "name:zho_x_preferred":[
        "\u5b89\u5a1c"
    ],
    "wof:name":"Anna",
    "wof:placetype":"locality"
},
  "geometry": {"coordinates":[27.03333,57.33333],"type":"Point"}
}