{
  "type": "Feature",
  "properties": {
    "gn:admin1_code":"05",
    "gn:asciiname":"Greiveri",
    "gn:country_code":"LV",
    "gn:dem":218,
    "gn:feature_class":"P",
    "gn:feature_code":"PPL",
    "gn:name":"Greiveri",
    "gn:population":0,
    "gn:timezone":"Europe/Riga",
    "iso:country":"LV",
    "wof:name":"Greiveri",
    "wof:placetype":"locality"
},
  "geometry": {"coordinates":[25.81006,57.10055],"type":"Point"}
}