{
  "type": "Feature",
  "properties": {
    "gn:admin1_code":"18",
    "gn:admin2_code":"660264.0",
    "gn:asciiname":"Jumpravmuiza",
    "gn:country_code":"LV",
    "gn:dem":35,
    "gn:feature_class":"P",
    "gn:feature_code":"PPL",
    "gn:name":"Jumpravmui\u017ea",
    "gn:population":0,
    "gn:timezone":"Europe/Riga",
    "iso:country":"LV",
    "name:lav_x_preferred":[
        "Jumpravas"
    ],
    "name:lav_x_variant":[
        "Jumprava",
        "Jumpravmui\u017ea"
    ],
    "name:und_x_variant":[
        "Yumpravmuyzha"
    ],
    "wof:name":"Jumpravmuiza",
    "wof:placetype":"locality"
},
  "geometry": {"coordinates":[24.60444,57.47821],"type":"Point"}
}