{
  "type": "Feature",
  "properties": {
    "gn:admin1_code":"03",
    "gn:admin2_code":"380266.0",
    "gn:asciiname":"Dukuleva",
    "gn:country_code":"LV",
    "gn:dem":129,
    "gn:feature_class":"P",
    "gn:feature_code":"PPL",
    "gn:name":"Duku\u013ceva",
    "gn:population":0,
    "gn:timezone":"Europe/Riga",
    "iso:country":"LV",
    "name:und_x_variant":[
        "Duku\u013ceva",
        "Duku\u013cava"
    ],
    "wof:name":"Dukuleva",
    "wof:placetype":"locality"
},
  "geometry": {"coordinates":[27.49491,57.04006],"type":"Point"}
}