{
  "type": "Feature",
  "properties": {
    "iso:country":"LV",
    "name:und_x_preferred":[
        "Kazas Seklis"
    ],
    "name:unk_x_variant":[
        "Kazas Seklis"
    ],
    "qs:gn_adm0_cc":"LV",
    "qs:gn_local":456172,
    "qs:local_max":23404,
    "qs:local_sum":42602,
    "qs:localhoods":31,
    "qs:name":"Kazas Seklis",
    "qs:name_adm0":"Latvija",
    "qs:name_adm1":"R\u013cga",
    "qs:name_adm2":"R\u013cga",
    "qs:name_local":"R\u012bga",
    "qs:photo_max":54,
    "qs:photo_sum":141,
    "qs:placetype":"Suburb",
    "qs:quad_count":18,
    "qs:woe_adm0":23424874,
    "qs:woe_adm1":20070121,
    "qs:woe_adm2":55844479,
    "qs:woe_lau":0,
    "qs:woe_local":854823,
    "qs:woe_ver":"7.10.0",
    "wof:lang":[
        "unk"
    ],
    "wof:name":"Kazas Seklis",
    "wof:placetype":"neighbourhood"
},
  "geometry": {"coordinates":[24.13499,56.919289],"type":"Point"}
}