{
  "type": "Feature",
  "properties": {
    "gn:admin1_code":"07",
    "gn:admin2_code":"440296.0",
    "gn:asciiname":"Tartaks",
    "gn:country_code":"LV",
    "gn:dem":162,
    "gn:feature_class":"P",
    "gn:feature_code":"PPL",
    "gn:name":"Tartaks",
    "gn:population":0,
    "gn:timezone":"Europe/Riga",
    "iso:country":"LV",
    "name:und_x_variant":[
        "Tartak",
        "Tartaki",
        "Tartaks"
    ],
    "wof:name":"Tartaks",
    "wof:placetype":"locality"
},
  "geometry": {"coordinates":[26.82906,55.81914],"type":"Point"}
}