{
  "type": "Feature",
  "properties": {
    "gn:admin1_code":"28",
    "gn:admin2_code":"880237.0",
    "gn:asciiname":"Kronmuiza",
    "gn:country_code":"LV",
    "gn:dem":53,
    "gn:feature_class":"P",
    "gn:feature_code":"PPL",
    "gn:name":"Kro\u0146mui\u017ea",
    "gn:population":0,
    "gn:timezone":"Europe/Riga",
    "iso:country":"LV",
    "name:und_x_variant":[
        "Kron\u012b\u0161i",
        "Kron\u2019muyzha",
        "Kro\u0146mui\u017ea"
    ],
    "wof:name":"Kronmuiza",
    "wof:placetype":"locality"
},
  "geometry": {"coordinates":[22.62166,57.37722],"type":"Point"}
}