{
  "type": "Feature",
  "properties": {
    "gn:admin1_code":"03",
    "gn:admin2_code":"380248.0",
    "gn:asciiname":"Dublava",
    "gn:country_code":"LV",
    "gn:dem":120,
    "gn:feature_class":"P",
    "gn:feature_code":"PPL",
    "gn:name":"Dub\u013cava",
    "gn:population":0,
    "gn:timezone":"Europe/Riga",
    "iso:country":"LV",
    "name:eng_x_preferred":[
        "Dub\u013ceva"
    ],
    "name:rus_x_preferred":[
        "\u0414\u0443\u0431\u043b\u0435\u0432\u043e"
    ],
    "name:und_x_variant":[
        "Dub\u013ceva",
        "Dub\u013cava"
    ],
    "wof:name":"Dublava",
    "wof:placetype":"locality"
},
  "geometry": {"coordinates":[27.33786,57.12216],"type":"Point"}
}