{
  "type": "Feature",
  "properties": {
    "gn:admin1_code":"E7",
    "gn:admin2_code":"381678.0",
    "gn:asciiname":"Sosnicas",
    "gn:country_code":"LV",
    "gn:dem":93,
    "gn:feature_class":"P",
    "gn:feature_code":"PPL",
    "gn:name":"Sosn\u012bcas",
    "gn:population":0,
    "gn:timezone":"Europe/Riga",
    "iso:country":"LV",
    "name:und_x_variant":[
        "Sasnitsa",
        "Sosnitsa",
        "Sasnica",
        "Sosnica",
        "Sosn\u012bcas",
        "Sasn\u012bcas"
    ],
    "wof:name":"Sosnicas",
    "wof:placetype":"locality"
},
  "geometry": {"coordinates":[27.734,57.27275],"type":"Point"}
}