{
  "type": "Feature",
  "properties": {
    "gn:admin1_code":"C2",
    "gn:admin2_code":"568786.0",
    "gn:asciiname":"Meldernieki",
    "gn:country_code":"LV",
    "gn:dem":85,
    "gn:feature_class":"P",
    "gn:feature_code":"PPL",
    "gn:name":"Meldernieki",
    "gn:population":0,
    "gn:timezone":"Europe/Riga",
    "iso:country":"LV",
    "name:und_x_variant":[
        "Mel\u2019dernek",
        "Meldernieki"
    ],
    "wof:name":"Meldernieki",
    "wof:placetype":"locality"
},
  "geometry": {"coordinates":[25.80035,56.47622],"type":"Point"}
}