{
  "type": "Feature",
  "properties": {
    "gn:admin1_code":"07",
    "gn:admin2_code":"440260.0",
    "gn:asciiname":"Birkineli",
    "gn:country_code":"LV",
    "gn:dem":137,
    "gn:feature_class":"P",
    "gn:feature_code":"PPL",
    "gn:name":"Birkine\u013ci",
    "gn:population":0,
    "gn:timezone":"Europe/Riga",
    "iso:country":"LV",
    "name:und_x_variant":[
        "Myza Birkinel",
        "Birkine\u013ci",
        "Bikine\u013cu Mui\u017ea",
        "Birkene\u013ci",
        "Berkene\u013ci"
    ],
    "wof:name":"Birkineli",
    "wof:placetype":"locality"
},
  "geometry": {"coordinates":[26.45209,55.81983],"type":"Point"}
}