{
  "type": "Feature",
  "properties": {
    "gn:admin1_code":"09",
    "gn:admin2_code":"500264.0",
    "gn:asciiname":"Kozas",
    "gn:cc2":"LV",
    "gn:country_code":"LV",
    "gn:dem":111,
    "gn:feature_class":"P",
    "gn:feature_code":"PPL",
    "gn:name":"Ko\u017eas",
    "gn:population":0,
    "gn:timezone":"Europe/Riga",
    "iso:country":"LV",
    "name:und_x_variant":[
        "Kozhas",
        "Ko\u017eas"
    ],
    "wof:name":"Kozas",
    "wof:placetype":"locality"
},
  "geometry": {"coordinates":[26.42255,57.27988000000001],"type":"Point"}
}