{
  "type": "Feature",
  "properties": {
    "gn:admin1_code":"04",
    "gn:admin2_code":"400292.0",
    "gn:asciiname":"Kageni",
    "gn:country_code":"LV",
    "gn:dem":34,
    "gn:feature_class":"P",
    "gn:feature_code":"PPL",
    "gn:name":"Ka\u0123eni",
    "gn:population":0,
    "gn:timezone":"Europe/Riga",
    "iso:country":"LV",
    "name:und_x_variant":[
        "Kag\u0123eni",
        "Ka\u0123eni"
    ],
    "wof:name":"Kageni",
    "wof:placetype":"locality"
},
  "geometry": {"coordinates":[24.41574,56.41761],"type":"Point"}
}