{
  "type": "Feature",
  "properties": {
    "gn:admin1_code":"33",
    "gn:admin2_code":"980278.0",
    "gn:asciiname":"Strupiki",
    "gn:country_code":"LV",
    "gn:dem":14,
    "gn:feature_class":"P",
    "gn:feature_code":"PPL",
    "gn:name":"Strupi\u0137i",
    "gn:population":0,
    "gn:timezone":"Europe/Riga",
    "iso:country":"LV",
    "wof:name":"Strupiki",
    "wof:placetype":"locality"
},
  "geometry": {"coordinates":[21.45,57.25],"type":"Point"}
}