{
  "type": "Feature",
  "properties": {
    "gn:admin1_code":"29",
    "gn:admin2_code":"900268.0",
    "gn:asciiname":"Jaunlestene",
    "gn:cc2":"LV",
    "gn:country_code":"LV",
    "gn:dem":65,
    "gn:feature_class":"P",
    "gn:feature_code":"PPL",
    "gn:name":"Jaunlestene",
    "gn:population":0,
    "gn:timezone":"Europe/Riga",
    "iso:country":"LV",
    "name:und_x_variant":[
        "Myza Yaunlestene",
        "Jaunlestenes Mui\u017ea"
    ],
    "wof:name":"Jaunlestene",
    "wof:placetype":"locality"
},
  "geometry": {"coordinates":[23.14278,56.79472],"type":"Point"}
}