{
  "type": "Feature",
  "properties": {
    "gn:admin1_code":"57",
    "gn:admin2_code":"601080.0",
    "gn:asciiname":"Neiksani",
    "gn:country_code":"LV",
    "gn:dem":159,
    "gn:feature_class":"P",
    "gn:feature_code":"PPL",
    "gn:name":"Neik\u0161\u0101ni",
    "gn:population":0,
    "gn:timezone":"Europe/Riga",
    "iso:country":"LV",
    "name:und_x_variant":[
        "Neik\u0161\u0101ni",
        "O\u0161upe"
    ],
    "wof:name":"Neiksani",
    "wof:placetype":"locality"
},
  "geometry": {"coordinates":[27.74886,56.03285],"type":"Point"}
}