{
  "type": "Feature",
  "properties": {
    "gn:admin1_code":"47",
    "gn:admin2_code":"384400.0",
    "gn:asciiname":"Dziervine",
    "gn:country_code":"LV",
    "gn:dem":111,
    "gn:feature_class":"P",
    "gn:feature_code":"PPL",
    "gn:name":"Dzierv\u012bne",
    "gn:population":0,
    "gn:timezone":"Europe/Riga",
    "iso:country":"LV",
    "name:und_x_variant":[
        "Dzierv\u012bne",
        "Dz\u0113rv\u0113ni"
    ],
    "wof:name":"Dziervine",
    "wof:placetype":"locality"
},
  "geometry": {"coordinates":[27.64554,56.87394000000001],"type":"Point"}
}