{
  "type": "Feature",
  "properties": {
    "gn:admin1_code":"07",
    "gn:admin2_code":"440286.0",
    "gn:asciiname":"Senheida",
    "gn:country_code":"LV",
    "gn:dem":156,
    "gn:feature_class":"P",
    "gn:feature_code":"PPL",
    "gn:name":"\u0160\u0113nheida",
    "gn:population":0,
    "gn:timezone":"Europe/Riga",
    "iso:country":"LV",
    "name:und_x_variant":[
        "\u0160\u0113nheida",
        "\u0160engeida"
    ],
    "wof:name":"Senheida",
    "wof:placetype":"locality"
},
  "geometry": {"coordinates":[26.74607,55.75372],"type":"Point"}
}