{
  "type": "Feature",
  "properties": {
    "gn:admin1_code":"78",
    "gn:admin2_code":"681072.0",
    "gn:asciiname":"Ruzori",
    "gn:country_code":"LV",
    "gn:dem":111,
    "gn:feature_class":"P",
    "gn:feature_code":"PPL",
    "gn:name":"R\u016bzori",
    "gn:population":0,
    "gn:timezone":"Europe/Riga",
    "iso:country":"LV",
    "name:und_x_variant":[
        "R\u016bzori",
        "R\u016bzari"
    ],
    "wof:name":"Ruzori",
    "wof:placetype":"locality"
},
  "geometry": {"coordinates":[27.79602,56.68600000000001],"type":"Point"}
}