{
  "type": "Feature",
  "properties": {
    "gn:admin1_code":"22",
    "gn:asciiname":"Beki",
    "gn:country_code":"LV",
    "gn:dem":147,
    "gn:feature_class":"P",
    "gn:feature_code":"PPL",
    "gn:name":"B\u0113\u0137i",
    "gn:population":0,
    "gn:timezone":"Europe/Riga",
    "iso:country":"LV",
    "name:und_x_variant":[
        "Bie\u0137i"
    ],
    "wof:name":"Beki",
    "wof:placetype":"locality"
},
  "geometry": {"coordinates":[26.92715,56.15191],"type":"Point"}
}