{
  "type": "Feature",
  "properties": {
    "gn:admin1_code":"14",
    "gn:admin2_code":"600286.0",
    "gn:asciiname":"Kazinova",
    "gn:country_code":"LV",
    "gn:dem":169,
    "gn:feature_class":"P",
    "gn:feature_code":"PPL",
    "gn:name":"Kazinova",
    "gn:population":0,
    "gn:timezone":"Europe/Riga",
    "iso:country":"LV",
    "wof:name":"Kazinova",
    "wof:placetype":"locality"
},
  "geometry": {"coordinates":[27.58753,55.95564],"type":"Point"}
}