{
  "type": "Feature",
  "properties": {
    "gn:admin1_code":"19",
    "gn:admin2_code":"680292.0",
    "gn:asciiname":"Zirgi",
    "gn:country_code":"LV",
    "gn:dem":184,
    "gn:feature_class":"P",
    "gn:feature_code":"PPL",
    "gn:name":"Zirgi",
    "gn:population":0,
    "gn:timezone":"Europe/Riga",
    "iso:country":"LV",
    "name:und_x_variant":[
        "Zyrgi",
        "Zirgi"
    ],
    "wof:name":"Zirgi",
    "wof:placetype":"locality"
},
  "geometry": {"coordinates":[27.79151,56.25735],"type":"Point"}
}