{
  "type": "Feature",
  "properties": {
    "gn:admin1_code":"B7",
    "gn:admin2_code":"387574.0",
    "gn:asciiname":"Forsteja",
    "gn:country_code":"LV",
    "gn:dem":98,
    "gn:feature_class":"P",
    "gn:feature_code":"PPL",
    "gn:name":"For\u0161teja",
    "gn:population":0,
    "gn:timezone":"Europe/Riga",
    "iso:country":"LV",
    "wof:name":"Forsteja",
    "wof:placetype":"locality"
},
  "geometry": {"coordinates":[27.15707,57.02185],"type":"Point"}
}