{
  "type": "Feature",
  "properties": {
    "gn:admin1_code":"60",
    "gn:admin2_code":"885150.0",
    "gn:asciiname":"Emerkalni",
    "gn:country_code":"LV",
    "gn:dem":23,
    "gn:feature_class":"P",
    "gn:feature_code":"PPL",
    "gn:name":"Emerkalni",
    "gn:population":0,
    "gn:timezone":"Europe/Riga",
    "iso:country":"LV",
    "name:und_x_variant":[
        "Emarkalny",
        "Emarkalni",
        "Emerkalni"
    ],
    "wof:name":"Emerkalni",
    "wof:placetype":"locality"
},
  "geometry": {"coordinates":[22.58333,57.56667],"type":"Point"}
}