{
  "type": "Feature",
  "properties": {
    "gn:admin1_code":"28",
    "gn:asciiname":"Jaunmuiza",
    "gn:cc2":"LV",
    "gn:country_code":"LV",
    "gn:dem":68,
    "gn:feature_class":"P",
    "gn:feature_code":"PPL",
    "gn:name":"Jaunmui\u017ea",
    "gn:population":0,
    "gn:timezone":"Europe/Riga",
    "iso:country":"LV",
    "name:und_x_variant":[
        "Yaunamuizha",
        "Jaun\u0101mui\u017ea",
        "Jaunmui\u017ea"
    ],
    "wof:name":"Jaunmuiza",
    "wof:placetype":"locality"
},
  "geometry": {"coordinates":[22.28628,57.60008000000001],"type":"Point"}
}