{
  "type": "Feature",
  "properties": {
    "gn:admin1_code":"39",
    "gn:admin2_code":"661037.0",
    "gn:asciiname":"Karogi",
    "gn:country_code":"LV",
    "gn:dem":57,
    "gn:feature_class":"P",
    "gn:feature_code":"PPL",
    "gn:name":"Karogi",
    "gn:population":0,
    "gn:timezone":"Europe/Riga",
    "iso:country":"LV",
    "name:und_x_variant":[
        "Karogs",
        "Karogi"
    ],
    "wof:name":"Karogi",
    "wof:placetype":"locality"
},
  "geometry": {"coordinates":[24.7859,57.81254000000001],"type":"Point"}
}