{
  "type": "Feature",
  "properties": {
    "gn:admin1_code":"24",
    "gn:admin2_code":"780262.0",
    "gn:asciiname":"Slakoti",
    "gn:country_code":"LV",
    "gn:dem":164,
    "gn:feature_class":"P",
    "gn:feature_code":"PPL",
    "gn:name":"\u0160\u013cakoti",
    "gn:population":0,
    "gn:timezone":"Europe/Riga",
    "iso:country":"LV",
    "name:und_x_variant":[
        "\u0160\u013cakoti",
        "\u0160lakoli"
    ],
    "wof:name":"Slakoti",
    "wof:placetype":"locality"
},
  "geometry": {"coordinates":[27.50511,56.28621999999999],"type":"Point"}
}