{
  "type": "Feature",
  "properties": {
    "gn:admin1_code":"30",
    "gn:asciiname":"Vadzi",
    "gn:cc2":"LV",
    "gn:country_code":"LV",
    "gn:dem":61,
    "gn:feature_class":"P",
    "gn:feature_code":"PPL",
    "gn:name":"Vad\u017ei",
    "gn:population":0,
    "gn:timezone":"Europe/Riga",
    "iso:country":"LV",
    "name:und_x_variant":[
        "Vadzis",
        "Vad\u017ei"
    ],
    "wof:name":"Vadzi",
    "wof:placetype":"locality"
},
  "geometry": {"coordinates":[25.80852,57.60215],"type":"Point"}
}