{
  "type": "Feature",
  "properties": {
    "gn:admin1_code":"03",
    "gn:admin2_code":"380290.0",
    "gn:asciiname":"Sudarbe",
    "gn:country_code":"LV",
    "gn:dem":116,
    "gn:feature_class":"P",
    "gn:feature_code":"PPL",
    "gn:name":"Sudarbe",
    "gn:population":0,
    "gn:timezone":"Europe/Riga",
    "iso:country":"LV",
    "name:eng_x_preferred":[
        "Sudarbe"
    ],
    "name:rus_x_preferred":[
        "\u0421\u0443\u0434\u0430\u0440\u0431\u0435"
    ],
    "wof:name":"Sudarbe",
    "wof:placetype":"locality"
},
  "geometry": {"coordinates":[27.31916,57.00253000000001],"type":"Point"}
}