{
  "type": "Feature",
  "properties": {
    "gn:admin1_code":"91",
    "gn:admin2_code":"701458.0",
    "gn:asciiname":"Roznieki",
    "gn:country_code":"LV",
    "gn:dem":103,
    "gn:feature_class":"P",
    "gn:feature_code":"PPL",
    "gn:name":"Roznieki",
    "gn:population":0,
    "gn:timezone":"Europe/Riga",
    "iso:country":"LV",
    "name:und_x_variant":[
        "Rozenek",
        "Roznieki"
    ],
    "wof:name":"Roznieki",
    "wof:placetype":"locality"
},
  "geometry": {"coordinates":[26.82839,56.97185],"type":"Point"}
}