{
  "type": "Feature",
  "properties": {
    "gn:admin1_code":"57",
    "gn:admin2_code":"601056.0",
    "gn:asciiname":"Mortini",
    "gn:country_code":"LV",
    "gn:dem":213,
    "gn:feature_class":"P",
    "gn:feature_code":"PPL",
    "gn:name":"Morti\u0146i",
    "gn:population":0,
    "gn:timezone":"Europe/Riga",
    "iso:country":"LV",
    "name:und_x_variant":[
        "Mortani",
        "Morti\u0146i"
    ],
    "wof:name":"Mortini",
    "wof:placetype":"locality"
},
  "geometry": {"coordinates":[27.6592,56.2271],"type":"Point"}
}