{
  "type": "Feature",
  "properties": {
    "gn:admin1_code":"02",
    "gn:admin2_code":"360280.0",
    "gn:asciiname":"Zaiceva",
    "gn:cc2":"LV",
    "gn:country_code":"LV",
    "gn:dem":149,
    "gn:feature_class":"P",
    "gn:feature_code":"PPL",
    "gn:name":"Zaiceva",
    "gn:population":0,
    "gn:timezone":"Europe/Riga",
    "iso:country":"LV",
    "name:eng_x_preferred":[
        "Zaiceva"
    ],
    "name:rus_x_preferred":[
        "\u0417\u0430\u0439\u0446\u0435\u0432\u0430"
    ],
    "name:und_x_variant":[
        "Zaytseva",
        "Zaicevo",
        "Za\u0137i"
    ],
    "wof:name":"Zaiceva",
    "wof:placetype":"locality"
},
  "geometry": {"coordinates":[27.4387,57.46633000000001],"type":"Point"}
}