{
  "type": "Feature",
  "properties": {
    "iso:country":"LV",
    "name:eng_x_preferred":[
        "Myulgraben"
    ],
    "name:eng_x_variant":[
        "Yaunmilgravis",
        "New Milgravis",
        "Jaunm\u012blgr\u0101vis"
    ],
    "name:lav_x_preferred":[
        "Jaunm\u012blgr\u0101vis"
    ],
    "name:lav_x_variant":[
        "Yaunmilgravis"
    ],
    "name:und_x_colloquial":[
        "Jaunmilgravis",
        "Novyy Myul'graben"
    ],
    "name:und_x_preferred":[
        "Jaunm\u012blgr\u0101vis"
    ],
    "name:und_x_variant":[
        "N\u00f3vyy My\u00fal'graben"
    ],
    "name:unk_x_variant":[
        "Jaunm\u012blgr\u0101vis"
    ],
    "qs:gn_adm0_cc":"LV",
    "qs:gn_local":456172,
    "qs:local_max":23404,
    "qs:local_sum":42602,
    "qs:localhoods":31,
    "qs:name":"Jaunm\u012blgr\u0101vis",
    "qs:name_adm0":"Latvija",
    "qs:name_adm1":"R\u013cga",
    "qs:name_adm2":"R\u013cga",
    "qs:name_local":"R\u012bga",
    "qs:photo_max":249,
    "qs:photo_sum":589,
    "qs:placetype":"Suburb",
    "qs:quad_count":25,
    "qs:woe_adm0":23424874,
    "qs:woe_adm1":20070121,
    "qs:woe_adm2":55844479,
    "qs:woe_funk":"Parented by a neighborhood",
    "qs:woe_lau":0,
    "qs:woe_local":854823,
    "qs:woe_ver":"7.10.0",
    "wof:lang":[
        "unk"
    ],
    "wof:name":"Jaunmilgravis",
    "wof:placetype":"neighbourhood"
},
  "geometry": {"coordinates":[24.12795,57.0235],"type":"Point"}
}