{
  "type": "Feature",
  "properties": {
    "gn:admin1_code":"20",
    "gn:admin2_code":"700282.0",
    "gn:asciiname":"Abaine",
    "gn:country_code":"LV",
    "gn:dem":90,
    "gn:feature_class":"P",
    "gn:feature_code":"PPL",
    "gn:name":"Abaine",
    "gn:population":0,
    "gn:timezone":"Europe/Riga",
    "iso:country":"LV",
    "wof:name":"Abaine",
    "wof:placetype":"locality"
},
  "geometry": {"coordinates":[26.86667000000001,56.83333],"type":"Point"}
}