{
  "type": "Feature",
  "properties": {
    "gn:admin1_code":"02",
    "gn:admin2_code":"360276.0",
    "gn:asciiname":"Lejaskrogs",
    "gn:country_code":"LV",
    "gn:dem":163,
    "gn:feature_class":"P",
    "gn:feature_code":"PPL",
    "gn:name":"Lejaskrogs",
    "gn:population":0,
    "gn:timezone":"Europe/Riga",
    "iso:country":"LV",
    "wof:name":"Lejaskrogs",
    "wof:placetype":"locality"
},
  "geometry": {"coordinates":[27.32764,57.49761],"type":"Point"}
}