{
  "type": "Feature",
  "properties": {
    "gn:admin1_code":"03",
    "gn:admin2_code":"380248.0",
    "gn:asciiname":"Berzkalne",
    "gn:country_code":"LV",
    "gn:dem":117,
    "gn:feature_class":"P",
    "gn:feature_code":"PPL",
    "gn:name":"B\u0113rzkalne",
    "gn:population":0,
    "gn:timezone":"Europe/Riga",
    "iso:country":"LV",
    "wof:name":"Berzkalne",
    "wof:placetype":"locality"
},
  "geometry": {"coordinates":[27.3495,57.10367],"type":"Point"}
}