{
  "type": "Feature",
  "properties": {
    "gn:admin1_code":"24",
    "gn:admin2_code":"780296.0",
    "gn:asciiname":"Adamova",
    "gn:country_code":"LV",
    "gn:dem":160,
    "gn:feature_class":"P",
    "gn:feature_code":"PPL",
    "gn:name":"Adamova",
    "gn:population":0,
    "gn:timezone":"Europe/Riga",
    "iso:country":"LV",
    "wof:name":"Adamova",
    "wof:placetype":"locality"
},
  "geometry": {"coordinates":[27.36883,56.56204],"type":"Point"}
}