{
  "type": "Feature",
  "properties": {
    "gn:admin1_code":"22",
    "gn:admin2_code":"760274.0",
    "gn:asciiname":"Lakauski",
    "gn:country_code":"LV",
    "gn:dem":105,
    "gn:feature_class":"P",
    "gn:feature_code":"PPL",
    "gn:name":"Lakauski",
    "gn:population":0,
    "gn:timezone":"Europe/Riga",
    "iso:country":"LV",
    "name:und_x_variant":[
        "Lakauskija",
        "Lakauska",
        "Lakovskoye",
        "Lakauski"
    ],
    "wof:name":"Lakauski",
    "wof:placetype":"locality"
},
  "geometry": {"coordinates":[26.59704,56.37571],"type":"Point"}
}