{
  "type": "Feature",
  "properties": {
    "gn:admin1_code":"E6",
    "gn:admin2_code":"561888.0",
    "gn:asciiname":"Katishi",
    "gn:country_code":"LV",
    "gn:dem":81,
    "gn:feature_class":"P",
    "gn:feature_code":"PPL",
    "gn:name":"Katishi",
    "gn:population":0,
    "gn:timezone":"Europe/Riga",
    "iso:country":"LV",
    "name:und_x_variant":[
        "Ka\u0137\u012b\u0161i",
        "Ka\u0137\u0101\u0161i"
    ],
    "wof:name":"Katishi",
    "wof:placetype":"locality"
},
  "geometry": {"coordinates":[25.33333,56.28333000000001],"type":"Point"}
}