{
  "type": "Feature",
  "properties": {
    "gn:admin1_code":"B1",
    "gn:admin2_code":"427776.0",
    "gn:asciiname":"Bormani",
    "gn:country_code":"LV",
    "gn:dem":164,
    "gn:feature_class":"P",
    "gn:feature_code":"PPL",
    "gn:name":"Borma\u0146i",
    "gn:population":0,
    "gn:timezone":"Europe/Riga",
    "iso:country":"LV",
    "wof:name":"Bormani",
    "wof:placetype":"locality"
},
  "geometry": {"coordinates":[25.6362,57.33841],"type":"Point"}
}