{
  "type": "Feature",
  "properties": {
    "gn:admin1_code":"35",
    "gn:admin2_code":"604342.0",
    "gn:asciiname":"Bruveri",
    "gn:country_code":"LV",
    "gn:dem":168,
    "gn:feature_class":"P",
    "gn:feature_code":"PPL",
    "gn:name":"Br\u016bveri",
    "gn:population":0,
    "gn:timezone":"Europe/Riga",
    "iso:country":"LV",
    "name:und_x_variant":[
        "Br\u016bveri",
        "Briuveri"
    ],
    "wof:name":"Bruveri",
    "wof:placetype":"locality"
},
  "geometry": {"coordinates":[27.03218,56.14281],"type":"Point"}
}