{
  "type": "Feature",
  "properties": {
    "gn:admin1_code":"B9",
    "gn:admin2_code":"407788.0",
    "gn:asciiname":"Svitene",
    "gn:country_code":"LV",
    "gn:dem":34,
    "gn:feature_class":"P",
    "gn:feature_code":"PPL",
    "gn:name":"Svitene",
    "gn:population":0,
    "gn:timezone":"Europe/Riga",
    "iso:country":"LV",
    "name:und_x_variant":[
        "Lielsvitenes Mui\u017ea",
        "Lielsvitene",
        "Lielsvitane",
        "Svitene"
    ],
    "wof:name":"Svitene",
    "wof:placetype":"locality"
},
  "geometry": {"coordinates":[23.92979,56.37577],"type":"Point"}
}