{
  "type": "Feature",
  "properties": {
    "gn:admin1_code":"20",
    "gn:asciiname":"Virdzes",
    "gn:country_code":"LV",
    "gn:dem":209,
    "gn:feature_class":"P",
    "gn:feature_code":"PPL",
    "gn:name":"Virdzes",
    "gn:population":0,
    "gn:timezone":"Europe/Riga",
    "iso:country":"LV",
    "wof:name":"Virdzes",
    "wof:placetype":"locality"
},
  "geometry": {"coordinates":[25.93078,56.93065],"type":"Point"}
}