{
  "type": "Feature",
  "properties": {
    "gn:admin1_code":"03",
    "gn:admin2_code":"380248.0",
    "gn:asciiname":"Filipovs",
    "gn:country_code":"LV",
    "gn:dem":122,
    "gn:feature_class":"P",
    "gn:feature_code":"PPL",
    "gn:name":"Filipovs",
    "gn:population":0,
    "gn:timezone":"Europe/Riga",
    "iso:country":"LV",
    "wof:name":"Filipovs",
    "wof:placetype":"locality"
},
  "geometry": {"coordinates":[27.38333,57.15],"type":"Point"}
}