{
  "type": "Feature",
  "properties": {
    "gn:admin1_code":"69",
    "gn:admin2_code":"440880.0",
    "gn:asciiname":"Baltini",
    "gn:country_code":"LV",
    "gn:dem":129,
    "gn:feature_class":"P",
    "gn:feature_code":"PPL",
    "gn:name":"Baltini",
    "gn:population":0,
    "gn:timezone":"Europe/Riga",
    "iso:country":"LV",
    "wof:name":"Baltini",
    "wof:placetype":"locality"
},
  "geometry": {"coordinates":[26.21033,56.03185],"type":"Point"}
}