{
  "type": "Feature",
  "properties": {
    "gn:admin1_code":"03",
    "gn:admin2_code":"380256.0",
    "gn:asciiname":"Zogi",
    "gn:country_code":"LV",
    "gn:dem":99,
    "gn:feature_class":"P",
    "gn:feature_code":"PPL",
    "gn:name":"\u017dogi",
    "gn:population":0,
    "gn:timezone":"Europe/Riga",
    "iso:country":"LV",
    "wof:name":"Zogi",
    "wof:placetype":"locality"
},
  "geometry": {"coordinates":[27.30563,56.81795],"type":"Point"}
}