{
  "type": "Feature",
  "properties": {
    "gn:admin1_code":"E7",
    "gn:admin2_code":"381682.0",
    "gn:asciiname":"Fabriki",
    "gn:country_code":"LV",
    "gn:dem":107,
    "gn:feature_class":"P",
    "gn:feature_code":"PPL",
    "gn:name":"Fabriki",
    "gn:population":0,
    "gn:timezone":"Europe/Riga",
    "iso:country":"LV",
    "name:und_x_variant":[
        "Yaun-Fabrika",
        "Fabriki"
    ],
    "wof:name":"Fabriki",
    "wof:placetype":"locality"
},
  "geometry": {"coordinates":[27.63172,57.07937],"type":"Point"}
}