{
  "type": "Feature",
  "properties": {
    "gn:admin1_code":"25",
    "gn:admin2_code":"10000.0",
    "gn:asciiname":"Bikernieki",
    "gn:cc2":"LV",
    "gn:country_code":"LV",
    "gn:dem":23,
    "gn:feature_class":"P",
    "gn:feature_code":"PPL",
    "gn:name":"Bi\u0137ernieki",
    "gn:population":0,
    "gn:timezone":"Europe/Riga",
    "iso:country":"LV",
    "name:und_x_variant":[
        "Biterniyeki",
        "Bityerneku"
    ],
    "wof:name":"Bikernieki",
    "wof:placetype":"locality"
},
  "geometry": {"coordinates":[24.25,56.96666999999999],"type":"Point"}
}