{
  "type": "Feature",
  "properties": {
    "gn:admin1_code":"02",
    "gn:admin2_code":"360280.0",
    "gn:asciiname":"Kalnapededze",
    "gn:country_code":"LV",
    "gn:dem":160,
    "gn:feature_class":"P",
    "gn:feature_code":"PPL",
    "gn:name":"Kalnapededze",
    "gn:population":0,
    "gn:timezone":"Europe/Riga",
    "iso:country":"LV",
    "name:und_x_variant":[
        "Myza Kalnpededze",
        "Kalnpededze",
        "Kalnapededze"
    ],
    "wof:name":"Kalnapededze",
    "wof:placetype":"locality"
},
  "geometry": {"coordinates":[27.37397,57.51677],"type":"Point"}
}