{
  "type": "Feature",
  "properties": {
    "gn:admin1_code":"29",
    "gn:admin2_code":"900254.0",
    "gn:asciiname":"Vaski",
    "gn:country_code":"LV",
    "gn:dem":68,
    "gn:feature_class":"P",
    "gn:feature_code":"PPL",
    "gn:name":"Vaski",
    "gn:population":0,
    "gn:timezone":"Europe/Riga",
    "iso:country":"LV",
    "name:und_x_variant":[
        "Myza Irlava",
        "Irlava",
        "Sovkhoz Irlava",
        "Irlavas Mui\u017ea",
        "Vaski"
    ],
    "wof:name":"Vaski",
    "wof:placetype":"locality"
},
  "geometry": {"coordinates":[23.04014,56.84148],"type":"Point"}
}