{
  "type": "Feature",
  "properties": {
    "gn:admin1_code":"39",
    "gn:admin2_code":"661037.0",
    "gn:asciiname":"Myza Viti",
    "gn:country_code":"LV",
    "gn:dem":49,
    "gn:feature_class":"P",
    "gn:feature_code":"PPL",
    "gn:name":"Myza Viti",
    "gn:population":0,
    "gn:timezone":"Europe/Riga",
    "iso:country":"LV",
    "name:eng_x_preferred":[
        "V\u012b\u0137i"
    ],
    "name:rus_x_preferred":[
        "\u0412\u0438\u043a\u0438"
    ],
    "name:und_x_variant":[
        "V\u012b\u0137u Mui\u017ea",
        "V\u012b\u0137u Mui\u017eas Centrs"
    ],
    "wof:name":"Myza Viti",
    "wof:placetype":"locality"
},
  "geometry": {"coordinates":[24.80083,57.86224],"type":"Point"}
}