{
  "type": "Feature",
  "properties": {
    "gn:admin1_code":"24",
    "gn:admin2_code":"780296.0",
    "gn:asciiname":"Burzova",
    "gn:country_code":"LV",
    "gn:dem":159,
    "gn:feature_class":"P",
    "gn:feature_code":"PPL",
    "gn:name":"Burzova",
    "gn:population":0,
    "gn:timezone":"Europe/Riga",
    "iso:country":"LV",
    "wof:name":"Burzova",
    "wof:placetype":"locality"
},
  "geometry": {"coordinates":[27.33948,56.58988000000001],"type":"Point"}
}