{
  "type": "Feature",
  "properties": {
    "gn:admin1_code":"02",
    "gn:admin2_code":"360256.0",
    "gn:asciiname":"Kolbergis",
    "gn:country_code":"LV",
    "gn:dem":192,
    "gn:feature_class":"P",
    "gn:feature_code":"PPL",
    "gn:name":"Kolber\u0123is",
    "gn:population":0,
    "gn:timezone":"Europe/Riga",
    "iso:country":"LV",
    "name:und_x_variant":[
        "Myza Kolbergi",
        "Kolber\u0123is",
        "Kolber\u0123i"
    ],
    "wof:name":"Kolbergis",
    "wof:placetype":"locality"
},
  "geometry": {"coordinates":[27.1158,57.43869],"type":"Point"}
}