{
  "type": "Feature",
  "properties": {
    "gn:gn_country":"LV",
    "gn:gn_fcode":"PPL",
    "gn:gn_pop":320,
    "gn:population":320,
    "iso:country":"LV",
    "name:dut_x_preferred":[
        "\u0136\u016b\u013cciems"
    ],
    "name:eng_x_preferred":[
        "\u0136\u016b\u013cciems"
    ],
    "name:lav_x_preferred":[
        "\u0136\u016b\u013cciems"
    ],
    "name:unk_x_variant":[
        "Tul\u2019tsiems"
    ],
    "qs_pg:aaroncc":"LV",
    "qs_pg:gn_country":"LV",
    "qs_pg:gn_fcode":"PPL",
    "qs_pg:gn_pop":320,
    "qs_pg:name":"\u0136u\u013cciems",
    "qs_pg:name_adm0":"Latvija",
    "qs_pg:name_adm1":"Talsi Novads",
    "qs_pg:photos_9r":0,
    "qs_pg:photos_sr":0,
    "qs_pg:pop_sr":2,
    "qs_pg:qs_pg_placetype":"locality",
    "qs_pg:qs_pg_placetype_gp":"Town",
    "qs_pg:woe_adm0":23424874,
    "woe:adm0_id":23424874,
    "woe:name_adm0":"Latvija",
    "woe:name_adm1":"Talsi Novads",
    "woe:placetype":"Town",
    "wof:name":"\u0136u\u013cciems",
    "wof:placetype":"locality",
    "wof:population":320
},
  "geometry": {"coordinates":[23.03194,57.26556],"type":"Point"}
}