{
  "type": "Feature",
  "properties": {
    "gn:admin1_code":"71",
    "gn:admin2_code":"321086.0",
    "gn:asciiname":"Pikslauki",
    "gn:country_code":"LV",
    "gn:dem":114,
    "gn:feature_class":"P",
    "gn:feature_code":"PPL",
    "gn:name":"Pikslauki",
    "gn:population":0,
    "gn:timezone":"Europe/Riga",
    "iso:country":"LV",
    "name:und_x_variant":[
        "Myza Pikstern",
        "Pikstere",
        "Pikslauki"
    ],
    "wof:name":"Pikslauki",
    "wof:placetype":"locality"
},
  "geometry": {"coordinates":[25.55139,56.47196],"type":"Point"}
}