{
  "type": "Feature",
  "properties": {
    "iso:country":"LV",
    "name:ceb_x_preferred":[
        "Dzintari"
    ],
    "name:eng_x_preferred":[
        "Edinburg"
    ],
    "name:eng_x_variant":[
        "Dzhintari",
        "Edinburga",
        "Dzintari"
    ],
    "name:est_x_preferred":[
        "Dzintari"
    ],
    "name:lav_x_preferred":[
        "Dzintari"
    ],
    "name:rus_x_preferred":[
        "\u0414\u0437\u0438\u043d\u0442\u0430\u0440\u0438"
    ],
    "name:swe_x_preferred":[
        "Dzintari"
    ],
    "qs:gn_adm0_cc":"LV",
    "qs:gn_fcode":"PPLX",
    "qs:gn_local":459201,
    "qs:gn_nam_loc":"jurmala",
    "qs:gn_namadm1":"13",
    "qs:gn_name":"Dzintari",
    "qs:local_max":729,
    "qs:local_sum":1749,
    "qs:localhoods":6,
    "qs:name":"Dzintari",
    "qs:name_adm0":"Latvija",
    "qs:name_adm1":"J\u017ermala",
    "qs:name_adm2":"J\u017ermala",
    "qs:name_en":"Edinburg",
    "qs:name_local":"J\u016brmala",
    "qs:photo_max":62,
    "qs:photo_sum":729,
    "qs:placetype":"Suburb",
    "qs:quad_count":49,
    "qs:woe_adm0":23424874,
    "qs:woe_adm1":20070119,
    "qs:woe_adm2":55844547,
    "qs:woe_lau":0,
    "qs:woe_local":852880,
    "qs:woe_ver":"7.10.0",
    "wd:wordcount":138,
    "wof:lang":[
        "unk"
    ],
    "wof:name":"Dzintari",
    "wof:placetype":"neighbourhood"
},
  "geometry": {"coordinates":[23.828735,56.976186],"type":"Point"}
}