{
  "type": "Feature",
  "properties": {
    "gn:admin1_code":"07",
    "gn:admin2_code":"440294.0",
    "gn:asciiname":"Zascenku Vaideri",
    "gn:country_code":"LV",
    "gn:dem":103,
    "gn:feature_class":"P",
    "gn:feature_code":"PPL",
    "gn:name":"Zascenku Vaideri",
    "gn:population":0,
    "gn:timezone":"Europe/Riga",
    "iso:country":"LV",
    "name:und_x_variant":[
        "Vaideri"
    ],
    "wof:name":"Zascenku Vaideri",
    "wof:placetype":"locality"
},
  "geometry": {"coordinates":[26.44788,56.04198],"type":"Point"}
}