{
  "type": "Feature",
  "properties": {
    "gn:admin1_code":"28",
    "gn:admin2_code":"880272.0",
    "gn:asciiname":"Purgali",
    "gn:country_code":"LV",
    "gn:dem":108,
    "gn:feature_class":"P",
    "gn:feature_code":"PPL",
    "gn:name":"Purgali",
    "gn:population":0,
    "gn:timezone":"Europe/Riga",
    "iso:country":"LV",
    "name:lav_x_preferred":[
        "Purgalciems"
    ],
    "wof:name":"Purgali",
    "wof:placetype":"locality"
},
  "geometry": {"coordinates":[22.59725,57.1725],"type":"Point"}
}