{
  "type": "Feature",
  "properties": {
    "gn:gn_country":"LV",
    "gn:gn_fcode":"PPL",
    "gn:gn_pop":0,
    "iso:country":"LV",
    "name:dan_x_preferred":[
        "L\u016b\u017e\u0146a"
    ],
    "name:dut_x_preferred":[
        "L\u016b\u017e\u0146a"
    ],
    "name:eng_x_preferred":[
        "L\u016b\u017e\u0146a"
    ],
    "name:est_x_preferred":[
        "L\u016b\u017e"
    ],
    "name:fin_x_preferred":[
        "L\u016b\u017e\u0146a"
    ],
    "name:lav_x_preferred":[
        "L\u016b\u017e\u0146a"
    ],
    "name:lit_x_preferred":[
        "L\u016b\u017enia"
    ],
    "name:rus_x_preferred":[
        "\u041b\u0443\u0436\u043d\u044f"
    ],
    "name:unk_x_variant":[
        "Luzhna"
    ],
    "qs_pg:aaroncc":"LV",
    "qs_pg:gn_country":"LV",
    "qs_pg:gn_fcode":"PPL",
    "qs_pg:gn_pop":0,
    "qs_pg:name":"L\u016b\u017e\u0146as",
    "qs_pg:name_adm0":"Latvija",
    "qs_pg:name_adm1":"Ventspils Novads",
    "qs_pg:photos":52,
    "qs_pg:photos_1k":11,
    "qs_pg:photos_9k":1,
    "qs_pg:photos_9r":2,
    "qs_pg:photos_all":52,
    "qs_pg:photos_sr":2,
    "qs_pg:pop_sr":0,
    "qs_pg:qs_pg_placetype":"locality",
    "qs_pg:qs_pg_placetype_gp":"Town",
    "qs_pg:woe_adm0":23424874,
    "woe:adm0_id":23424874,
    "woe:name_adm0":"Latvija",
    "woe:name_adm1":"Ventspils Novads",
    "woe:placetype":"Town",
    "wof:name":"L\u016b\u017e\u0146as",
    "wof:placetype":"locality"
},
  "geometry": {"coordinates":[21.88416,57.59463],"type":"Point"}
}