{
  "type": "Feature",
  "properties": {
    "gn:admin1_code":"D1",
    "gn:admin2_code":"941670.0",
    "gn:asciiname":"Silva",
    "gn:country_code":"LV",
    "gn:dem":136,
    "gn:feature_class":"P",
    "gn:feature_code":"PPL",
    "gn:name":"Silva",
    "gn:population":0,
    "gn:timezone":"Europe/Riga",
    "iso:country":"LV",
    "wof:name":"Silva",
    "wof:placetype":"locality"
},
  "geometry": {"coordinates":[25.93501,57.41309],"type":"Point"}
}