{
  "type": "Feature",
  "properties": {
    "gn:admin1_code":"D1",
    "gn:admin2_code":"941670.0",
    "gn:asciiname":"Silva",
    "gn:country_code":"LV",
    "gn:dem":136,
    "gn:feature_class":"P",
    "gn:feature_code":"PPL",
    "gn:name":"Silva",
    "gn:population":0,
    "gn:timezone":"Europe/Riga",
    "iso:country":"LV",
    "name:ces_x_preferred":[
        "Silva"
    ],
    "name:deu_x_preferred":[
        "Silva"
    ],
    "name:fin_x_preferred":[
        "Silva"
    ],
    "name:fra_x_preferred":[
        "Silva"
    ],
    "name:glg_x_preferred":[
        "Silva"
    ],
    "name:nld_x_preferred":[
        "Silva"
    ],
    "name:por_x_preferred":[
        "Silva"
    ],
    "name:spa_x_preferred":[
        "Silva"
    ],
    "name:ukr_x_preferred":[
        "\u0421\u0456\u043b\u0432\u0430"
    ],
    "name:zho_x_preferred":[
        "\u5e2d\u5c14\u74e6"
    ],
    "wof:name":"Silva",
    "wof:placetype":"locality"
},
  "geometry": {"coordinates":[25.93501,57.41309],"type":"Point"}
}