{
  "type": "Feature",
  "properties": {
    "gn:admin1_code":"18",
    "gn:admin2_code":"660288.0",
    "gn:asciiname":"Kirbizi",
    "gn:country_code":"LV",
    "gn:dem":31,
    "gn:feature_class":"P",
    "gn:feature_code":"PPL",
    "gn:name":"\u0136irbi\u017ei",
    "gn:population":0,
    "gn:timezone":"Europe/Riga",
    "iso:country":"LV",
    "name:eng_x_preferred":[
        "\u0136irbi\u017ei"
    ],
    "name:rus_x_preferred":[
        "\u041a\u0438\u0440\u0431\u0438\u0436\u0438"
    ],
    "name:und_x_variant":[
        "Myza Tribizhi",
        "\u0136irbi\u017eu Mui\u017ea",
        "Kiberi",
        "Kirbizhi"
    ],
    "wof:name":"Kirbizi",
    "wof:placetype":"locality"
},
  "geometry": {"coordinates":[24.49588,57.65008],"type":"Point"}
}