{
  "type": "Feature",
  "properties": {
    "gn:admin1_code":"E7",
    "gn:admin2_code":"381682.0",
    "gn:asciiname":"Mukausova",
    "gn:country_code":"LV",
    "gn:dem":98,
    "gn:feature_class":"P",
    "gn:feature_code":"PPL",
    "gn:name":"Mukau\u0161ova",
    "gn:population":0,
    "gn:timezone":"Europe/Riga",
    "iso:country":"LV",
    "name:und_x_variant":[
        "Muka\u0161i",
        "Mukashi",
        "Muko\u0161eva",
        "Mukau\u0161ova"
    ],
    "wof:name":"Mukausova",
    "wof:placetype":"locality"
},
  "geometry": {"coordinates":[27.67015,57.01844000000001],"type":"Point"}
}