{
  "type": "Feature",
  "properties": {
    "gn:admin1_code":"20",
    "gn:admin2_code":"700282.0",
    "gn:asciiname":"Rupsala",
    "gn:country_code":"LV",
    "gn:dem":96,
    "gn:feature_class":"P",
    "gn:feature_code":"PPL",
    "gn:name":"Rupsala",
    "gn:population":0,
    "gn:timezone":"Europe/Riga",
    "iso:country":"LV",
    "name:und_x_variant":[
        "Rupsalas"
    ],
    "wof:name":"Rupsala",
    "wof:placetype":"locality"
},
  "geometry": {"coordinates":[26.72005,56.86573000000001],"type":"Point"}
}