{
  "type": "Feature",
  "properties": {
    "gn:admin1_code":"09",
    "gn:admin2_code":"500256.0",
    "gn:asciiname":"Galgauska",
    "gn:cc2":"LV",
    "gn:country_code":"LV",
    "gn:dem":119,
    "gn:feature_class":"P",
    "gn:feature_code":"PPL",
    "gn:name":"Galgauska",
    "gn:population":0,
    "gn:timezone":"Europe/Riga",
    "iso:country":"LV",
    "name:und_x_variant":[
        "Vei\u0161i",
        "Myza Galgauska",
        "Galgauska"
    ],
    "wof:name":"Galgauska",
    "wof:placetype":"locality"
},
  "geometry": {"coordinates":[26.55147,57.16687],"type":"Point"}
}