{
  "type": "Feature",
  "properties": {
    "gn:admin1_code":"14",
    "gn:asciiname":"Armani",
    "gn:country_code":"LV",
    "gn:dem":179,
    "gn:feature_class":"P",
    "gn:feature_code":"PPL",
    "gn:name":"\u0100rma\u0146i",
    "gn:population":0,
    "gn:timezone":"Europe/Riga",
    "iso:country":"LV",
    "wof:name":"Armani",
    "wof:placetype":"locality"
},
  "geometry": {"coordinates":[27.59079,56.18202],"type":"Point"}
}