{
  "type": "Feature",
  "properties": {
    "gn:admin1_code":"14",
    "gn:asciiname":"Armani",
    "gn:country_code":"LV",
    "gn:dem":179,
    "gn:feature_class":"P",
    "gn:feature_code":"PPL",
    "gn:name":"\u0100rma\u0146i",
    "gn:population":0,
    "gn:timezone":"Europe/Riga",
    "iso:country":"LV",
    "name:ara_x_preferred":[
        "\u0623\u0631\u0645\u0627\u0646\u064a"
    ],
    "name:ast_x_preferred":[
        "Armani"
    ],
    "name:azb_x_preferred":[
        "\u0622\u0631\u0645\u0627\u0646\u06cc"
    ],
    "name:bul_x_preferred":[
        "\u0410\u0440\u043c\u0430\u043d\u0438"
    ],
    "name:ces_x_preferred":[
        "Armani"
    ],
    "name:dan_x_preferred":[
        "Armani"
    ],
    "name:ell_x_preferred":[
        "\u0391\u03c1\u03bc\u03ac\u03bd\u03b9"
    ],
    "name:fas_x_preferred":[
        "\u0622\u0631\u0645\u0627\u0646\u06cc"
    ],
    "name:fra_x_preferred":[
        "Giorgio Armani"
    ],
    "name:gan_x_preferred":[
        "Armani"
    ],
    "name:guj_x_preferred":[
        "\u0a85\u0ab0\u0aae\u0abe\u0aa8\u0ac0"
    ],
    "name:heb_x_preferred":[
        "\u05d0\u05e8\u05de\u05e0\u05d9"
    ],
    "name:hye_x_preferred":[
        "Giorgio Armani"
    ],
    "name:ita_x_preferred":[
        "Giorgio Armani"
    ],
    "name:jpn_x_preferred":[
        "\u30a2\u30eb\u30de\u30fc\u30cb"
    ],
    "name:kor_x_preferred":[
        "\uc544\ub974\ub9c8\ub2c8"
    ],
    "name:lit_x_preferred":[
        "Armani"
    ],
    "name:mkd_x_preferred":[
        "\u0410\u0440\u043c\u0430\u043d\u0438"
    ],
    "name:nld_x_preferred":[
        "Armani"
    ],
    "name:pan_x_preferred":[
        "\u0a06\u0a30\u0a2e\u0a3e\u0a28\u0a40"
    ],
    "name:pnb_x_preferred":[
        "\u0622\u0631\u0645\u0627\u0646\u06cc"
    ],
    "name:pol_x_preferred":[
        "Giorgio Armani"
    ],
    "name:por_x_preferred":[
        "Armani"
    ],
    "name:ron_x_preferred":[
        "Armani"
    ],
    "name:rus_x_preferred":[
        "Giorgio Armani"
    ],
    "name:spa_x_preferred":[
        "Armani"
    ],
    "name:swe_x_preferred":[
        "Armani"
    ],
    "name:tur_x_preferred":[
        "Giorgio Armani"
    ],
    "name:ukr_x_preferred":[
        "Giorgio Armani"
    ],
    "name:vie_x_preferred":[
        "Armani"
    ],
    "name:zho_x_preferred":[
        "\u4e9e\u66fc\u5c3c"
    ],
    "wof:name":"Armani",
    "wof:placetype":"locality"
},
  "geometry": {"coordinates":[27.59079,56.18202],"type":"Point"}
}