{
  "type": "Feature",
  "properties": {
    "gn:admin1_code":"33",
    "gn:admin2_code":"980278.0",
    "gn:asciiname":"Lagzdini",
    "gn:country_code":"LV",
    "gn:dem":6,
    "gn:feature_class":"P",
    "gn:feature_code":"PPL",
    "gn:name":"Lagzdi\u0146i",
    "gn:population":0,
    "gn:timezone":"Europe/Riga",
    "iso:country":"LV",
    "wof:name":"Lagzdini",
    "wof:placetype":"locality"
},
  "geometry": {"coordinates":[21.45,57.16667],"type":"Point"}
}