{
  "type": "Feature",
  "properties": {
    "gn:admin1_code":"12",
    "gn:admin2_code":"540286.0",
    "gn:asciiname":"Ketleri",
    "gn:cc2":"LV",
    "gn:country_code":"LV",
    "gn:dem":14,
    "gn:feature_class":"P",
    "gn:feature_code":"PPL",
    "gn:name":"\u0136etl\u0113ri",
    "gn:population":0,
    "gn:timezone":"Europe/Riga",
    "iso:country":"LV",
    "name:und_x_variant":[
        "Tetleri"
    ],
    "wof:name":"Ketleri",
    "wof:placetype":"locality"
},
  "geometry": {"coordinates":[23.68333,56.78333000000001],"type":"Point"}
}