{
  "type": "Feature",
  "properties": {
    "gn:admin1_code":"56",
    "gn:admin2_code":"684948.0",
    "gn:asciiname":"Zeltini",
    "gn:country_code":"LV",
    "gn:dem":120,
    "gn:feature_class":"P",
    "gn:feature_code":"PPL",
    "gn:name":"Zelti\u0146i",
    "gn:population":0,
    "gn:timezone":"Europe/Riga",
    "iso:country":"LV",
    "name:und_x_variant":[
        "Zelte\u0146",
        "Zelti\u0146i",
        "Ze\u013cte\u0146i"
    ],
    "wof:name":"Zeltini",
    "wof:placetype":"locality"
},
  "geometry": {"coordinates":[27.89007,56.54841],"type":"Point"}
}