{
  "type": "Feature",
  "properties": {
    "gn:admin1_code":"60",
    "gn:admin2_code":"885150.0",
    "gn:asciiname":"Lauki",
    "gn:country_code":"LV",
    "gn:dem":75,
    "gn:feature_class":"P",
    "gn:feature_code":"PPL",
    "gn:name":"Lauki",
    "gn:population":0,
    "gn:timezone":"Europe/Riga",
    "iso:country":"LV",
    "wof:name":"Lauki",
    "wof:placetype":"locality"
},
  "geometry": {"coordinates":[22.45767,57.60086999999999],"type":"Point"}
}