{
  "type": "Feature",
  "properties": {
    "gn:admin1_code":"27",
    "gn:admin2_code":"840276.0",
    "gn:asciiname":"Aunini",
    "gn:country_code":"LV",
    "gn:dem":100,
    "gn:feature_class":"P",
    "gn:feature_code":"PPL",
    "gn:name":"Auni\u0146i",
    "gn:population":0,
    "gn:timezone":"Europe/Riga",
    "iso:country":"LV",
    "wof:name":"Aunini",
    "wof:placetype":"locality"
},
  "geometry": {"coordinates":[22.19758,56.56847],"type":"Point"}
}