{
  "type": "Feature",
  "properties": {
    "gn:admin1_code":"18",
    "gn:asciiname":"Stali",
    "gn:country_code":"LV",
    "gn:dem":80,
    "gn:feature_class":"P",
    "gn:feature_code":"PPL",
    "gn:name":"Sta\u013ci",
    "gn:population":0,
    "gn:timezone":"Europe/Riga",
    "iso:country":"LV",
    "wof:name":"Stali",
    "wof:placetype":"locality"
},
  "geometry": {"coordinates":[25.75745,57.8622],"type":"Point"}
}