{
  "type": "Feature",
  "properties": {
    "gn:admin1_code":"33",
    "gn:admin2_code":"980290.0",
    "gn:asciiname":"Vendzavas",
    "gn:cc2":"LV",
    "gn:country_code":"LV",
    "gn:dem":7,
    "gn:feature_class":"P",
    "gn:feature_code":"PPL",
    "gn:name":"Vendzavas",
    "gn:population":0,
    "gn:timezone":"Europe/Riga",
    "iso:country":"LV",
    "name:und_x_variant":[
        "Vendzava",
        "Myza Vendzava",
        "Vendava",
        "Vendzava Mui\u017eas Centrs",
        "Venzava",
        "Vendzavas"
    ],
    "wof:name":"Vendzavas",
    "wof:placetype":"locality"
},
  "geometry": {"coordinates":[21.67405,57.17878],"type":"Point"}
}