{
  "type": "Feature",
  "properties": {
    "gn:admin1_code":"28",
    "gn:admin2_code":"880270.0",
    "gn:asciiname":"Myza Shtede",
    "gn:country_code":"LV",
    "gn:dem":67,
    "gn:feature_class":"P",
    "gn:feature_code":"PPL",
    "gn:name":"Myza Shtede",
    "gn:population":0,
    "gn:timezone":"Europe/Riga",
    "iso:country":"LV",
    "name:und_x_variant":[
        "\u0160\u0137\u0113des",
        "\u0160\u0137ede Mui\u017eas Centrs",
        "\u0160\u0137\u0113de"
    ],
    "wof:name":"Myza Shtede",
    "wof:placetype":"locality"
},
  "geometry": {"coordinates":[22.73194,57.25589],"type":"Point"}
}