{
  "type": "Feature",
  "properties": {
    "gn:admin1_code":"24",
    "gn:admin2_code":"780250.0",
    "gn:asciiname":"Taunaga",
    "gn:country_code":"LV",
    "gn:dem":115,
    "gn:feature_class":"P",
    "gn:feature_code":"PPL",
    "gn:name":"Taunaga",
    "gn:population":0,
    "gn:timezone":"Europe/Riga",
    "iso:country":"LV",
    "name:und_x_variant":[
        "Yaunlesna",
        "Taunoga",
        "Taunaga"
    ],
    "wof:name":"Taunaga",
    "wof:placetype":"locality"
},
  "geometry": {"coordinates":[27.20791,56.67985],"type":"Point"}
}