{
  "type": "Feature",
  "properties": {
    "gn:admin1_code":"24",
    "gn:admin2_code":"780246.0",
    "gn:asciiname":"Baltais Dukstigals",
    "gn:country_code":"LV",
    "gn:dem":171,
    "gn:feature_class":"P",
    "gn:feature_code":"PPL",
    "gn:name":"Baltais Dukstigals",
    "gn:population":0,
    "gn:timezone":"Europe/Riga",
    "iso:country":"LV",
    "name:und_x_variant":[
        "Dukstigala Pusmui\u017ea",
        "Dukstigale",
        "Balta Dukstigala",
        "Baltais Dukstgals",
        "Baltais Dukstigals"
    ],
    "wof:name":"Baltais Dukstigals",
    "wof:placetype":"locality"
},
  "geometry": {"coordinates":[27.43799000000001,56.37229],"type":"Point"}
}