{
  "type": "Feature",
  "properties": {
    "gn:admin1_code":"03",
    "gn:admin2_code":"380258.0",
    "gn:asciiname":"Kurna",
    "gn:country_code":"LV",
    "gn:dem":112,
    "gn:feature_class":"P",
    "gn:feature_code":"PPL",
    "gn:name":"Kurna",
    "gn:population":0,
    "gn:timezone":"Europe/Riga",
    "iso:country":"LV",
    "name:eng_x_preferred":[
        "Kurna"
    ],
    "name:rus_x_preferred":[
        "\u041a\u0443\u0440\u043d\u0430"
    ],
    "wof:name":"Kurna",
    "wof:placetype":"locality"
},
  "geometry": {"coordinates":[27.21062,57.14454],"type":"Point"}
}