{
  "type": "Feature",
  "properties": {
    "gn:admin1_code":"42",
    "gn:admin2_code":"424742.0",
    "gn:asciiname":"Amatas Skola",
    "gn:country_code":"LV",
    "gn:dem":187,
    "gn:feature_class":"P",
    "gn:feature_code":"PPL",
    "gn:name":"Amatas Skola",
    "gn:population":0,
    "gn:timezone":"Europe/Riga",
    "iso:country":"LV",
    "name:und_x_variant":[
        "Doli",
        "Doles",
        "Vecdoles",
        "Amatas Skola"
    ],
    "wof:name":"Amatas Skola",
    "wof:placetype":"locality"
},
  "geometry": {"coordinates":[25.27734,57.16728000000001],"type":"Point"}
}