{
  "type": "Feature",
  "properties": {
    "gn:country":"LV",
    "gn:fcode":"PPL",
    "gn:population":70,
    "iso:country":"LV",
    "name:eng_x_preferred":[
        "Abragciems"
    ],
    "name:lav_x_preferred":[
        "Abragciems"
    ],
    "name:lit_x_preferred":[
        "Abragciemis"
    ],
    "name:nld_x_preferred":[
        "Abragciems"
    ],
    "name:pol_x_preferred":[
        "Abragciems"
    ],
    "name:und_x_variant":[
        "Abragtsiyems"
    ],
    "qs_pg:aaroncc":"LV",
    "qs_pg:gn_country":"LV",
    "qs_pg:gn_fcode":"PPL",
    "qs_pg:gn_pop":70,
    "qs_pg:name":"Abragciems",
    "qs_pg:name_adm0":"Latvija",
    "qs_pg:name_adm1":"Engures Novads",
    "qs_pg:photos_9k":1,
    "qs_pg:photos_9r":1,
    "qs_pg:photos_all":8,
    "qs_pg:photos_sr":0,
    "qs_pg:pop_sr":1,
    "qs_pg:qs_pg_placetype":"locality",
    "qs_pg:qs_pg_placetype_gp":"Town",
    "qs_pg:woe_adm0":23424874,
    "woe:adm0_id":23424874,
    "woe:name_adm0":"Latvija",
    "woe:name_adm1":"Engures Novads",
    "woe:placetype":"Town",
    "wof:name":"Abragciems",
    "wof:placetype":"locality",
    "wof:population":70
},
  "geometry": {"coordinates":[23.20361,57.20278],"type":"Point"}
}