{
  "type": "Feature",
  "properties": {
    "gn:country":"LV",
    "gn:fcode":"PPL",
    "gn:population":0,
    "iso:country":"LV",
    "name:arz_x_preferred":[
        "\u067e\u0631\u064a\u0643\u0648\u0644\u0649"
    ],
    "name:bel_x_preferred":[
        "\u041f\u0440\u044b\u0435\u043a\u0443\u043b\u0456"
    ],
    "name:ceb_x_preferred":[
        "Prieku\u013ci"
    ],
    "name:deu_x_preferred":[
        "Prieku\u013ci"
    ],
    "name:eng_x_preferred":[
        "Prieku\u013ci"
    ],
    "name:epo_x_preferred":[
        "Prieku\u013ci"
    ],
    "name:est_x_preferred":[
        "Prieku\u013ci"
    ],
    "name:fas_x_preferred":[
        "\u067e\u0631\u06cc\u06a9\u0648\u0644\u06cc"
    ],
    "name:lav_x_preferred":[
        "Prieku\u013ci"
    ],
    "name:lit_x_preferred":[
        "Priekuliai"
    ],
    "name:nld_x_preferred":[
        "Prieku\u013ci"
    ],
    "name:rus_x_preferred":[
        "\u041f\u0440\u0438\u0435\u043a\u0443\u043b\u0438"
    ],
    "name:spa_x_preferred":[
        "Prieku\u013ci"
    ],
    "name:swe_x_preferred":[
        "Prieku\u013ci"
    ],
    "name:und_x_variant":[
        "Prieku\u013cu Mui\u017ea"
    ],
    "name:zho_x_preferred":[
        "\u666e\u91cc\u57c3\u5eab\u5229"
    ],
    "qs_pg:aaroncc":"LV",
    "qs_pg:gn_country":"LV",
    "qs_pg:gn_fcode":"PPL",
    "qs_pg:gn_pop":0,
    "qs_pg:name":"Priekul\u0327i",
    "qs_pg:name_adm0":"Latvija",
    "qs_pg:name_adm1":"Priekuau Novads",
    "qs_pg:photos":28,
    "qs_pg:photos_1k":6,
    "qs_pg:photos_9k":1,
    "qs_pg:photos_9r":2,
    "qs_pg:photos_all":28,
    "qs_pg:photos_sr":2,
    "qs_pg:pop_sr":0,
    "qs_pg:qs_pg_placetype":"locality",
    "qs_pg:qs_pg_placetype_gp":"Town",
    "qs_pg:woe_adm0":23424874,
    "woe:adm0_id":23424874,
    "woe:name_adm0":"Latvija",
    "woe:name_adm1":"Priekuau Novads",
    "woe:placetype":"Town",
    "wof:name":"Priekul\u0327i",
    "wof:placetype":"locality",
    "wof:population":2532
},
  "geometry": {"coordinates":[25.36147,57.315],"type":"Point"}
}