{
  "type": "Feature",
  "properties": {
    "gn:gn_country":"LV",
    "gn:gn_fcode":"PPL",
    "gn:gn_pop":390,
    "gn:population":390,
    "iso:country":"LV",
    "name:dut_x_preferred":[
        "Rauda"
    ],
    "name:eng_x_preferred":[
        "Rauda"
    ],
    "name:lav_x_preferred":[
        "Rauda"
    ],
    "name:unk_x_variant":[
        "Rauda Mui\u017eas Centrs"
    ],
    "qs_pg:aaroncc":"LV",
    "qs_pg:gn_country":"LV",
    "qs_pg:gn_fcode":"PPL",
    "qs_pg:gn_pop":390,
    "qs_pg:name":"Rauda",
    "qs_pg:name_adm0":"Latvija",
    "qs_pg:name_adm1":"Engures Novads",
    "qs_pg:photos_9k":1,
    "qs_pg:photos_9r":1,
    "qs_pg:photos_all":22,
    "qs_pg:photos_sr":0,
    "qs_pg:pop_sr":2,
    "qs_pg:qs_pg_placetype":"locality",
    "qs_pg:qs_pg_placetype_gp":"Town",
    "qs_pg:woe_adm0":23424874,
    "woe:adm0_id":23424874,
    "woe:name_adm0":"Latvija",
    "woe:name_adm1":"Engures Novads",
    "woe:placetype":"Town",
    "wof:name":"Rauda",
    "wof:placetype":"locality",
    "wof:population":390
},
  "geometry": {"coordinates":[23.18139,57.00861],"type":"Point"}
}