{
  "type": "Feature",
  "properties": {
    "iso:country":"LV",
    "name:est_x_preferred":[
        "Vaivari"
    ],
    "name:lav_x_preferred":[
        "Vaivari"
    ],
    "name:rus_x_preferred":[
        "\u0412\u0430\u0439\u0432\u0430\u0440\u0438"
    ],
    "wof:name":"Vaivari",
    "wof:placetype":"neighbourhood"
},
  "geometry": {"coordinates":[23.66833412982191,56.9565532650513],"type":"Point"}
}