{
  "type": "Feature",
  "properties": {
    "gn:admin1_code":"33",
    "gn:admin2_code":"980290.0",
    "gn:asciiname":"Sise",
    "gn:cc2":"LV",
    "gn:country_code":"LV",
    "gn:dem":10,
    "gn:feature_class":"P",
    "gn:feature_code":"PPL",
    "gn:name":"Sise",
    "gn:population":0,
    "gn:timezone":"Europe/Riga",
    "iso:country":"LV",
    "name:und_x_variant":[
        "Sises Ciems",
        "Sise"
    ],
    "wof:name":"Sise",
    "wof:placetype":"locality"
},
  "geometry": {"coordinates":[21.55131,57.12553000000001],"type":"Point"}
}