{
  "type": "Feature",
  "properties": {
    "iso:country":"LV",
    "name:lav_x_preferred":[
        "Atg\u0101zene"
    ],
    "wof:name":"Atgazene",
    "wof:placetype":"neighbourhood"
},
  "geometry": {"coordinates":[24.08145174643543,56.91082373190103],"type":"Point"}
}