{
  "type": "Feature",
  "properties": {
    "gn:admin1_code":"35",
    "gn:admin2_code":"604342.0",
    "gn:asciiname":"Mazdzerkali",
    "gn:country_code":"LV",
    "gn:dem":156,
    "gn:feature_class":"P",
    "gn:feature_code":"PPL",
    "gn:name":"Mazdzerka\u013ci",
    "gn:population":0,
    "gn:timezone":"Europe/Riga",
    "iso:country":"LV",
    "name:und_x_variant":[
        "Dzerkali",
        "Dzerkali\u0161ki",
        "Mazdzerka\u013ci"
    ],
    "wof:name":"Mazdzerkali",
    "wof:placetype":"locality"
},
  "geometry": {"coordinates":[27.06667,56.13333000000001],"type":"Point"}
}