{
  "type": "Feature",
  "properties": {
    "gn:admin1_code":"61",
    "gn:admin2_code":"640850.0",
    "gn:asciiname":"Dunalka",
    "gn:country_code":"LV",
    "gn:dem":42,
    "gn:feature_class":"P",
    "gn:feature_code":"PPL",
    "gn:name":"Dunalka",
    "gn:population":0,
    "gn:timezone":"Europe/Riga",
    "iso:country":"LV",
    "name:und_x_variant":[
        "Myza Dunalka",
        "Dunalkas Mui\u017ea",
        "Dunalka"
    ],
    "wof:name":"Dunalka",
    "wof:placetype":"locality"
},
  "geometry": {"coordinates":[21.33018,56.6848],"type":"Point"}
}