{
  "type": "Feature",
  "properties": {
    "gn:admin1_code":"A3",
    "gn:admin2_code":"546766.0",
    "gn:asciiname":"Aizupes",
    "gn:country_code":"LV",
    "gn:dem":7,
    "gn:feature_class":"P",
    "gn:feature_code":"PPL",
    "gn:name":"Aizupes",
    "gn:population":0,
    "gn:timezone":"Europe/Riga",
    "iso:country":"LV",
    "wof:name":"Aizupes",
    "wof:placetype":"locality"
},
  "geometry": {"coordinates":[23.79964,56.69496],"type":"Point"}
}