{
  "type": "Feature",
  "properties": {
    "gn:admin1_code":"A8",
    "gn:admin2_code":"641658.0",
    "gn:asciiname":"Aizviki",
    "gn:country_code":"LV",
    "gn:dem":84,
    "gn:feature_class":"P",
    "gn:feature_code":"PPL",
    "gn:name":"Aizv\u012b\u0137i",
    "gn:population":0,
    "gn:timezone":"Europe/Riga",
    "iso:country":"LV",
    "name:und_x_variant":[
        "Myza Ayzviti",
        "Aizvi\u0137i Mui\u017eas Centrs",
        "Ayzviki",
        "Aizv\u012b\u0137i"
    ],
    "wof:name":"Aizviki",
    "wof:placetype":"locality"
},
  "geometry": {"coordinates":[21.72441,56.33438],"type":"Point"}
}