{
  "type": "Feature",
  "properties": {
    "gn:admin1_code":"53",
    "gn:admin2_code":"805200.0",
    "gn:asciiname":"Siguli",
    "gn:country_code":"LV",
    "gn:dem":4,
    "gn:feature_class":"P",
    "gn:feature_code":"PPL",
    "gn:name":"Sigu\u013ci",
    "gn:population":0,
    "gn:timezone":"Europe/Riga",
    "iso:country":"LV",
    "wof:name":"Siguli",
    "wof:placetype":"locality"
},
  "geometry": {"coordinates":[24.31171,57.12785],"type":"Point"}
}