{
  "type": "Feature",
  "properties": {
    "gn:admin1_code":"57",
    "gn:admin2_code":"601042.0",
    "gn:asciiname":"Vecokra",
    "gn:country_code":"LV",
    "gn:dem":166,
    "gn:feature_class":"P",
    "gn:feature_code":"PPL",
    "gn:name":"Vecokra",
    "gn:population":0,
    "gn:timezone":"Europe/Riga",
    "iso:country":"LV",
    "wof:name":"Vecokra",
    "wof:placetype":"locality"
},
  "geometry": {"coordinates":[27.28498,56.12369],"type":"Point"}
}