{
  "type": "Feature",
  "properties": {
    "gn:admin1_code":"E2",
    "gn:admin2_code":"769190.0",
    "gn:asciiname":"Zabludniki",
    "gn:country_code":"LV",
    "gn:dem":98,
    "gn:feature_class":"P",
    "gn:feature_code":"PPL",
    "gn:name":"Zabl\u016bdn\u012bki",
    "gn:population":0,
    "gn:timezone":"Europe/Riga",
    "iso:country":"LV",
    "name:und_x_variant":[
        "Zabl\u016bdn\u012bki",
        "Zabludni\u0137i"
    ],
    "wof:name":"Zabludniki",
    "wof:placetype":"locality"
},
  "geometry": {"coordinates":[26.47546,56.22807],"type":"Point"}
}