{
  "type": "Feature",
  "properties": {
    "gn:admin1_code":"22",
    "gn:admin2_code":"760274.0",
    "gn:asciiname":"Anspoki",
    "gn:cc2":"LV",
    "gn:country_code":"LV",
    "gn:dem":112,
    "gn:feature_class":"P",
    "gn:feature_code":"PPL",
    "gn:name":"Anspoki",
    "gn:population":0,
    "gn:timezone":"Europe/Riga",
    "iso:country":"LV",
    "name:eng_x_preferred":[
        "Anspoki"
    ],
    "name:rus_x_preferred":[
        "\u0411.\u0410\u043d\u0441\u043f\u043e\u043a\u0438"
    ],
    "name:und_x_variant":[
        "Anspaki",
        "Anspoki"
    ],
    "wof:name":"Anspoki",
    "wof:placetype":"locality"
},
  "geometry": {"coordinates":[26.6415,56.38331],"type":"Point"}
}