{
  "type": "Feature",
  "properties": {
    "gn:admin1_code":"33",
    "gn:admin2_code":"980290.0",
    "gn:asciiname":"Krievbudas",
    "gn:country_code":"LV",
    "gn:dem":12,
    "gn:feature_class":"P",
    "gn:feature_code":"PPL",
    "gn:name":"Krievb\u016bdas",
    "gn:population":0,
    "gn:timezone":"Europe/Riga",
    "iso:country":"LV",
    "name:und_x_variant":[
        "Krievb\u016bdas",
        "Beti",
        "B\u0113ti",
        "B\u0113tciems"
    ],
    "wof:name":"Krievbudas",
    "wof:placetype":"locality"
},
  "geometry": {"coordinates":[21.57283,57.11785],"type":"Point"}
}