{
  "type": "Feature",
  "properties": {
    "gn:admin1_code":"39",
    "gn:admin2_code":"661027.0",
    "gn:asciiname":"Smilgas",
    "gn:country_code":"LV",
    "gn:dem":77,
    "gn:feature_class":"P",
    "gn:feature_code":"PPL",
    "gn:name":"Smilgas",
    "gn:population":0,
    "gn:timezone":"Europe/Riga",
    "iso:country":"LV",
    "wof:name":"Smilgas",
    "wof:placetype":"locality"
},
  "geometry": {"coordinates":[24.85009,57.75416],"type":"Point"}
}