{
  "type": "Feature",
  "properties": {
    "gn:admin1_code":"30",
    "gn:asciiname":"Evele",
    "gn:cc2":"LV",
    "gn:country_code":"LV",
    "gn:dem":72,
    "gn:feature_class":"P",
    "gn:feature_code":"PPL",
    "gn:name":"\u0112vele",
    "gn:population":0,
    "gn:timezone":"Europe/Riga",
    "iso:country":"LV",
    "name:und_x_variant":[
        "Myza Evele",
        "\u0112veles Mui\u017ea",
        "\u0112vele"
    ],
    "wof:name":"Evele",
    "wof:placetype":"locality"
},
  "geometry": {"coordinates":[25.55875,57.69392],"type":"Point"}
}