{
  "type": "Feature",
  "properties": {
    "gn:admin1_code":"31",
    "gn:asciiname":"Pantene",
    "gn:cc2":"LV",
    "gn:country_code":"LV",
    "gn:dem":65,
    "gn:feature_class":"P",
    "gn:feature_code":"PPL",
    "gn:name":"Pantene",
    "gn:population":0,
    "gn:timezone":"Europe/Riga",
    "iso:country":"LV",
    "name:ara_x_preferred":[
        "\u0628\u0627\u0646\u062a\u064a\u0646"
    ],
    "name:aze_x_preferred":[
        "Pantene"
    ],
    "name:dan_x_preferred":[
        "Pantene"
    ],
    "name:fas_x_preferred":[
        "\u067e\u0627\u0646\u062a\u06cc\u0646"
    ],
    "name:fra_x_preferred":[
        "Pantene"
    ],
    "name:ind_x_preferred":[
        "Pantene"
    ],
    "name:ita_x_preferred":[
        "Pantene"
    ],
    "name:jpn_x_preferred":[
        "\u30d1\u30f3\u30c6\u30fc\u30f3"
    ],
    "name:msa_x_preferred":[
        "Pantene"
    ],
    "name:pol_x_preferred":[
        "Pantene"
    ],
    "name:por_x_preferred":[
        "Pantene"
    ],
    "name:sco_x_preferred":[
        "Pantene"
    ],
    "name:spa_x_preferred":[
        "Pantene"
    ],
    "name:tgl_x_preferred":[
        "Pantene"
    ],
    "name:tur_x_preferred":[
        "Pantene"
    ],
    "name:und_x_variant":[
        "Myza Pantene",
        "Pantenes Mui\u017ea",
        "Pantene"
    ],
    "wof:name":"Pantene",
    "wof:placetype":"locality"
},
  "geometry": {"coordinates":[25.2065,57.86585],"type":"Point"}
}