{
  "type": "Feature",
  "properties": {
    "gn:admin1_code":"31",
    "gn:asciiname":"Pantene",
    "gn:cc2":"LV",
    "gn:country_code":"LV",
    "gn:dem":65,
    "gn:feature_class":"P",
    "gn:feature_code":"PPL",
    "gn:name":"Pantene",
    "gn:population":0,
    "gn:timezone":"Europe/Riga",
    "iso:country":"LV",
    "name:und_x_variant":[
        "Myza Pantene",
        "Pantenes Mui\u017ea",
        "Pantene"
    ],
    "wof:name":"Pantene",
    "wof:placetype":"locality"
},
  "geometry": {"coordinates":[25.2065,57.86585],"type":"Point"}
}