{
  "type": "Feature",
  "properties": {
    "gn:admin1_code":"07",
    "gn:admin2_code":"440270.0",
    "gn:asciiname":"Janciski",
    "gn:country_code":"LV",
    "gn:dem":134,
    "gn:feature_class":"P",
    "gn:feature_code":"PPL",
    "gn:name":"Janci\u0161ki",
    "gn:population":0,
    "gn:timezone":"Europe/Riga",
    "iso:country":"LV",
    "name:und_x_variant":[
        "Janci\u0161kas"
    ],
    "wof:name":"Janciski",
    "wof:placetype":"locality"
},
  "geometry": {"coordinates":[26.75076,55.99478000000001],"type":"Point"}
}