{
  "type": "Feature",
  "properties": {
    "gn:admin1_code":"04",
    "gn:admin2_code":"400260.0",
    "gn:asciiname":"Birzgali",
    "gn:country_code":"LV",
    "gn:dem":35,
    "gn:feature_class":"P",
    "gn:feature_code":"PPL",
    "gn:name":"Birzga\u013ci",
    "gn:population":0,
    "gn:timezone":"Europe/Riga",
    "iso:country":"LV",
    "name:eng_x_preferred":[
        "Birzga\u013ci"
    ],
    "name:rus_x_preferred":[
        "\u0411\u0438\u0440\u0437\u0433\u0430\u043b\u0435"
    ],
    "name:und_x_variant":[
        "Birzgale",
        "Birzga\u013ci"
    ],
    "wof:name":"Birzgali",
    "wof:placetype":"locality"
},
  "geometry": {"coordinates":[24.22354,56.28633000000001],"type":"Point"}
}