{
  "type": "Feature",
  "properties": {
    "gn:admin1_code":"10",
    "gn:asciiname":"Birzi",
    "gn:cc2":"LV",
    "gn:country_code":"LV",
    "gn:dem":90,
    "gn:feature_class":"P",
    "gn:feature_code":"PPL",
    "gn:name":"Bir\u017ei",
    "gn:population":0,
    "gn:timezone":"Europe/Riga",
    "iso:country":"LV",
    "name:eng_x_preferred":[
        "Bir\u017ei"
    ],
    "name:rus_x_preferred":[
        "\u0411\u0438\u0440\u0436\u0438"
    ],
    "name:und_x_variant":[
        "Myza Birzha",
        "Birzhi",
        "Myza Bushgof",
        "Birzai",
        "Bir\u017eu Mui\u017ea"
    ],
    "wof:name":"Birzi",
    "wof:placetype":"locality"
},
  "geometry": {"coordinates":[25.77221,56.4063],"type":"Point"}
}