{
  "type": "Feature",
  "properties": {
    "gn:gn_country":"LV",
    "gn:gn_fcode":"PPL",
    "gn:gn_pop":0,
    "iso:country":"LV",
    "name:eng_x_preferred":[
        "Bern\u0101ti"
    ],
    "name:lav_x_preferred":[
        "Bern\u0101ti"
    ],
    "name:nld_x_preferred":[
        "Bern\u0101ti"
    ],
    "name:unk_x_variant":[
        "Bern\u0101te"
    ],
    "qs_pg:aaroncc":"LV",
    "qs_pg:gn_country":"LV",
    "qs_pg:gn_fcode":"PPL",
    "qs_pg:gn_pop":0,
    "qs_pg:name":"Bern\u0101ti",
    "qs_pg:name_adm0":"Latvija",
    "qs_pg:name_adm1":"N\u013ccas Novads",
    "qs_pg:photos":38,
    "qs_pg:photos_1k":8,
    "qs_pg:photos_9k":1,
    "qs_pg:photos_9r":2,
    "qs_pg:photos_all":38,
    "qs_pg:photos_sr":2,
    "qs_pg:pop_sr":0,
    "qs_pg:qs_pg_placetype":"locality",
    "qs_pg:qs_pg_placetype_gp":"Town",
    "qs_pg:woe_adm0":23424874,
    "woe:adm0_id":23424874,
    "woe:name_adm0":"Latvija",
    "woe:name_adm1":"N\u013ccas Novads",
    "woe:placetype":"Town",
    "wof:name":"Bern\u0101ti",
    "wof:placetype":"locality"
},
  "geometry": {"coordinates":[20.98801,56.37497],"type":"Point"}
}