{
  "type": "Feature",
  "properties": {
    "gn:admin1_code":"C1",
    "gn:admin2_code":"661435.0",
    "gn:asciiname":"Svetciems",
    "gn:country_code":"LV",
    "gn:dem":13,
    "gn:feature_class":"P",
    "gn:feature_code":"PPL",
    "gn:name":"Sv\u0113tciems",
    "gn:population":0,
    "gn:timezone":"Europe/Riga",
    "iso:country":"LV",
    "name:eng_x_preferred":[
        "Sv\u0113tciems"
    ],
    "name:rus_x_preferred":[
        "\u0421\u0432\u0435\u0442\u0446\u0438\u0435\u043c\u0441"
    ],
    "name:und_x_variant":[
        "Sveiciema Mui\u017ea",
        "Myza Svytsiyems",
        "Sveiciems",
        "Svettsiyems",
        "Sveiciems Mui\u017eas Centrs",
        "Svettsiyem"
    ],
    "wof:name":"Svetciems",
    "wof:placetype":"locality"
},
  "geometry": {"coordinates":[24.37659,57.70296],"type":"Point"}
}