{
  "type": "Feature",
  "properties": {
    "gn:admin1_code":"30",
    "gn:admin2_code":"940292.0",
    "gn:asciiname":"Mezmuiza",
    "gn:country_code":"LV",
    "gn:dem":64,
    "gn:feature_class":"P",
    "gn:feature_code":"PPL",
    "gn:name":"Me\u017emui\u017ea",
    "gn:population":0,
    "gn:timezone":"Europe/Riga",
    "iso:country":"LV",
    "wof:name":"Mezmuiza",
    "wof:placetype":"locality"
},
  "geometry": {"coordinates":[26.04155,57.59305],"type":"Point"}
}