{
  "type": "Feature",
  "properties": {
    "gn:admin1_code":"A8",
    "gn:admin2_code":"641698.0",
    "gn:asciiname":"Kalnakrogs",
    "gn:country_code":"LV",
    "gn:dem":19,
    "gn:feature_class":"P",
    "gn:feature_code":"PPL",
    "gn:name":"Kalnakrogs",
    "gn:population":0,
    "gn:timezone":"Europe/Riga",
    "iso:country":"LV",
    "wof:name":"Kalnakrogs",
    "wof:placetype":"locality"
},
  "geometry": {"coordinates":[21.43333,56.43333000000001],"type":"Point"}
}