{
  "type": "Feature",
  "properties": {
    "gn:admin1_code":"24",
    "gn:admin2_code":"780288.0",
    "gn:asciiname":"Deneliski",
    "gn:country_code":"LV",
    "gn:dem":139,
    "gn:feature_class":"P",
    "gn:feature_code":"PPL",
    "gn:name":"Deneli\u0161\u0137i",
    "gn:population":0,
    "gn:timezone":"Europe/Riga",
    "iso:country":"LV",
    "wof:name":"Deneliski",
    "wof:placetype":"locality"
},
  "geometry": {"coordinates":[27.09143,56.47643000000001],"type":"Point"}
}