{
  "type": "Feature",
  "properties": {
    "iso:country":"LV",
    "wof:name":"Vakarbul",
    "wof:placetype":"neighbourhood"
},
  "geometry": {"coordinates":[23.94458033967763,56.99987390374947],"type":"Point"}
}