{
  "type": "Feature",
  "properties": {
    "gn:admin1_code":"10",
    "gn:admin2_code":"560266.0",
    "gn:asciiname":"Vidsala",
    "gn:cc2":"LV",
    "gn:country_code":"LV",
    "gn:dem":115,
    "gn:feature_class":"P",
    "gn:feature_code":"PPL",
    "gn:name":"Vidsala",
    "gn:population":0,
    "gn:timezone":"Europe/Riga",
    "iso:country":"LV",
    "name:und_x_variant":[
        "Kalnaciems",
        "Vidsala"
    ],
    "wof:name":"Vidsala",
    "wof:placetype":"locality"
},
  "geometry": {"coordinates":[25.8598,56.34307],"type":"Point"}
}