{
  "type": "Feature",
  "properties": {
    "gn:admin1_code":"12",
    "gn:admin2_code":"540286.0",
    "gn:asciiname":"Valgunde",
    "gn:country_code":"LV",
    "gn:dem":5,
    "gn:feature_class":"P",
    "gn:feature_code":"PPL",
    "gn:name":"Valgunde",
    "gn:population":0,
    "gn:timezone":"Europe/Riga",
    "iso:country":"LV",
    "name:und_x_variant":[
        "Myza Volgunta",
        "Indu\u013ci",
        "Myza Volguntas",
        "Valguntes",
        "Valgunte Mui\u017eas Centrs",
        "Volguntes Mui\u017ea",
        "Valgunte",
        "Valgunde"
    ],
    "wof:name":"Valgunde",
    "wof:placetype":"locality"
},
  "geometry": {"coordinates":[23.6806,56.74921],"type":"Point"}
}