{
  "type": "Feature",
  "properties": {
    "gn:admin1_code":"B5",
    "gn:admin2_code":"808400.0",
    "gn:asciiname":"Villasmuiza",
    "gn:country_code":"LV",
    "gn:dem":54,
    "gn:feature_class":"P",
    "gn:feature_code":"PPL",
    "gn:name":"Villasmui\u017ea",
    "gn:population":0,
    "gn:timezone":"Europe/Riga",
    "iso:country":"LV",
    "name:und_x_variant":[
        "Yugla",
        "Upeskrasti",
        "Puri\u0146i",
        "Villasmui\u017ea"
    ],
    "wof:name":"Villasmuiza",
    "wof:placetype":"locality"
},
  "geometry": {"coordinates":[24.68449,56.95707],"type":"Point"}
}