{
  "type": "Feature",
  "properties": {
    "gn:admin1_code":"07",
    "gn:admin2_code":"440264.0",
    "gn:asciiname":"Volodina",
    "gn:country_code":"LV",
    "gn:dem":145,
    "gn:feature_class":"P",
    "gn:feature_code":"PPL",
    "gn:name":"Volodina",
    "gn:population":0,
    "gn:timezone":"Europe/Riga",
    "iso:country":"LV",
    "name:und_x_variant":[
        "Valodina"
    ],
    "wof:name":"Volodina",
    "wof:placetype":"locality"
},
  "geometry": {"coordinates":[26.58757,55.8146],"type":"Point"}
}