{
  "type": "Feature",
  "properties": {
    "gn:admin1_code":"71",
    "gn:admin2_code":"321078.0",
    "gn:asciiname":"Bagu",
    "gn:country_code":"LV",
    "gn:dem":66,
    "gn:feature_class":"P",
    "gn:feature_code":"PPL",
    "gn:name":"Bagu",
    "gn:population":0,
    "gn:timezone":"Europe/Riga",
    "iso:country":"LV",
    "wof:name":"Bagu",
    "wof:placetype":"locality"
},
  "geometry": {"coordinates":[25.35,56.53333000000001],"type":"Point"}
}