{
  "type": "Feature",
  "properties": {
    "gn:admin1_code":"33",
    "gn:admin2_code":"980290.0",
    "gn:asciiname":"Blende",
    "gn:country_code":"LV",
    "gn:dem":8,
    "gn:feature_class":"P",
    "gn:feature_code":"PPL",
    "gn:name":"Blende",
    "gn:population":0,
    "gn:timezone":"Europe/Riga",
    "iso:country":"LV",
    "name:deu_x_preferred":[
        "Blende"
    ],
    "name:nno_x_preferred":[
        "Blende"
    ],
    "wof:name":"Blende",
    "wof:placetype":"locality"
},
  "geometry": {"coordinates":[21.56667,57.16667],"type":"Point"}
}