{
  "type": "Feature",
  "properties": {
    "gn:admin1_code":"24",
    "gn:admin2_code":"766348.0",
    "gn:asciiname":"Zamezi",
    "gn:country_code":"LV",
    "gn:dem":126,
    "gn:feature_class":"P",
    "gn:feature_code":"PPL",
    "gn:name":"Zame\u017ei",
    "gn:population":0,
    "gn:timezone":"Europe/Riga",
    "iso:country":"LV",
    "name:und_x_variant":[
        "Zamo\u017ei",
        "Zamezhi",
        "Zame\u017ei"
    ],
    "wof:name":"Zamezi",
    "wof:placetype":"locality"
},
  "geometry": {"coordinates":[26.92139,56.44464],"type":"Point"}
}