{
  "type": "Feature",
  "properties": {
    "gn:admin1_code":"78",
    "gn:admin2_code":"681068.0",
    "gn:asciiname":"Soldoni",
    "gn:country_code":"LV",
    "gn:dem":109,
    "gn:feature_class":"P",
    "gn:feature_code":"PPL",
    "gn:name":"Soldoni",
    "gn:population":0,
    "gn:timezone":"Europe/Riga",
    "iso:country":"LV",
    "name:und_x_variant":[
        "Soldonie"
    ],
    "wof:name":"Soldoni",
    "wof:placetype":"locality"
},
  "geometry": {"coordinates":[27.65666,56.77466],"type":"Point"}
}