{
  "type": "Feature",
  "properties": {
    "gn:admin1_code":"15",
    "gn:admin2_code":"620246.0",
    "gn:asciiname":"Balini",
    "gn:country_code":"LV",
    "gn:dem":42,
    "gn:feature_class":"P",
    "gn:feature_code":"PPL",
    "gn:name":"Bali\u0146i",
    "gn:population":0,
    "gn:timezone":"Europe/Riga",
    "iso:country":"LV",
    "wof:name":"Balini",
    "wof:placetype":"locality"
},
  "geometry": {"coordinates":[21.66667,57.03333000000001],"type":"Point"}
}