{
  "type": "Feature",
  "properties": {
    "gn:admin1_code":"28",
    "gn:admin2_code":"880254.0",
    "gn:asciiname":"Ukene",
    "gn:country_code":"LV",
    "gn:dem":44,
    "gn:feature_class":"P",
    "gn:feature_code":"PPL",
    "gn:name":"\u016a\u0137ene",
    "gn:population":0,
    "gn:timezone":"Europe/Riga",
    "iso:country":"LV",
    "wof:name":"Ukene",
    "wof:placetype":"locality"
},
  "geometry": {"coordinates":[22.48333,57.26667],"type":"Point"}
}