{
  "type": "Feature",
  "properties": {
    "gn:admin1_code":"28",
    "gn:admin2_code":"880254.0",
    "gn:asciiname":"Lici",
    "gn:country_code":"LV",
    "gn:dem":52,
    "gn:feature_class":"P",
    "gn:feature_code":"PPL",
    "gn:name":"L\u012b\u010di",
    "gn:population":0,
    "gn:timezone":"Europe/Riga",
    "iso:country":"LV",
    "wof:name":"Lici",
    "wof:placetype":"locality"
},
  "geometry": {"coordinates":[22.41761,57.18028],"type":"Point"}
}