{
  "type": "Feature",
  "properties": {
    "gn:admin1_code":"24",
    "gn:admin2_code":"780252.0",
    "gn:asciiname":"Tuci",
    "gn:country_code":"LV",
    "gn:dem":161,
    "gn:feature_class":"P",
    "gn:feature_code":"PPL",
    "gn:name":"Tu\u010di",
    "gn:population":0,
    "gn:timezone":"Europe/Riga",
    "iso:country":"LV",
    "name:und_x_variant":[
        "Tuchi",
        "T\u016b\u010di",
        "Tu\u010di"
    ],
    "wof:name":"Tuci",
    "wof:placetype":"locality"
},
  "geometry": {"coordinates":[27.05402,56.31295],"type":"Point"}
}