{
  "type": "Feature",
  "properties": {
    "gn:admin1_code":"22",
    "gn:asciiname":"Bortnieki",
    "gn:cc2":"LV",
    "gn:country_code":"LV",
    "gn:dem":136,
    "gn:feature_class":"P",
    "gn:feature_code":"PPL",
    "gn:name":"Bortnieki",
    "gn:population":0,
    "gn:timezone":"Europe/Riga",
    "iso:country":"LV",
    "name:und_x_variant":[
        "Borotniki",
        "Bortnieki"
    ],
    "wof:name":"Bortnieki",
    "wof:placetype":"locality"
},
  "geometry": {"coordinates":[26.88015,56.43559000000001],"type":"Point"}
}