{
  "type": "Feature",
  "properties": {
    "gn:admin1_code":"08",
    "gn:admin2_code":"460272.0",
    "gn:asciiname":"Krimunas",
    "gn:country_code":"LV",
    "gn:dem":23,
    "gn:feature_class":"P",
    "gn:feature_code":"PPL",
    "gn:name":"Krim\u016bnas",
    "gn:population":0,
    "gn:timezone":"Europe/Riga",
    "iso:country":"LV",
    "name:ceb_x_preferred":[
        "Krim\u016bnas"
    ],
    "name:lav_x_preferred":[
        "Krim\u016bnas"
    ],
    "name:rus_x_preferred":[
        "\u041a\u0440\u0438\u043c\u0443\u043d\u0430\u0441"
    ],
    "name:swe_x_preferred":[
        "Krim\u016bnas"
    ],
    "name:und_x_variant":[
        "Krim\u016bnas"
    ],
    "wof:name":"Krimunas",
    "wof:placetype":"locality"
},
  "geometry": {"coordinates":[23.37583,56.57139],"type":"Point"}
}