{
  "type": "Feature",
  "properties": {
    "gn:admin1_code":"78",
    "gn:admin2_code":"681068.0",
    "gn:asciiname":"Barkani",
    "gn:country_code":"LV",
    "gn:dem":101,
    "gn:feature_class":"P",
    "gn:feature_code":"PPL",
    "gn:name":"Bark\u0101ni",
    "gn:population":0,
    "gn:timezone":"Europe/Riga",
    "iso:country":"LV",
    "wof:name":"Barkani",
    "wof:placetype":"locality"
},
  "geometry": {"coordinates":[27.72424,56.82719],"type":"Point"}
}