{
  "type": "Feature",
  "properties": {
    "gn:admin1_code":"C7",
    "gn:admin2_code":"801666.0",
    "gn:asciiname":"Myza Kartuzhi",
    "gn:country_code":"LV",
    "gn:dem":102,
    "gn:feature_class":"P",
    "gn:feature_code":"PPL",
    "gn:name":"Myza Kartuzhi",
    "gn:population":0,
    "gn:timezone":"Europe/Riga",
    "iso:country":"LV",
    "name:und_x_variant":[
        "Kartu\u017eu Mui\u017ea",
        "K\u0101rt\u016b\u017ei"
    ],
    "wof:name":"Myza Kartuzhi",
    "wof:placetype":"locality"
},
  "geometry": {"coordinates":[25.02426,57.10585],"type":"Point"}
}