{
  "type": "Feature",
  "properties": {
    "gn:admin1_code":"15",
    "gn:admin2_code":"620280.0",
    "gn:asciiname":"Streijas",
    "gn:country_code":"LV",
    "gn:dem":47,
    "gn:feature_class":"P",
    "gn:feature_code":"PPL",
    "gn:name":"Streijas",
    "gn:population":0,
    "gn:timezone":"Europe/Riga",
    "iso:country":"LV",
    "wof:name":"Streijas",
    "wof:placetype":"locality"
},
  "geometry": {"coordinates":[22.21667,57.05],"type":"Point"}
}