{
  "type": "Feature",
  "properties": {
    "gn:admin1_code":"28",
    "gn:admin2_code":"880292.0",
    "gn:asciiname":"Valdgale",
    "gn:cc2":"LV",
    "gn:country_code":"LV",
    "gn:dem":65,
    "gn:feature_class":"P",
    "gn:feature_code":"PPL",
    "gn:name":"Valdgale",
    "gn:population":0,
    "gn:timezone":"Europe/Riga",
    "iso:country":"LV",
    "name:und_x_variant":[
        "Valdeg\u0101le",
        "Volgate",
        "Valgale",
        "Valdgale"
    ],
    "wof:name":"Valdgale",
    "wof:placetype":"locality"
},
  "geometry": {"coordinates":[22.56969,57.28294],"type":"Point"}
}