{
  "type": "Feature",
  "properties": {
    "gn:admin1_code":"85",
    "gn:admin2_code":"566968.0",
    "gn:asciiname":"Purnini",
    "gn:country_code":"LV",
    "gn:dem":86,
    "gn:feature_class":"P",
    "gn:feature_code":"PPL",
    "gn:name":"Purni\u0146i",
    "gn:population":0,
    "gn:timezone":"Europe/Riga",
    "iso:country":"LV",
    "wof:name":"Purnini",
    "wof:placetype":"locality"
},
  "geometry": {"coordinates":[25.84975,56.57409000000001],"type":"Point"}
}