{
  "type": "Feature",
  "properties": {
    "gn:admin1_code":"31",
    "gn:asciiname":"Talci",
    "gn:cc2":"LV",
    "gn:country_code":"LV",
    "gn:dem":58,
    "gn:feature_class":"P",
    "gn:feature_code":"PPL",
    "gn:name":"Tal\u010di",
    "gn:population":0,
    "gn:timezone":"Europe/Riga",
    "iso:country":"LV",
    "name:und_x_variant":[
        "Lukstins",
        "Tal\u010di"
    ],
    "wof:name":"Talci",
    "wof:placetype":"locality"
},
  "geometry": {"coordinates":[25.00896,57.9834],"type":"Point"}
}