{
  "type": "Feature",
  "properties": {
    "gn:admin1_code":"01",
    "gn:asciiname":"Siljani",
    "gn:country_code":"LV",
    "gn:dem":116,
    "gn:feature_class":"P",
    "gn:feature_code":"PPL",
    "gn:name":"Silj\u0101\u0146i",
    "gn:population":0,
    "gn:timezone":"Europe/Riga",
    "iso:country":"LV",
    "wof:name":"Siljani",
    "wof:placetype":"locality"
},
  "geometry": {"coordinates":[25.62183,56.74124000000001],"type":"Point"}
}