{
  "type": "Feature",
  "properties": {
    "gn:admin1_code":"E9",
    "gn:admin2_code":"681884.0",
    "gn:asciiname":"Latisonki",
    "gn:country_code":"LV",
    "gn:dem":170,
    "gn:feature_class":"P",
    "gn:feature_code":"PPL",
    "gn:name":"Lati\u0161onki",
    "gn:population":0,
    "gn:timezone":"Europe/Riga",
    "iso:country":"LV",
    "name:und_x_variant":[
        "Latyshenki",
        "Lati\u0161onki"
    ],
    "wof:name":"Latisonki",
    "wof:placetype":"locality"
},
  "geometry": {"coordinates":[28.05974,56.15466],"type":"Point"}
}