{
  "type": "Feature",
  "properties": {
    "gn:admin1_code":"18",
    "gn:admin2_code":"660280.0",
    "gn:asciiname":"Rozes",
    "gn:cc2":"LV",
    "gn:country_code":"LV",
    "gn:dem":89,
    "gn:feature_class":"P",
    "gn:feature_code":"PPL",
    "gn:name":"Rozes",
    "gn:population":0,
    "gn:timezone":"Europe/Riga",
    "iso:country":"LV",
    "name:und_x_variant":[
        "\u0160arlate"
    ],
    "wof:name":"Rozes",
    "wof:placetype":"locality"
},
  "geometry": {"coordinates":[24.94556,57.51917],"type":"Point"}
}