{
  "type": "Feature",
  "properties": {
    "gn:admin1_code":"12",
    "gn:admin2_code":"540262.0",
    "gn:asciiname":"Livesmuiza",
    "gn:country_code":"LV",
    "gn:dem":5,
    "gn:feature_class":"P",
    "gn:feature_code":"PPL",
    "gn:name":"L\u012bvesmui\u017ea",
    "gn:population":0,
    "gn:timezone":"Europe/Riga",
    "iso:country":"LV",
    "name:und_x_variant":[
        "Lives",
        "L\u012bvesmui\u017ea"
    ],
    "wof:name":"Livesmuiza",
    "wof:placetype":"locality"
},
  "geometry": {"coordinates":[23.49576,56.71726999999999],"type":"Point"}
}