{
  "type": "Feature",
  "properties": {
    "gn:country":"LV",
    "gn:fcode":"PPL",
    "gn:population":0,
    "iso:country":"LV",
    "name:ceb_x_preferred":[
        "M\u0101rupe"
    ],
    "name:deu_x_preferred":[
        "M\u0101rupe"
    ],
    "name:eng_x_preferred":[
        "M\u0101rupe"
    ],
    "name:est_x_preferred":[
        "M\u0101rupe"
    ],
    "name:fra_x_preferred":[
        "M\u0101rupe"
    ],
    "name:lav_x_preferred":[
        "M\u0101rupe"
    ],
    "name:lit_x_preferred":[
        "Marup\u0117"
    ],
    "name:nld_x_preferred":[
        "M\u0101rupe"
    ],
    "name:rus_x_preferred":[
        "\u041c\u0430\u0440\u0443\u043f\u0435"
    ],
    "name:swe_x_preferred":[
        "M\u0101rupe"
    ],
    "qs_pg:aaroncc":"LV",
    "qs_pg:gn_country":"LV",
    "qs_pg:gn_fcode":"PPL",
    "qs_pg:gn_pop":0,
    "qs_pg:name":"Marupe",
    "qs_pg:name_adm0":"Latvija",
    "qs_pg:name_adm1":"M\u0105rupes Novads",
    "qs_pg:photos":54,
    "qs_pg:photos_1k":11,
    "qs_pg:photos_9k":1,
    "qs_pg:photos_9r":3,
    "qs_pg:photos_all":100,
    "qs_pg:photos_sr":2,
    "qs_pg:pop_sr":0,
    "qs_pg:qs_pg_placetype":"locality",
    "qs_pg:qs_pg_placetype_gp":"Town",
    "qs_pg:woe_adm0":23424874,
    "woe:adm0_id":23424874,
    "woe:name_adm0":"Latvija",
    "woe:name_adm1":"M\u0105rupes Novads",
    "woe:placetype":"Town",
    "wof:name":"Marupe",
    "wof:placetype":"locality"
},
  "geometry": {"coordinates":[24.05113,56.90544],"type":"Point"}
}