{
  "type": "Feature",
  "properties": {
    "gn:admin1_code":"E7",
    "gn:admin2_code":"381678.0",
    "gn:asciiname":"Karigova",
    "gn:country_code":"LV",
    "gn:dem":105,
    "gn:feature_class":"P",
    "gn:feature_code":"PPL",
    "gn:name":"Karigova",
    "gn:population":0,
    "gn:timezone":"Europe/Riga",
    "iso:country":"LV",
    "name:und_x_variant":[
        "Karigava",
        "Karigova"
    ],
    "wof:name":"Karigova",
    "wof:placetype":"locality"
},
  "geometry": {"coordinates":[27.6559,57.25204],"type":"Point"}
}