{
  "type": "Feature",
  "properties": {
    "gn:admin1_code":"42",
    "gn:admin2_code":"424768.0",
    "gn:asciiname":"Kuileni",
    "gn:country_code":"LV",
    "gn:dem":140,
    "gn:feature_class":"P",
    "gn:feature_code":"PPL",
    "gn:name":"Kuil\u0113ni",
    "gn:population":0,
    "gn:timezone":"Europe/Riga",
    "iso:country":"LV",
    "name:und_x_variant":[
        "Kuileny",
        "Kuil\u0113ni"
    ],
    "wof:name":"Kuileni",
    "wof:placetype":"locality"
},
  "geometry": {"coordinates":[25.16667,57.06667],"type":"Point"}
}