{
  "type": "Feature",
  "properties": {
    "gn:admin1_code":"20",
    "gn:admin2_code":"700242.0",
    "gn:asciiname":"Oli",
    "gn:country_code":"LV",
    "gn:dem":238,
    "gn:feature_class":"P",
    "gn:feature_code":"PPL",
    "gn:name":"O\u013ci",
    "gn:population":0,
    "gn:timezone":"Europe/Riga",
    "iso:country":"LV",
    "wof:name":"Oli",
    "wof:placetype":"locality"
},
  "geometry": {"coordinates":[26.18058,56.93251],"type":"Point"}
}