{
  "type": "Feature",
  "properties": {
    "gn:admin1_code":"03",
    "gn:admin2_code":"380246.0",
    "gn:asciiname":"Naudaskalns",
    "gn:country_code":"LV",
    "gn:dem":112,
    "gn:feature_class":"P",
    "gn:feature_code":"PPL",
    "gn:name":"Naudaskalns",
    "gn:population":0,
    "gn:timezone":"Europe/Riga",
    "iso:country":"LV",
    "name:und_x_variant":[
        "Naudv\u0161eva",
        "Naudu\u0161eva",
        "Naudusheva",
        "Naudaskalns"
    ],
    "wof:name":"Naudaskalns",
    "wof:placetype":"locality"
},
  "geometry": {"coordinates":[27.23551,57.08559],"type":"Point"}
}