{
  "type": "Feature",
  "properties": {
    "iso:country":"LV",
    "name:eng_x_preferred":[
        "Dubulty"
    ],
    "name:eng_x_variant":[
        "Dubbeln",
        "Dubulti"
    ],
    "name:est_x_preferred":[
        "Dubulti"
    ],
    "name:heb_x_preferred":[
        "\u05d3\u05d5\u05d1\u05dc\u05df"
    ],
    "name:lav_x_preferred":[
        "Dubulti"
    ],
    "name:lit_x_preferred":[
        "Dubultai"
    ],
    "name:rus_x_preferred":[
        "\u0414\u0443\u0431\u0443\u043b\u0442\u044b"
    ],
    "qs:gn_adm0_cc":"LV",
    "qs:gn_fcode":"PPLX",
    "qs:gn_local":459201,
    "qs:gn_nam_loc":"jurmala",
    "qs:gn_namadm1":"13",
    "qs:gn_name":"Dubulti",
    "qs:local_max":729,
    "qs:local_sum":1749,
    "qs:localhoods":6,
    "qs:name":"Dubulti",
    "qs:name_adm0":"Latvija",
    "qs:name_adm1":"J\u017ermala",
    "qs:name_adm2":"J\u017ermala",
    "qs:name_en":"Dubulty",
    "qs:name_local":"J\u016brmala",
    "qs:photo_max":6,
    "qs:photo_sum":22,
    "qs:placetype":"Suburb",
    "qs:quad_count":7,
    "qs:woe_adm0":23424874,
    "qs:woe_adm1":20070119,
    "qs:woe_adm2":55844547,
    "qs:woe_lau":0,
    "qs:woe_local":852880,
    "qs:woe_ver":"7.10.0",
    "wd:wordcount":162,
    "wof:lang":[
        "unk"
    ],
    "wof:name":"Dubulti",
    "wof:placetype":"neighbourhood"
},
  "geometry": {"coordinates":[23.772225,56.97025],"type":"Point"}
}