{
  "type": "Feature",
  "properties": {
    "gn:admin1_code":"03",
    "gn:admin2_code":"380252.0",
    "gn:asciiname":"Pusleva",
    "gn:country_code":"LV",
    "gn:dem":111,
    "gn:feature_class":"P",
    "gn:feature_code":"PPL",
    "gn:name":"P\u016b\u0161\u013ceva",
    "gn:population":0,
    "gn:timezone":"Europe/Riga",
    "iso:country":"LV",
    "wof:name":"Pusleva",
    "wof:placetype":"locality"
},
  "geometry": {"coordinates":[27.60991,56.99266],"type":"Point"}
}