{
  "type": "Feature",
  "properties": {
    "gn:admin1_code":"14",
    "gn:asciiname":"Ezernieki",
    "gn:cc2":"LV",
    "gn:country_code":"LV",
    "gn:dem":177,
    "gn:feature_class":"P",
    "gn:feature_code":"PPL",
    "gn:name":"Ezernieki",
    "gn:population":0,
    "gn:timezone":"Europe/Riga",
    "iso:country":"LV",
    "name:eng_x_preferred":[
        "Ezernieki"
    ],
    "name:rus_x_preferred":[
        "\u042d\u0437\u0435\u0440\u043d\u0438\u0435\u043a\u0438"
    ],
    "name:und_x_variant":[
        "Bukmuyzha",
        "Ezerniyeki",
        "Bukmui\u017ea",
        "Ezernieki"
    ],
    "wof:name":"Ezernieki",
    "wof:placetype":"locality"
},
  "geometry": {"coordinates":[27.65606,56.18519000000001],"type":"Point"}
}