{
  "type": "Feature",
  "properties": {
    "gn:admin1_code":"04",
    "gn:asciiname":"Klavnieki",
    "gn:country_code":"LV",
    "gn:dem":46,
    "gn:feature_class":"P",
    "gn:feature_code":"PPL",
    "gn:name":"Klavnie\u0137i",
    "gn:population":0,
    "gn:timezone":"Europe/Riga",
    "iso:country":"LV",
    "wof:name":"Klavnieki",
    "wof:placetype":"locality"
},
  "geometry": {"coordinates":[24.53333,56.65],"type":"Point"}
}