{
  "type": "Feature",
  "properties": {
    "gn:admin1_code":"20",
    "gn:asciiname":"Barbali",
    "gn:cc2":"LV",
    "gn:country_code":"LV",
    "gn:dem":104,
    "gn:feature_class":"P",
    "gn:feature_code":"PPL",
    "gn:name":"B\u0101rba\u013ci",
    "gn:population":0,
    "gn:timezone":"Europe/Riga",
    "iso:country":"LV",
    "name:und_x_variant":[
        "Barbu\u013ci-Tropi",
        "Borba\u013ci"
    ],
    "wof:name":"Barbali",
    "wof:placetype":"locality"
},
  "geometry": {"coordinates":[26.5143,56.65623000000001],"type":"Point"}
}