{
  "type": "Feature",
  "properties": {
    "gn:admin1_code":"33",
    "gn:admin2_code":"980260.0",
    "gn:asciiname":"Speltes",
    "gn:country_code":"LV",
    "gn:dem":43,
    "gn:feature_class":"P",
    "gn:feature_code":"PPL",
    "gn:name":"Speltes",
    "gn:population":0,
    "gn:timezone":"Europe/Riga",
    "iso:country":"LV",
    "wof:name":"Speltes",
    "wof:placetype":"locality"
},
  "geometry": {"coordinates":[22.01094,57.3931],"type":"Point"}
}