{
  "type": "Feature",
  "properties": {
    "gn:admin1_code":"24",
    "gn:admin2_code":"780284.0",
    "gn:asciiname":"Zogotas",
    "gn:country_code":"LV",
    "gn:dem":129,
    "gn:feature_class":"P",
    "gn:feature_code":"PPL",
    "gn:name":"\u017dogotas",
    "gn:population":0,
    "gn:timezone":"Europe/Riga",
    "iso:country":"LV",
    "name:und_x_variant":[
        "\u017dagatas",
        "Zhogoty",
        "\u017dagati",
        "\u017dogoti",
        "\u017dogotas"
    ],
    "wof:name":"Zogotas",
    "wof:placetype":"locality"
},
  "geometry": {"coordinates":[27.36681,56.72009],"type":"Point"}
}