{
  "type": "Feature",
  "properties": {
    "gn:admin1_code":"07",
    "gn:admin2_code":"440268.0",
    "gn:asciiname":"Ilukste",
    "gn:country_code":"LV",
    "gn:dem":81,
    "gn:feature_class":"P",
    "gn:feature_code":"PPL",
    "gn:name":"Il\u016bkste",
    "gn:population":0,
    "gn:timezone":"Europe/Riga",
    "iso:country":"LV",
    "wof:name":"Ilukste",
    "wof:placetype":"locality"
},
  "geometry": {"coordinates":[26.35,56.05],"type":"Point"}
}