{
  "type": "Feature",
  "properties": {
    "gn:admin1_code":"04",
    "gn:admin2_code":"400246.0",
    "gn:asciiname":"Budberga",
    "gn:country_code":"LV",
    "gn:dem":34,
    "gn:feature_class":"P",
    "gn:feature_code":"PPL",
    "gn:name":"Budberga",
    "gn:population":0,
    "gn:timezone":"Europe/Riga",
    "iso:country":"LV",
    "name:und_x_variant":[
        "Pa\u0146em\u016bne",
        "Budbe\u0123e",
        "Budberga"
    ],
    "wof:name":"Budberga",
    "wof:placetype":"locality"
},
  "geometry": {"coordinates":[24.52063,56.31215],"type":"Point"}
}