{
  "type": "Feature",
  "properties": {
    "gn:admin1_code":"18",
    "gn:admin2_code":"660268.0",
    "gn:asciiname":"Budele",
    "gn:cc2":"LV",
    "gn:country_code":"LV",
    "gn:dem":60,
    "gn:feature_class":"P",
    "gn:feature_code":"PPL",
    "gn:name":"B\u016bdele",
    "gn:population":0,
    "gn:timezone":"Europe/Riga",
    "iso:country":"LV",
    "name:und_x_variant":[
        "Suc\u0113ni",
        "B\u016bdeles",
        "B\u016bdele"
    ],
    "wof:name":"Budele",
    "wof:placetype":"locality"
},
  "geometry": {"coordinates":[24.73556,57.71583],"type":"Point"}
}