{
  "type": "Feature",
  "properties": {
    "gn:admin1_code":"C1",
    "gn:admin2_code":"661460.0",
    "gn:asciiname":"Dunte",
    "gn:country_code":"LV",
    "gn:dem":42,
    "gn:elevation":"41.0",
    "gn:feature_class":"P",
    "gn:feature_code":"PPL",
    "gn:name":"Dunte",
    "gn:population":25,
    "gn:timezone":"Europe/Riga",
    "iso:country":"LV",
    "name:deu_x_historical":[
        "Dunteshof"
    ],
    "name:deu_x_preferred":[
        "Dunteshof"
    ],
    "name:eng_x_preferred":[
        "Dunte"
    ],
    "name:rus_x_preferred":[
        "\u0414\u0443\u043d\u0442\u0435"
    ],
    "name:und_x_variant":[
        "Myza Dunte",
        "Duntes Mui\u017ea",
        "Dunte"
    ],
    "wof:name":"Dunte",
    "wof:placetype":"locality",
    "wof:population":25
},
  "geometry": {"coordinates":[24.42732,57.40579],"type":"Point"}
}