{
  "type": "Feature",
  "properties": {
    "gn:admin1_code":"19",
    "gn:asciiname":"Bartuli",
    "gn:cc2":"LV",
    "gn:country_code":"LV",
    "gn:dem":111,
    "gn:feature_class":"P",
    "gn:feature_code":"PPL",
    "gn:name":"B\u0101rtu\u013ci",
    "gn:population":0,
    "gn:timezone":"Europe/Riga",
    "iso:country":"LV",
    "name:und_x_variant":[
        "Barguly",
        "B\u0101rtu\u013ci"
    ],
    "wof:name":"Bartuli",
    "wof:placetype":"locality"
},
  "geometry": {"coordinates":[27.97716,56.59735],"type":"Point"}
}