{
  "type": "Feature",
  "properties": {
    "gn:admin1_code":"D1",
    "gn:admin2_code":"941670.0",
    "gn:asciiname":"Stars",
    "gn:country_code":"LV",
    "gn:dem":127,
    "gn:feature_class":"P",
    "gn:feature_code":"PPL",
    "gn:name":"Stars",
    "gn:population":0,
    "gn:timezone":"Europe/Riga",
    "iso:country":"LV",
    "wof:name":"Stars",
    "wof:placetype":"locality"
},
  "geometry": {"coordinates":[25.98333,57.45],"type":"Point"}
}