{
  "type": "Feature",
  "properties": {
    "gn:admin1_code":"27",
    "gn:admin2_code":"840258.0",
    "gn:asciiname":"Jaunlutrini",
    "gn:country_code":"LV",
    "gn:dem":96,
    "gn:feature_class":"P",
    "gn:feature_code":"PPL",
    "gn:name":"Jaunlutri\u0146i",
    "gn:population":0,
    "gn:timezone":"Europe/Riga",
    "iso:country":"LV",
    "name:und_x_variant":[
        "Jaunlutri\u0146i",
        "Yaunlutrin\u2019skiy",
        "Myza Yaunmuyzha",
        "Jaunmui\u017ea"
    ],
    "wof:name":"Jaunlutrini",
    "wof:placetype":"locality"
},
  "geometry": {"coordinates":[22.40492,56.8286],"type":"Point"}
}