{
  "type": "Feature",
  "properties": {
    "gn:admin1_code":"53",
    "gn:admin2_code":"805200.0",
    "gn:asciiname":"Garupe",
    "gn:country_code":"LV",
    "gn:dem":4,
    "gn:feature_class":"P",
    "gn:feature_code":"PPL",
    "gn:name":"Garupe",
    "gn:population":0,
    "gn:timezone":"Europe/Riga",
    "iso:country":"LV",
    "name:und_x_variant":[
        "Arhitekts",
        "Jaunzemnieki",
        "Arkhitekts",
        "Garupe"
    ],
    "wof:name":"Garupe",
    "wof:placetype":"locality"
},
  "geometry": {"coordinates":[24.2348,57.12111],"type":"Point"}
}