{
  "type": "Feature",
  "properties": {
    "gn:admin1_code":"62",
    "gn:asciiname":"Ozolpils",
    "gn:country_code":"LV",
    "gn:dem":58,
    "gn:feature_class":"P",
    "gn:feature_code":"PPL",
    "gn:name":"Ozolpils",
    "gn:population":0,
    "gn:timezone":"Europe/Riga",
    "iso:country":"LV",
    "wof:name":"Ozolpils",
    "wof:placetype":"locality"
},
  "geometry": {"coordinates":[23.26274,56.9199],"type":"Point"}
}