{
  "type": "Feature",
  "properties": {
    "gn:admin1_code":"18",
    "gn:admin2_code":"660276.0",
    "gn:asciiname":"Skultes Muiza",
    "gn:country_code":"LV",
    "gn:dem":38,
    "gn:feature_class":"P",
    "gn:feature_code":"PPL",
    "gn:name":"Skultes Mui\u017ea",
    "gn:population":0,
    "gn:timezone":"Europe/Riga",
    "iso:country":"LV",
    "name:und_x_variant":[
        "Myza Skulte",
        "Skujnese",
        "Skulte",
        "Skultesmuyzha",
        "Straumes",
        "Skultesmui\u017ea",
        "Skultes Mui\u017ea"
    ],
    "wof:name":"Skultes Muiza",
    "wof:placetype":"locality"
},
  "geometry": {"coordinates":[24.49453,57.37369],"type":"Point"}
}