{
  "type": "Feature",
  "properties": {
    "gn:admin1_code":"20",
    "gn:admin2_code":"700276.0",
    "gn:asciiname":"Salas",
    "gn:country_code":"LV",
    "gn:dem":117,
    "gn:feature_class":"P",
    "gn:feature_code":"PPL",
    "gn:name":"Salas",
    "gn:population":0,
    "gn:timezone":"Europe/Riga",
    "iso:country":"LV",
    "name:arg_x_preferred":[
        "Salas"
    ],
    "name:cat_x_preferred":[
        "Salas"
    ],
    "name:ceb_x_preferred":[
        "Salas"
    ],
    "name:deu_x_preferred":[
        "Salas"
    ],
    "name:fra_x_preferred":[
        "Salas"
    ],
    "name:glg_x_preferred":[
        "Salas"
    ],
    "name:ind_x_preferred":[
        "Salas"
    ],
    "name:jpn_x_preferred":[
        "\u30b5\u30fc\u30e9\u30b9"
    ],
    "name:lav_x_preferred":[
        "Salas"
    ],
    "name:oci_x_preferred":[
        "Salas"
    ],
    "name:por_x_preferred":[
        "Salas"
    ],
    "name:ron_x_preferred":[
        "S\u0103la\u0219"
    ],
    "name:rus_x_preferred":[
        "\u0421\u0430\u043b\u0430\u0441"
    ],
    "name:spa_x_preferred":[
        "Salas"
    ],
    "name:swe_x_preferred":[
        "Salas"
    ],
    "name:tur_x_preferred":[
        "Salas"
    ],
    "name:zho_x_preferred":[
        "\u8428\u62c9\u65af"
    ],
    "wof:name":"Salas",
    "wof:placetype":"locality"
},
  "geometry": {"coordinates":[26.29749,56.67896],"type":"Point"}
}