{
  "type": "Feature",
  "properties": {
    "gn:admin1_code":"20",
    "gn:admin2_code":"700276.0",
    "gn:asciiname":"Salas",
    "gn:country_code":"LV",
    "gn:dem":117,
    "gn:feature_class":"P",
    "gn:feature_code":"PPL",
    "gn:name":"Salas",
    "gn:population":0,
    "gn:timezone":"Europe/Riga",
    "iso:country":"LV",
    "wof:name":"Salas",
    "wof:placetype":"locality"
},
  "geometry": {"coordinates":[26.29749,56.67896],"type":"Point"}
}