{
  "type": "Feature",
  "properties": {
    "gn:admin1_code":"12",
    "gn:admin2_code":"540286.0",
    "gn:asciiname":"Klivmuiza",
    "gn:country_code":"LV",
    "gn:dem":1,
    "gn:feature_class":"P",
    "gn:feature_code":"PPL",
    "gn:name":"Kl\u012bvmui\u017ea",
    "gn:population":0,
    "gn:timezone":"Europe/Riga",
    "iso:country":"LV",
    "name:und_x_variant":[
        "Polumyza Klives",
        "Kl\u012bve",
        "Kl\u012bves Pusmui\u017ea",
        "Kl\u012bvmui\u017ea"
    ],
    "wof:name":"Klivmuiza",
    "wof:placetype":"locality"
},
  "geometry": {"coordinates":[23.60391,56.80651],"type":"Point"}
}