{
  "type": "Feature",
  "properties": {
    "gn:admin1_code":"31",
    "gn:asciiname":"Jaunvale",
    "gn:cc2":"LV",
    "gn:country_code":"LV",
    "gn:dem":72,
    "gn:feature_class":"P",
    "gn:feature_code":"PPL",
    "gn:name":"Jaunv\u0101le",
    "gn:population":0,
    "gn:timezone":"Europe/Riga",
    "iso:country":"LV",
    "name:und_x_variant":[
        "Myza Yaunvale",
        "Jaunv\u0101les Mui\u017ea",
        "Jaunv\u0101le"
    ],
    "wof:name":"Jaunvale",
    "wof:placetype":"locality"
},
  "geometry": {"coordinates":[25.6148,57.48135],"type":"Point"}
}