{
  "type": "Feature",
  "properties": {
    "gn:admin1_code":"33",
    "gn:admin2_code":"980294.0",
    "gn:asciiname":"Dzikli",
    "gn:country_code":"LV",
    "gn:dem":14,
    "gn:feature_class":"P",
    "gn:feature_code":"PPL",
    "gn:name":"Dzik\u013ci",
    "gn:population":0,
    "gn:timezone":"Europe/Riga",
    "iso:country":"LV",
    "wof:name":"Dzikli",
    "wof:placetype":"locality"
},
  "geometry": {"coordinates":[21.77164,57.15393],"type":"Point"}
}