{
  "type": "Feature",
  "properties": {
    "gn:admin1_code":"04",
    "gn:admin2_code":"400256.0",
    "gn:asciiname":"Lambarte",
    "gn:country_code":"LV",
    "gn:dem":28,
    "gn:feature_class":"P",
    "gn:feature_code":"PPL",
    "gn:name":"Lamb\u0101rte",
    "gn:population":0,
    "gn:timezone":"Europe/Riga",
    "iso:country":"LV",
    "name:und_x_variant":[
        "Puksi",
        "Myza Lambarte",
        "Lamb\u0101rte"
    ],
    "wof:name":"Lambarte",
    "wof:placetype":"locality"
},
  "geometry": {"coordinates":[24.34989,56.52121],"type":"Point"}
}