{
  "type": "Feature",
  "properties": {
    "gn:admin1_code":"27",
    "gn:asciiname":"Sturi",
    "gn:cc2":"LV",
    "gn:country_code":"LV",
    "gn:dem":117,
    "gn:feature_class":"P",
    "gn:feature_code":"PPL",
    "gn:name":"St\u016bri",
    "gn:population":0,
    "gn:timezone":"Europe/Riga",
    "iso:country":"LV",
    "name:und_x_variant":[
        "Sturukrogs",
        "St\u016bri"
    ],
    "wof:name":"Sturi",
    "wof:placetype":"locality"
},
  "geometry": {"coordinates":[22.75681,56.58554],"type":"Point"}
}