{
  "type": "Feature",
  "properties": {
    "gn:admin1_code":"77",
    "gn:admin2_code":"901262.0",
    "gn:asciiname":"Upesjani",
    "gn:country_code":"LV",
    "gn:dem":70,
    "gn:feature_class":"P",
    "gn:feature_code":"PPL",
    "gn:name":"Upesj\u0101\u0146i",
    "gn:population":0,
    "gn:timezone":"Europe/Riga",
    "iso:country":"LV",
    "name:und_x_variant":[
        "Upes\u2019yani",
        "Upesj\u0101\u0146i"
    ],
    "wof:name":"Upesjani",
    "wof:placetype":"locality"
},
  "geometry": {"coordinates":[22.76667,57.08333],"type":"Point"}
}