{
  "type": "Feature",
  "properties": {
    "gn:admin1_code":"24",
    "gn:admin2_code":"780272.0",
    "gn:asciiname":"Zelenpole",
    "gn:country_code":"LV",
    "gn:dem":185,
    "gn:feature_class":"P",
    "gn:feature_code":"PPL",
    "gn:name":"Zelenpole",
    "gn:population":0,
    "gn:timezone":"Europe/Riga",
    "iso:country":"LV",
    "name:und_x_variant":[
        "Ze\u013cenpole"
    ],
    "wof:name":"Zelenpole",
    "wof:placetype":"locality"
},
  "geometry": {"coordinates":[27.50173,56.26197],"type":"Point"}
}