{
  "type": "Feature",
  "properties": {
    "gn:admin1_code":"C9",
    "gn:admin2_code":"621268.0",
    "gn:asciiname":"Tukums",
    "gn:country_code":"LV",
    "gn:dem":47,
    "gn:feature_class":"P",
    "gn:feature_code":"PPL",
    "gn:name":"Tukums",
    "gn:population":0,
    "gn:timezone":"Europe/Riga",
    "iso:country":"LV",
    "name:und_x_variant":[
        "Tukummui\u017ea",
        "T\u016bkumi",
        "Tukums",
        "Tukuma Mui\u017ea"
    ],
    "wof:name":"Tukums",
    "wof:placetype":"locality"
},
  "geometry": {"coordinates":[21.99426,56.55608],"type":"Point"}
}