{
  "type": "Feature",
  "properties": {
    "gn:admin1_code":"C9",
    "gn:admin2_code":"621268.0",
    "gn:asciiname":"Tukums",
    "gn:country_code":"LV",
    "gn:dem":47,
    "gn:feature_class":"P",
    "gn:feature_code":"PPL",
    "gn:name":"Tukums",
    "gn:population":0,
    "gn:timezone":"Europe/Riga",
    "iso:country":"LV",
    "name:ara_x_preferred":[
        "\u062a\u0648\u0643\u0648\u0645\u0648\u0633"
    ],
    "name:bak_x_preferred":[
        "\u0422\u0443\u043a\u0443\u043c\u0441"
    ],
    "name:bel_x_preferred":[
        "\u0422\u0443\u043a\u0443\u043c\u0441"
    ],
    "name:bul_x_preferred":[
        "\u0422\u0443\u043a\u0443\u043c\u0441"
    ],
    "name:cat_x_preferred":[
        "Tukums"
    ],
    "name:ceb_x_preferred":[
        "Tukums"
    ],
    "name:ces_x_preferred":[
        "Tukums"
    ],
    "name:dan_x_preferred":[
        "Tukums"
    ],
    "name:deu_x_preferred":[
        "Tukums"
    ],
    "name:epo_x_preferred":[
        "Tukums"
    ],
    "name:est_x_preferred":[
        "Tukums"
    ],
    "name:fas_x_preferred":[
        "\u062a\u0648\u06a9\u0648\u0645\u0633"
    ],
    "name:fin_x_preferred":[
        "Tukums"
    ],
    "name:fra_x_preferred":[
        "Tukums"
    ],
    "name:hsb_x_preferred":[
        "Tukums"
    ],
    "name:hun_x_preferred":[
        "Tukums"
    ],
    "name:hye_x_preferred":[
        "\u054f\u0578\u0582\u056f\u0578\u0582\u0574\u057d"
    ],
    "name:jpn_x_preferred":[
        "\u30c8\u30a5\u30af\u30e0\u30b9"
    ],
    "name:kaz_x_preferred":[
        "\u0422\u0443\u043a\u0443\u043c\u0441"
    ],
    "name:kor_x_preferred":[
        "\ud22c\ucff0\uc2a4"
    ],
    "name:lav_x_preferred":[
        "Tukums"
    ],
    "name:lit_x_preferred":[
        "Tukumas"
    ],
    "name:ltg_x_preferred":[
        "Tukums"
    ],
    "name:nld_x_preferred":[
        "Tukums"
    ],
    "name:nor_x_preferred":[
        "Tukums"
    ],
    "name:pol_x_preferred":[
        "Tukums"
    ],
    "name:por_x_preferred":[
        "Tukums"
    ],
    "name:rus_x_preferred":[
        "\u0422\u0443\u043a\u0443\u043c\u0441"
    ],
    "name:spa_x_preferred":[
        "Tukums"
    ],
    "name:srp_x_preferred":[
        "\u0422\u0443\u043a\u0443\u043c\u0441"
    ],
    "name:swe_x_preferred":[
        "Tukums"
    ],
    "name:tat_x_preferred":[
        "\u0422\u0443\u043a\u0443\u043c\u0441"
    ],
    "name:tur_x_preferred":[
        "Tukums"
    ],
    "name:ukr_x_preferred":[
        "\u0422\u0443\u043a\u0443\u043c\u0441"
    ],
    "name:und_x_variant":[
        "Tukummui\u017ea",
        "T\u016bkumi",
        "Tukuma Mui\u017ea"
    ],
    "name:zho_x_preferred":[
        "\u5716\u5eab\u59c6\u65af"
    ],
    "wof:name":"Tukums",
    "wof:placetype":"locality"
},
  "geometry": {"coordinates":[21.99426,56.55608],"type":"Point"}
}