{
  "type": "Feature",
  "properties": {
    "gn:admin1_code":"E2",
    "gn:admin2_code":"769190.0",
    "gn:asciiname":"Macani",
    "gn:country_code":"LV",
    "gn:dem":96,
    "gn:feature_class":"P",
    "gn:feature_code":"PPL",
    "gn:name":"Ma\u010d\u0101ni",
    "gn:population":0,
    "gn:timezone":"Europe/Riga",
    "iso:country":"LV",
    "name:und_x_variant":[
        "Machani",
        "Ma\u010danu Pusmui\u017ea",
        "Ma\u010d\u0101ni"
    ],
    "wof:name":"Macani",
    "wof:placetype":"locality"
},
  "geometry": {"coordinates":[26.40019,56.25271],"type":"Point"}
}