{
  "type": "Feature",
  "properties": {
    "gn:admin1_code":"33",
    "gn:admin2_code":"980233.0",
    "gn:asciiname":"Cunca",
    "gn:country_code":"LV",
    "gn:dem":25,
    "gn:feature_class":"P",
    "gn:feature_code":"PPL",
    "gn:name":"\u010cun\u010da",
    "gn:population":0,
    "gn:timezone":"Europe/Riga",
    "iso:country":"LV",
    "wof:name":"Cunca",
    "wof:placetype":"locality"
},
  "geometry": {"coordinates":[21.78333,57.28333000000001],"type":"Point"}
}