{
  "type": "Feature",
  "properties": {
    "gn:admin1_code":"35",
    "gn:admin2_code":"604342.0",
    "gn:asciiname":"Kodori",
    "gn:country_code":"LV",
    "gn:dem":155,
    "gn:feature_class":"P",
    "gn:feature_code":"PPL",
    "gn:name":"Kodori",
    "gn:population":0,
    "gn:timezone":"Europe/Riga",
    "iso:country":"LV",
    "name:heb_x_preferred":[
        "\u05e7\u05d5\u05d3\u05d5\u05e8\u05d9"
    ],
    "name:nld_x_preferred":[
        "Kodori"
    ],
    "name:spa_x_preferred":[
        "Kodori"
    ],
    "name:swe_x_preferred":[
        "Kodori"
    ],
    "name:und_x_variant":[
        "Kodory",
        "Kodari",
        "Kodori"
    ],
    "wof:name":"Kodori",
    "wof:placetype":"locality"
},
  "geometry": {"coordinates":[26.95104000000001,56.15614],"type":"Point"}
}