{
  "type": "Feature",
  "properties": {
    "gn:admin1_code":"A5",
    "gn:admin2_code":"641486.0",
    "gn:asciiname":"Riva",
    "gn:country_code":"LV",
    "gn:dem":20,
    "gn:feature_class":"P",
    "gn:feature_code":"PPL",
    "gn:name":"R\u012bva",
    "gn:population":0,
    "gn:timezone":"Europe/Riga",
    "iso:country":"LV",
    "name:lav_x_preferred":[
        "R\u012bva"
    ],
    "wof:name":"Riva",
    "wof:placetype":"locality"
},
  "geometry": {"coordinates":[21.40105,56.90733],"type":"Point"}
}