{
  "type": "Feature",
  "properties": {
    "gn:admin1_code":"37",
    "gn:admin2_code":"640648.0",
    "gn:asciiname":"Jurgumuiza",
    "gn:country_code":"LV",
    "gn:dem":43,
    "gn:feature_class":"P",
    "gn:feature_code":"PPL",
    "gn:name":"Jur\u0123umui\u017ea",
    "gn:population":0,
    "gn:timezone":"Europe/Riga",
    "iso:country":"LV",
    "name:und_x_variant":[
        "Yurdi",
        "Jur\u0123u",
        "Jur\u0123umui\u017ea"
    ],
    "wof:name":"Jurgumuiza",
    "wof:placetype":"locality"
},
  "geometry": {"coordinates":[21.36899,56.74571],"type":"Point"}
}