{
  "type": "Feature",
  "properties": {
    "gn:admin1_code":"37",
    "gn:admin2_code":"640666.0",
    "gn:asciiname":"Lieldroga",
    "gn:country_code":"LV",
    "gn:dem":108,
    "gn:feature_class":"P",
    "gn:feature_code":"PPL",
    "gn:name":"Lieldroga",
    "gn:population":0,
    "gn:timezone":"Europe/Riga",
    "iso:country":"LV",
    "name:und_x_variant":[
        "Liyeldroga",
        "Lieldrogas",
        "Lieldroga"
    ],
    "wof:name":"Lieldroga",
    "wof:placetype":"locality"
},
  "geometry": {"coordinates":[21.68333,56.58333],"type":"Point"}
}