{
  "type": "Feature",
  "properties": {
    "gn:admin1_code":"14",
    "gn:admin2_code":"600286.0",
    "gn:asciiname":"Jonini",
    "gn:country_code":"LV",
    "gn:dem":165,
    "gn:feature_class":"P",
    "gn:feature_code":"PPL",
    "gn:name":"Jonini",
    "gn:population":0,
    "gn:timezone":"Europe/Riga",
    "iso:country":"LV",
    "name:und_x_variant":[
        "Jo\u0146ini"
    ],
    "wof:name":"Jonini",
    "wof:placetype":"locality"
},
  "geometry": {"coordinates":[27.62238,55.92661],"type":"Point"}
}