{
  "type": "Feature",
  "properties": {
    "gn:admin1_code":"37",
    "gn:admin2_code":"640642.0",
    "gn:asciiname":"Kudra",
    "gn:country_code":"LV",
    "gn:dem":65,
    "gn:feature_class":"P",
    "gn:feature_code":"PPL",
    "gn:name":"K\u016bdra",
    "gn:population":0,
    "gn:timezone":"Europe/Riga",
    "iso:country":"LV",
    "name:urd_x_preferred":[
        "\u06a9\u062f\u0631\u0627"
    ],
    "wof:name":"Kudra",
    "wof:placetype":"locality"
},
  "geometry": {"coordinates":[21.57209,56.72969000000001],"type":"Point"}
}