{
  "type": "Feature",
  "properties": {
    "gn:admin1_code":"24",
    "gn:admin2_code":"780280.0",
    "gn:asciiname":"Babri",
    "gn:country_code":"LV",
    "gn:dem":165,
    "gn:feature_class":"P",
    "gn:feature_code":"PPL",
    "gn:name":"Babri",
    "gn:population":0,
    "gn:timezone":"Europe/Riga",
    "iso:country":"LV",
    "name:und_x_variant":[
        "Bebri"
    ],
    "wof:name":"Babri",
    "wof:placetype":"locality"
},
  "geometry": {"coordinates":[27.19851,56.23791],"type":"Point"}
}