{
  "type": "Feature",
  "properties": {
    "gn:admin1_code":"12",
    "gn:admin2_code":"540262.0",
    "gn:asciiname":"Mastiki",
    "gn:country_code":"LV",
    "gn:dem":1,
    "gn:feature_class":"P",
    "gn:feature_code":"PPL",
    "gn:name":"Masti\u0137i",
    "gn:population":0,
    "gn:timezone":"Europe/Riga",
    "iso:country":"LV",
    "wof:name":"Mastiki",
    "wof:placetype":"locality"
},
  "geometry": {"coordinates":[23.66,56.74028000000001],"type":"Point"}
}