{
  "type": "Feature",
  "properties": {
    "gn:admin1_code":"07",
    "gn:admin2_code":"440296.0",
    "gn:asciiname":"Rudziniski",
    "gn:country_code":"LV",
    "gn:dem":168,
    "gn:feature_class":"P",
    "gn:feature_code":"PPL",
    "gn:name":"Rudzini\u0161ki",
    "gn:population":0,
    "gn:timezone":"Europe/Riga",
    "iso:country":"LV",
    "name:und_x_variant":[
        "Rudinishki",
        "Rudni\u0161ku Pusmui\u017ea",
        "Rudz\u012b\u0161i",
        "Rudzini\u0161ki"
    ],
    "wof:name":"Rudziniski",
    "wof:placetype":"locality"
},
  "geometry": {"coordinates":[26.80479,55.86489],"type":"Point"}
}