{
  "type": "Feature",
  "properties": {
    "gn:admin1_code":"09",
    "gn:admin2_code":"500290.0",
    "gn:asciiname":"Staki",
    "gn:country_code":"LV",
    "gn:dem":131,
    "gn:feature_class":"P",
    "gn:feature_code":"PPL",
    "gn:name":"St\u0101\u0137i",
    "gn:population":0,
    "gn:timezone":"Europe/Riga",
    "iso:country":"LV",
    "name:und_x_variant":[
        "Stati",
        "St\u0101\u0137i"
    ],
    "wof:name":"Staki",
    "wof:placetype":"locality"
},
  "geometry": {"coordinates":[26.73119,57.13343],"type":"Point"}
}