{
  "type": "Feature",
  "properties": {
    "gn:admin1_code":"91",
    "gn:admin2_code":"701458.0",
    "gn:asciiname":"Ergala",
    "gn:country_code":"LV",
    "gn:dem":92,
    "gn:feature_class":"P",
    "gn:feature_code":"PPL",
    "gn:name":"\u011argala",
    "gn:population":0,
    "gn:timezone":"Europe/Riga",
    "iso:country":"LV",
    "wof:name":"Ergala",
    "wof:placetype":"locality"
},
  "geometry": {"coordinates":[26.81023,56.92184],"type":"Point"}
}