{
  "type": "Feature",
  "properties": {
    "gn:gn_country":"LV",
    "gn:gn_fcode":"PPL",
    "gn:gn_pop":0,
    "iso:country":"LV",
    "name:eng_x_preferred":[
        "Krusti\u0146i"
    ],
    "name:est_x_preferred":[
        "Krusti\u0146i"
    ],
    "name:lav_x_preferred":[
        "Krusti\u0146i"
    ],
    "name:nld_x_preferred":[
        "Krusti\u0146i"
    ],
    "name:rus_x_preferred":[
        "\u041a\u0440\u0443\u0441\u0442\u044b\u043d\u0438"
    ],
    "name:unk_x_variant":[
        "Senite"
    ],
    "qs_pg:aaroncc":"LV",
    "qs_pg:gn_country":"LV",
    "qs_pg:gn_fcode":"PPL",
    "qs_pg:gn_pop":0,
    "qs_pg:name":"Krusti\u0146i",
    "qs_pg:name_adm0":"Latvija",
    "qs_pg:name_adm1":"In\u010dukalna Novads",
    "qs_pg:photos":15,
    "qs_pg:photos_1k":3,
    "qs_pg:photos_9k":1,
    "qs_pg:photos_9r":1,
    "qs_pg:photos_all":15,
    "qs_pg:photos_sr":1,
    "qs_pg:pop_sr":0,
    "qs_pg:qs_pg_placetype":"locality",
    "qs_pg:qs_pg_placetype_gp":"Town",
    "qs_pg:woe_adm0":23424874,
    "woe:adm0_id":23424874,
    "woe:name_adm0":"Latvija",
    "woe:name_adm1":"In\u010dukalna Novads",
    "woe:placetype":"Town",
    "wof:name":"Krusti\u0146i",
    "wof:placetype":"locality"
},
  "geometry": {"coordinates":[24.65222,57.12139],"type":"Point"}
}