{
  "type": "Feature",
  "properties": {
    "gn:admin1_code":"01",
    "gn:admin2_code":"320244.0",
    "gn:asciiname":"Gridzini",
    "gn:country_code":"LV",
    "gn:dem":83,
    "gn:feature_class":"P",
    "gn:feature_code":"PPL",
    "gn:name":"Gridzini",
    "gn:population":0,
    "gn:timezone":"Europe/Riga",
    "iso:country":"LV",
    "wof:name":"Gridzini",
    "wof:placetype":"locality"
},
  "geometry": {"coordinates":[25.18333,56.61666999999999],"type":"Point"}
}