{
  "type": "Feature",
  "properties": {
    "gn:admin1_code":"19",
    "gn:admin2_code":"680278.0",
    "gn:asciiname":"Andri",
    "gn:country_code":"LV",
    "gn:dem":177,
    "gn:feature_class":"P",
    "gn:feature_code":"PPL",
    "gn:name":"Andri",
    "gn:population":0,
    "gn:timezone":"Europe/Riga",
    "iso:country":"LV",
    "wof:name":"Andri",
    "wof:placetype":"locality"
},
  "geometry": {"coordinates":[27.86336,56.35746],"type":"Point"}
}