{
  "type": "Feature",
  "properties": {
    "gn:admin1_code":"29",
    "gn:admin2_code":"900280.0",
    "gn:asciiname":"Tilmani",
    "gn:country_code":"LV",
    "gn:dem":52,
    "gn:feature_class":"P",
    "gn:feature_code":"PPL",
    "gn:name":"Tilma\u0146i",
    "gn:population":0,
    "gn:timezone":"Europe/Riga",
    "iso:country":"LV",
    "name:und_x_variant":[
        "Polumyza Tilmenu",
        "Tylmani",
        "Tilma\u0146i"
    ],
    "wof:name":"Tilmani",
    "wof:placetype":"locality"
},
  "geometry": {"coordinates":[23.24083,56.82806],"type":"Point"}
}