{
  "type": "Feature",
  "properties": {
    "gn:admin1_code":"22",
    "gn:asciiname":"Gribolva",
    "gn:country_code":"LV",
    "gn:dem":113,
    "gn:feature_class":"P",
    "gn:feature_code":"PPL",
    "gn:name":"Gribolva",
    "gn:population":0,
    "gn:timezone":"Europe/Riga",
    "iso:country":"LV",
    "wof:name":"Gribolva",
    "wof:placetype":"locality"
},
  "geometry": {"coordinates":[26.76922,56.49927],"type":"Point"}
}