{
  "type": "Feature",
  "properties": {
    "gn:admin1_code":"71",
    "gn:admin2_code":"321078.0",
    "gn:asciiname":"Pastamuiza",
    "gn:country_code":"LV",
    "gn:dem":87,
    "gn:feature_class":"P",
    "gn:feature_code":"PPL",
    "gn:name":"Pastamui\u017ea",
    "gn:population":0,
    "gn:timezone":"Europe/Riga",
    "iso:country":"LV",
    "name:und_x_variant":[
        "Myza Pasta",
        "Pastmui\u017ea",
        "Pastamui\u017ea"
    ],
    "wof:name":"Pastamuiza",
    "wof:placetype":"locality"
},
  "geometry": {"coordinates":[25.45,56.61666999999999],"type":"Point"}
}