{
  "type": "Feature",
  "properties": {
    "gn:admin1_code":"D1",
    "gn:admin2_code":"941690.0",
    "gn:asciiname":"Kengi",
    "gn:country_code":"LV",
    "gn:dem":163,
    "gn:feature_class":"P",
    "gn:feature_code":"PPL",
    "gn:name":"\u0136e\u0146\u0123i",
    "gn:population":0,
    "gn:timezone":"Europe/Riga",
    "iso:country":"LV",
    "name:und_x_variant":[
        "Fol\u2019vark Kenge",
        "\u0136e\u0146gis",
        "\u0136e\u0146\u0123i"
    ],
    "wof:name":"Kengi",
    "wof:placetype":"locality"
},
  "geometry": {"coordinates":[26.08235,57.31958],"type":"Point"}
}