{
  "type": "Feature",
  "properties": {
    "gn:admin1_code":"14",
    "gn:admin2_code":"600268.0",
    "gn:asciiname":"Boraukas",
    "gn:cc2":"LV",
    "gn:country_code":"LV",
    "gn:dem":159,
    "gn:feature_class":"P",
    "gn:feature_code":"PPL",
    "gn:name":"Boraukas",
    "gn:population":0,
    "gn:timezone":"Europe/Riga",
    "iso:country":"LV",
    "name:und_x_variant":[
        "Borovka",
        "Boraukas"
    ],
    "wof:name":"Boraukas",
    "wof:placetype":"locality"
},
  "geometry": {"coordinates":[27.27931,55.8968],"type":"Point"}
}