{
  "type": "Feature",
  "properties": {
    "gn:admin1_code":"33",
    "gn:admin2_code":"980266.0",
    "gn:asciiname":"Darzini",
    "gn:country_code":"LV",
    "gn:dem":2,
    "gn:feature_class":"P",
    "gn:feature_code":"PPL",
    "gn:name":"D\u0101rzini",
    "gn:population":0,
    "gn:timezone":"Europe/Riga",
    "iso:country":"LV",
    "wof:name":"Darzini",
    "wof:placetype":"locality"
},
  "geometry": {"coordinates":[21.63333,57.36666999999999],"type":"Point"}
}