{
  "type": "Feature",
  "properties": {
    "gn:admin1_code":"71",
    "gn:asciiname":"Robezkrogs",
    "gn:country_code":"LV",
    "gn:dem":78,
    "gn:feature_class":"P",
    "gn:feature_code":"PPL",
    "gn:name":"Robe\u017ekrogs",
    "gn:population":0,
    "gn:timezone":"Europe/Riga",
    "iso:country":"LV",
    "wof:name":"Robezkrogs",
    "wof:placetype":"locality"
},
  "geometry": {"coordinates":[25.56393,56.56513],"type":"Point"}
}