{
  "type": "Feature",
  "properties": {
    "gn:admin1_code":"14",
    "gn:admin2_code":"600288.0",
    "gn:asciiname":"Kazinci",
    "gn:country_code":"LV",
    "gn:dem":167,
    "gn:feature_class":"P",
    "gn:feature_code":"PPL",
    "gn:name":"Kazi\u0146\u010di",
    "gn:population":0,
    "gn:timezone":"Europe/Riga",
    "iso:country":"LV",
    "name:und_x_variant":[
        "Mazin\u010di",
        "Kazinauci",
        "Kazinovtsy",
        "Kazi\u0146\u010di"
    ],
    "wof:name":"Kazinci",
    "wof:placetype":"locality"
},
  "geometry": {"coordinates":[27.39766,56.01521999999999],"type":"Point"}
}