{
  "type": "Feature",
  "properties": {
    "gn:admin1_code":"15",
    "gn:admin2_code":"620296.0",
    "gn:asciiname":"Duras",
    "gn:country_code":"LV",
    "gn:dem":70,
    "gn:feature_class":"P",
    "gn:feature_code":"PPL",
    "gn:name":"D\u016bras",
    "gn:population":0,
    "gn:timezone":"Europe/Riga",
    "iso:country":"LV",
    "name:und_x_variant":[
        "D\u016bras",
        "D\u016bri",
        "D\u016brupe"
    ],
    "wof:name":"Duras",
    "wof:placetype":"locality"
},
  "geometry": {"coordinates":[22.21507,56.82363],"type":"Point"}
}