{
  "type": "Feature",
  "properties": {
    "gn:admin1_code":"15",
    "gn:admin2_code":"620296.0",
    "gn:asciiname":"Duras",
    "gn:country_code":"LV",
    "gn:dem":70,
    "gn:feature_class":"P",
    "gn:feature_code":"PPL",
    "gn:name":"D\u016bras",
    "gn:population":0,
    "gn:timezone":"Europe/Riga",
    "iso:country":"LV",
    "name:ceb_x_preferred":[
        "Duras"
    ],
    "name:ces_x_preferred":[
        "Duras"
    ],
    "name:deu_x_preferred":[
        "Duras"
    ],
    "name:fra_x_preferred":[
        "Duras"
    ],
    "name:glg_x_preferred":[
        "Duras"
    ],
    "name:jpn_x_preferred":[
        "\u30c7\u30e5\u30e9\u30b9"
    ],
    "name:nds_x_preferred":[
        "Duras"
    ],
    "name:nld_x_preferred":[
        "Duras"
    ],
    "name:rus_x_preferred":[
        "\u0414\u044e\u0440\u0430\u0441"
    ],
    "name:slk_x_preferred":[
        "Duras"
    ],
    "name:swe_x_preferred":[
        "Duras"
    ],
    "name:und_x_variant":[
        "D\u016bras",
        "D\u016bri",
        "D\u016brupe"
    ],
    "wof:name":"Duras",
    "wof:placetype":"locality"
},
  "geometry": {"coordinates":[22.21507,56.82363],"type":"Point"}
}