{
  "type": "Feature",
  "properties": {
    "gn:admin1_code":"15",
    "gn:admin2_code":"620292.0",
    "gn:asciiname":"Kikuri",
    "gn:cc2":"LV",
    "gn:country_code":"LV",
    "gn:dem":47,
    "gn:feature_class":"P",
    "gn:feature_code":"PPL",
    "gn:name":"\u0136ikuri",
    "gn:population":0,
    "gn:timezone":"Europe/Riga",
    "iso:country":"LV",
    "name:und_x_variant":[
        "Ezermali",
        "Myza Tikuri",
        "\u0136ikuri"
    ],
    "wof:name":"Kikuri",
    "wof:placetype":"locality"
},
  "geometry": {"coordinates":[21.66611,56.80104],"type":"Point"}
}