{
  "type": "Feature",
  "properties": {
    "gn:admin1_code":"A3",
    "gn:admin2_code":"546744.0",
    "gn:asciiname":"Cenu",
    "gn:country_code":"LV",
    "gn:dem":3,
    "gn:feature_class":"P",
    "gn:feature_code":"PPL",
    "gn:name":"Cenu",
    "gn:population":0,
    "gn:timezone":"Europe/Riga",
    "iso:country":"LV",
    "wof:name":"Cenu",
    "wof:placetype":"locality"
},
  "geometry": {"coordinates":[23.8587,56.69584],"type":"Point"}
}