{
  "type": "Feature",
  "properties": {
    "gn:admin1_code":"44",
    "gn:admin2_code":"460825.0",
    "gn:asciiname":"Bruveri",
    "gn:country_code":"LV",
    "gn:dem":107,
    "gn:feature_class":"P",
    "gn:feature_code":"PPL",
    "gn:name":"Br\u016bveri",
    "gn:population":0,
    "gn:timezone":"Europe/Riga",
    "iso:country":"LV",
    "name:und_x_variant":[
        "Br\u016bveli",
        "Br\u016bveri"
    ],
    "wof:name":"Bruveri",
    "wof:placetype":"locality"
},
  "geometry": {"coordinates":[22.88333,56.48333],"type":"Point"}
}