{
  "type": "Feature",
  "properties": {
    "gn:admin1_code":"03",
    "gn:admin2_code":"380294.0",
    "gn:asciiname":"Viksna",
    "gn:country_code":"LV",
    "gn:dem":129,
    "gn:feature_class":"P",
    "gn:feature_code":"PPL",
    "gn:name":"V\u012bksna",
    "gn:population":0,
    "gn:timezone":"Europe/Riga",
    "iso:country":"LV",
    "name:und_x_variant":[
        "Kubulyshki",
        "Vikstume\u017es",
        "Kubuli\u0161\u0137i",
        "Viksnumezh",
        "Vikstumezhs",
        "V\u012bksna"
    ],
    "wof:name":"Viksna",
    "wof:placetype":"locality"
},
  "geometry": {"coordinates":[27.32077,57.21494000000001],"type":"Point"}
}