{
  "type": "Feature",
  "properties": {
    "gn:admin1_code":"14",
    "gn:asciiname":"Ozolini",
    "gn:country_code":"LV",
    "gn:dem":187,
    "gn:feature_class":"P",
    "gn:feature_code":"PPL",
    "gn:name":"Ozoli\u0146i",
    "gn:population":0,
    "gn:timezone":"Europe/Riga",
    "iso:country":"LV",
    "wof:name":"Ozolini",
    "wof:placetype":"locality"
},
  "geometry": {"coordinates":[27.512,56.08746],"type":"Point"}
}