{
  "type": "Feature",
  "properties": {
    "gn:admin1_code":"09",
    "gn:admin2_code":"500284.0",
    "gn:asciiname":"Birzuli",
    "gn:country_code":"LV",
    "gn:dem":184,
    "gn:feature_class":"P",
    "gn:feature_code":"PPL",
    "gn:name":"Birzu\u013ci",
    "gn:population":0,
    "gn:timezone":"Europe/Riga",
    "iso:country":"LV",
    "wof:name":"Birzuli",
    "wof:placetype":"locality"
},
  "geometry": {"coordinates":[26.22128,57.17313000000001],"type":"Point"}
}