{
  "type": "Feature",
  "properties": {
    "gn:admin1_code":"33",
    "gn:admin2_code":"980270.0",
    "gn:asciiname":"Dzirnavas",
    "gn:country_code":"LV",
    "gn:dem":25,
    "gn:feature_class":"P",
    "gn:feature_code":"PPL",
    "gn:name":"Dzirnavas",
    "gn:population":0,
    "gn:timezone":"Europe/Riga",
    "iso:country":"LV",
    "wof:name":"Dzirnavas",
    "wof:placetype":"locality"
},
  "geometry": {"coordinates":[22.08409,57.24325],"type":"Point"}
}