{
  "type": "Feature",
  "properties": {
    "gn:admin1_code":"A5",
    "gn:admin2_code":"641496.0",
    "gn:asciiname":"Ziemupe",
    "gn:cc2":"LV",
    "gn:country_code":"LV",
    "gn:dem":12,
    "gn:feature_class":"P",
    "gn:feature_code":"PPL",
    "gn:name":"Ziemupe",
    "gn:population":0,
    "gn:timezone":"Europe/Riga",
    "iso:country":"LV",
    "name:und_x_variant":[
        "Ziyemupe",
        "Zemuppen Farm",
        "Ziemupes Mui\u017eas Centrs",
        "Ziemupes Mui\u017ea",
        "Ziemupe"
    ],
    "wof:name":"Ziemupe",
    "wof:placetype":"locality"
},
  "geometry": {"coordinates":[21.07669,56.74833],"type":"Point"}
}