{
  "type": "Feature",
  "properties": {
    "gn:admin1_code":"02",
    "gn:admin2_code":"360256.0",
    "gn:asciiname":"Silenieku Dzirnavas",
    "gn:country_code":"LV",
    "gn:dem":143,
    "gn:feature_class":"P",
    "gn:feature_code":"PPL",
    "gn:name":"Silenieku Dzirnavas",
    "gn:population":0,
    "gn:timezone":"Europe/Riga",
    "iso:country":"LV",
    "name:und_x_variant":[
        "Yaunsilenyeki",
        "Jaunsilnieki",
        "Jaunsilenieki",
        "Silenieku Dzirnavas"
    ],
    "wof:name":"Silenieku Dzirnavas",
    "wof:placetype":"locality"
},
  "geometry": {"coordinates":[27.32902,57.44035],"type":"Point"}
}