{
  "type": "Feature",
  "properties": {
    "gn:admin1_code":"E2",
    "gn:admin2_code":"769194.0",
    "gn:asciiname":"Zakisi",
    "gn:country_code":"LV",
    "gn:dem":120,
    "gn:feature_class":"P",
    "gn:feature_code":"PPL",
    "gn:name":"Za\u0137\u012b\u0161i",
    "gn:population":0,
    "gn:timezone":"Europe/Riga",
    "iso:country":"LV",
    "name:und_x_variant":[
        "Za\u0137\u012b\u0161i",
        "\u0160usts"
    ],
    "wof:name":"Zakisi",
    "wof:placetype":"locality"
},
  "geometry": {"coordinates":[26.65691,56.19508],"type":"Point"}
}