{
  "type": "Feature",
  "properties": {
    "gn:admin1_code":"45",
    "gn:admin2_code":"804988.0",
    "gn:asciiname":"Spunciems",
    "gn:country_code":"LV",
    "gn:dem":5,
    "gn:feature_class":"P",
    "gn:feature_code":"PPL",
    "gn:name":"Spu\u0146ciems",
    "gn:population":0,
    "gn:timezone":"Europe/Riga",
    "iso:country":"LV",
    "name:und_x_variant":[
        "Spunn\u2019tsiyem",
        "Spuntsiems",
        "Spu\u0146\u0146ciems",
        "Spu\u0146ciems"
    ],
    "wof:name":"Spunciems",
    "wof:placetype":"locality"
},
  "geometry": {"coordinates":[23.70555,56.93048],"type":"Point"}
}