{
  "type": "Feature",
  "properties": {
    "iso:country":"LV",
    "name:dan_x_preferred":[
        "Zolit\u016bde"
    ],
    "name:deu_x_preferred":[
        "Zolit\u016bde"
    ],
    "name:eng_x_preferred":[
        "Zolit\u016bde"
    ],
    "name:est_x_preferred":[
        "Zolit\u016bde"
    ],
    "name:lav_x_preferred":[
        "Zolit\u016bde"
    ],
    "name:rus_x_preferred":[
        "\u0417\u043e\u043b\u0438\u0442\u0443\u0434\u0435"
    ],
    "name:und_x_variant":[
        "Zolitude"
    ],
    "qs:gn_adm0_cc":"LV",
    "qs:gn_fcode":"PPL",
    "qs:gn_local":456172,
    "qs:gn_name":"Zolit\u016bde",
    "qs:local_max":23404,
    "qs:local_sum":42602,
    "qs:localhoods":31,
    "qs:name":"Zolitude",
    "qs:name_adm0":"Latvija",
    "qs:name_adm1":"R\u013cga",
    "qs:name_adm2":"R\u013cga",
    "qs:name_local":"R\u012bga",
    "qs:photo_max":15,
    "qs:photo_sum":126,
    "qs:placetype":"Suburb",
    "qs:quad_count":40,
    "qs:woe_adm0":23424874,
    "qs:woe_adm1":20070121,
    "qs:woe_adm2":55844479,
    "qs:woe_lau":0,
    "qs:woe_local":854823,
    "qs:woe_ver":"7.10.0",
    "wd:wordcount":657,
    "wof:lang":[
        "unk"
    ],
    "wof:name":"Zolitude",
    "wof:placetype":"neighbourhood"
},
  "geometry": {"coordinates":[24.010275,56.942724],"type":"Point"}
}