{
  "type": "Feature",
  "properties": {
    "gn:admin1_code":"71",
    "gn:admin2_code":"321050.0",
    "gn:asciiname":"Rundale",
    "gn:country_code":"LV",
    "gn:dem":83,
    "gn:feature_class":"P",
    "gn:feature_code":"PPL",
    "gn:name":"Rundale",
    "gn:population":0,
    "gn:timezone":"Europe/Riga",
    "iso:country":"LV",
    "name:gle_x_preferred":[
        "Rond\u00e1il"
    ],
    "name:ita_x_preferred":[
        "Rundale"
    ],
    "wof:name":"Rundale",
    "wof:placetype":"locality"
},
  "geometry": {"coordinates":[25.18333,56.43333000000001],"type":"Point"}
}