{
  "type": "Feature",
  "properties": {
    "gn:admin1_code":"B7",
    "gn:admin2_code":"387574.0",
    "gn:asciiname":"Kraukleva",
    "gn:country_code":"LV",
    "gn:dem":114,
    "gn:feature_class":"P",
    "gn:feature_code":"PPL",
    "gn:name":"Krauk\u013ceva",
    "gn:population":0,
    "gn:timezone":"Europe/Riga",
    "iso:country":"LV",
    "name:und_x_variant":[
        "Krauklyava",
        "Krauk\u013ceva"
    ],
    "wof:name":"Kraukleva",
    "wof:placetype":"locality"
},
  "geometry": {"coordinates":[27.28794000000001,57.02128],"type":"Point"}
}