{
  "type": "Feature",
  "properties": {
    "gn:admin1_code":"24",
    "gn:admin2_code":"780276.0",
    "gn:asciiname":"Balbisi",
    "gn:country_code":"LV",
    "gn:dem":161,
    "gn:feature_class":"P",
    "gn:feature_code":"PPL",
    "gn:name":"Balbi\u0161i",
    "gn:population":0,
    "gn:timezone":"Europe/Riga",
    "iso:country":"LV",
    "name:und_x_variant":[
        "Balbi\u0161i",
        "Ozolaine"
    ],
    "wof:name":"Balbisi",
    "wof:placetype":"locality"
},
  "geometry": {"coordinates":[27.26474,56.44977],"type":"Point"}
}