{
  "type": "Feature",
  "properties": {
    "gn:admin1_code":"78",
    "gn:admin2_code":"681070.0",
    "gn:asciiname":"Mortuzani",
    "gn:country_code":"LV",
    "gn:dem":115,
    "gn:feature_class":"P",
    "gn:feature_code":"PPL",
    "gn:name":"Mortuz\u0101ni",
    "gn:population":0,
    "gn:timezone":"Europe/Riga",
    "iso:country":"LV",
    "name:eng_x_preferred":[
        "Martuz\u0101ni"
    ],
    "name:rus_x_preferred":[
        "\u041c\u0430\u0440\u0442\u0443\u0437\u0430\u043d\u0438"
    ],
    "name:und_x_variant":[
        "Martuz\u0101ni",
        "Mortuz\u0101ni"
    ],
    "wof:name":"Mortuzani",
    "wof:placetype":"locality"
},
  "geometry": {"coordinates":[27.6134,56.72633],"type":"Point"}
}