{
  "type": "Feature",
  "properties": {
    "gn:admin1_code":"20",
    "gn:admin2_code":"700268.0",
    "gn:asciiname":"Medzula",
    "gn:cc2":"LV",
    "gn:country_code":"LV",
    "gn:dem":231,
    "gn:feature_class":"P",
    "gn:feature_code":"PPL",
    "gn:name":"M\u0113dzula",
    "gn:population":0,
    "gn:timezone":"Europe/Riga",
    "iso:country":"LV",
    "name:und_x_variant":[
        "M\u0113dz\u016blas Mui\u017ea",
        "Myza Medzula",
        "M\u0113dzula"
    ],
    "wof:name":"Medzula",
    "wof:placetype":"locality"
},
  "geometry": {"coordinates":[25.9443,57.01994000000001],"type":"Point"}
}