{
  "type": "Feature",
  "properties": {
    "gn:admin1_code":"19",
    "gn:admin2_code":"680246.0",
    "gn:asciiname":"Konogolci",
    "gn:country_code":"LV",
    "gn:dem":115,
    "gn:feature_class":"P",
    "gn:feature_code":"PPL",
    "gn:name":"Konogo\u013cci",
    "gn:population":0,
    "gn:timezone":"Europe/Riga",
    "iso:country":"LV",
    "wof:name":"Konogolci",
    "wof:placetype":"locality"
},
  "geometry": {"coordinates":[28.10561,56.47608],"type":"Point"}
}