{
  "type": "Feature",
  "properties": {
    "iso:country":"LV",
    "name:dan_x_preferred":[
        "\u010ciekurkalns"
    ],
    "name:est_x_preferred":[
        "\u010ciekurkalns"
    ],
    "name:fra_x_preferred":[
        "\u010ciekurkalns"
    ],
    "name:lav_x_preferred":[
        "\u010ciekurkalns"
    ],
    "name:rus_x_preferred":[
        "\u0427\u0438\u0435\u043a\u0443\u0440\u043a\u0430\u043b\u043d\u0441"
    ],
    "qs_pg:aaroncc":"LV",
    "qs_pg:name":"\u010ciekurkalns",
    "qs_pg:name_adm0":"Latvija",
    "qs_pg:name_adm1":"R\u013cga",
    "qs_pg:photos":125,
    "qs_pg:photos_1k":25,
    "qs_pg:photos_9k":1,
    "qs_pg:photos_9r":3,
    "qs_pg:photos_all":125,
    "qs_pg:photos_sr":3,
    "qs_pg:pop_sr":0,
    "qs_pg:qs_pg_placetype":"locality",
    "qs_pg:qs_pg_placetype_gp":"Town",
    "qs_pg:woe_adm0":23424874,
    "woe:adm0_id":23424874,
    "woe:name_adm0":"Latvija",
    "woe:name_adm1":"R\u013cga",
    "woe:placetype":"Town",
    "wof:name":"\u010ciekurkalns",
    "wof:placetype":"locality"
},
  "geometry": {"coordinates":[24.172668,56.984465],"type":"Point"}
}