{
  "type": "Feature",
  "properties": {
    "gn:admin1_code":"29",
    "gn:admin2_code":"900258.0",
    "gn:asciiname":"Abavnieki",
    "gn:country_code":"LV",
    "gn:dem":64,
    "gn:feature_class":"P",
    "gn:feature_code":"PPL",
    "gn:name":"Abavnieki",
    "gn:population":0,
    "gn:timezone":"Europe/Riga",
    "iso:country":"LV",
    "name:und_x_variant":[
        "Abava"
    ],
    "wof:name":"Abavnieki",
    "wof:placetype":"locality"
},
  "geometry": {"coordinates":[22.93314,56.97436999999999],"type":"Point"}
}