{
  "type": "Feature",
  "properties": {
    "gn:admin1_code":"A5",
    "gn:admin2_code":"641486.0",
    "gn:asciiname":"Upsede",
    "gn:country_code":"LV",
    "gn:dem":32,
    "gn:feature_class":"P",
    "gn:feature_code":"PPL",
    "gn:name":"Ups\u0113de",
    "gn:population":0,
    "gn:timezone":"Europe/Riga",
    "iso:country":"LV",
    "name:und_x_variant":[
        "Ups\u0113de",
        "Lankas"
    ],
    "wof:name":"Upsede",
    "wof:placetype":"locality"
},
  "geometry": {"coordinates":[21.27347,56.76292],"type":"Point"}
}