{
  "type": "Feature",
  "properties": {
    "gn:admin1_code":"09",
    "gn:admin2_code":"500288.0",
    "gn:asciiname":"Vecstameriena",
    "gn:country_code":"LV",
    "gn:dem":128,
    "gn:feature_class":"P",
    "gn:feature_code":"PPL",
    "gn:name":"Vecst\u0101meriena",
    "gn:population":0,
    "gn:timezone":"Europe/Riga",
    "iso:country":"LV",
    "name:eng_x_preferred":[
        "Vecst\u0101meriena"
    ],
    "name:rus_x_preferred":[
        "\u0421\u0442\u0430\u043c\u0435\u0440\u0438\u0435\u043d\u0430"
    ],
    "wof:name":"Vecstameriena",
    "wof:placetype":"locality"
},
  "geometry": {"coordinates":[26.88801,57.21459],"type":"Point"}
}