{
  "type": "Feature",
  "properties": {
    "gn:admin1_code":"10",
    "gn:asciiname":"Bikernieki",
    "gn:country_code":"LV",
    "gn:dem":93,
    "gn:feature_class":"P",
    "gn:feature_code":"PPL",
    "gn:name":"Bi\u0137ernieki",
    "gn:population":0,
    "gn:timezone":"Europe/Riga",
    "iso:country":"LV",
    "wof:name":"Bikernieki",
    "wof:placetype":"locality"
},
  "geometry": {"coordinates":[25.80259,56.3973],"type":"Point"}
}