{
  "type": "Feature",
  "properties": {
    "gn:admin1_code":"30",
    "gn:asciiname":"Daksti",
    "gn:cc2":"LV",
    "gn:country_code":"LV",
    "gn:dem":56,
    "gn:feature_class":"P",
    "gn:feature_code":"PPL",
    "gn:name":"Daksti",
    "gn:population":0,
    "gn:timezone":"Europe/Riga",
    "iso:country":"LV",
    "name:eng_x_preferred":[
        "Daksti"
    ],
    "name:rus_x_preferred":[
        "\u0414\u0430\u043a\u0441\u0442\u044b"
    ],
    "name:und_x_variant":[
        "V\u0101rnas",
        "Daksty",
        "V\u0101rna",
        "Dakste"
    ],
    "wof:name":"Daksti",
    "wof:placetype":"locality"
},
  "geometry": {"coordinates":[25.6408,57.75199],"type":"Point"}
}