{
  "type": "Feature",
  "properties": {
    "gn:admin1_code":"B5",
    "gn:admin2_code":"808400.0",
    "gn:asciiname":"Vaverkrogs",
    "gn:country_code":"LV",
    "gn:dem":50,
    "gn:feature_class":"P",
    "gn:feature_code":"PPL",
    "gn:name":"V\u0101verkrogs",
    "gn:population":0,
    "gn:timezone":"Europe/Riga",
    "iso:country":"LV",
    "name:und_x_variant":[
        "Kangar\u012bsi",
        "Ezeri\u0146i",
        "V\u0101veres",
        "Vaverkalnyni",
        "V\u0101veres Krogs",
        "V\u0101verkrogs"
    ],
    "wof:name":"Vaverkrogs",
    "wof:placetype":"locality"
},
  "geometry": {"coordinates":[24.67198,56.9229],"type":"Point"}
}