{
  "type": "Feature",
  "properties": {
    "gn:admin1_code":"19",
    "gn:admin2_code":"680292.0",
    "gn:asciiname":"Osova",
    "gn:country_code":"LV",
    "gn:dem":179,
    "gn:feature_class":"P",
    "gn:feature_code":"PPL",
    "gn:name":"Osova",
    "gn:population":0,
    "gn:timezone":"Europe/Riga",
    "iso:country":"LV",
    "name:und_x_variant":[
        "Osava",
        "Osova",
        "Osvova"
    ],
    "wof:name":"Osova",
    "wof:placetype":"locality"
},
  "geometry": {"coordinates":[27.8544,56.33284],"type":"Point"}
}