{
  "type": "Feature",
  "properties": {
    "gn:admin1_code":"60",
    "gn:admin2_code":"885150.0",
    "gn:asciiname":"Sabdagas",
    "gn:country_code":"LV",
    "gn:dem":55,
    "gn:feature_class":"P",
    "gn:feature_code":"PPL",
    "gn:name":"Sabdagas",
    "gn:population":0,
    "gn:timezone":"Europe/Riga",
    "iso:country":"LV",
    "name:und_x_variant":[
        "Sabdagsa Ciems",
        "Sabdagas Ciems",
        "Sabdaga",
        "Sabdagas"
    ],
    "wof:name":"Sabdagas",
    "wof:placetype":"locality"
},
  "geometry": {"coordinates":[22.32182,57.47003],"type":"Point"}
}