{
  "type": "Feature",
  "properties": {
    "gn:admin1_code":"A5",
    "gn:admin2_code":"641496.0",
    "gn:asciiname":"Saraiki",
    "gn:country_code":"LV",
    "gn:dem":17,
    "gn:feature_class":"P",
    "gn:feature_code":"PPL",
    "gn:name":"Sarai\u0137i",
    "gn:population":0,
    "gn:timezone":"Europe/Riga",
    "iso:country":"LV",
    "name:pol_x_preferred":[
        "Saraiki"
    ],
    "name:snd_x_preferred":[
        "\u0633\u0631\u0627\u0626\u06aa\u064a \u0645\u0627\u06bb\u06be\u0648"
    ],
    "name:und_x_variant":[
        "Myza Saraykas",
        "Saraika",
        "Saraikas",
        "Saraikas Mui\u017ea",
        "Sarai\u0137i"
    ],
    "wof:name":"Saraiki",
    "wof:placetype":"locality"
},
  "geometry": {"coordinates":[21.07292,56.66344],"type":"Point"}
}