{
  "type": "Feature",
  "properties": {
    "gn:admin1_code":"24",
    "gn:admin2_code":"780272.0",
    "gn:asciiname":"Skrjabi",
    "gn:country_code":"LV",
    "gn:dem":176,
    "gn:feature_class":"P",
    "gn:feature_code":"PPL",
    "gn:name":"\u0160krjabi",
    "gn:population":0,
    "gn:timezone":"Europe/Riga",
    "iso:country":"LV",
    "name:und_x_variant":[
        "\u0160krjabi",
        "\u0160krebi"
    ],
    "wof:name":"Skrjabi",
    "wof:placetype":"locality"
},
  "geometry": {"coordinates":[27.46907,56.27568],"type":"Point"}
}