{
  "type": "Feature",
  "properties": {
    "gn:admin1_code":"09",
    "gn:admin2_code":"500290.0",
    "gn:asciiname":"Skieneri",
    "gn:country_code":"LV",
    "gn:dem":132,
    "gn:feature_class":"P",
    "gn:feature_code":"PPL",
    "gn:name":"\u0160\u0137ieneri",
    "gn:population":0,
    "gn:timezone":"Europe/Riga",
    "iso:country":"LV",
    "wof:name":"Skieneri",
    "wof:placetype":"locality"
},
  "geometry": {"coordinates":[26.73531,57.14175],"type":"Point"}
}