{
  "type": "Feature",
  "properties": {
    "gn:admin1_code":"A4",
    "gn:admin2_code":"427582.0",
    "gn:asciiname":"Placis",
    "gn:country_code":"LV",
    "gn:dem":52,
    "gn:feature_class":"P",
    "gn:feature_code":"PPL",
    "gn:name":"Pl\u0101cis",
    "gn:population":0,
    "gn:timezone":"Europe/Riga",
    "iso:country":"LV",
    "name:eng_x_preferred":[
        "Pl\u0101cis"
    ],
    "name:rus_x_preferred":[
        "\u041f\u043b\u0430\u0446\u0438\u0441"
    ],
    "name:und_x_variant":[
        "Pla\u010dakrogs",
        "Placi",
        "Platsis"
    ],
    "wof:name":"Placis",
    "wof:placetype":"locality"
},
  "geometry": {"coordinates":[24.9795,57.36326],"type":"Point"}
}