{
  "type": "Feature",
  "properties": {
    "gn:admin1_code":"65",
    "gn:admin2_code":"641060.0",
    "gn:asciiname":"Cimdenieki",
    "gn:country_code":"LV",
    "gn:dem":15,
    "gn:feature_class":"P",
    "gn:feature_code":"PPL",
    "gn:name":"Cimdenieki",
    "gn:population":0,
    "gn:timezone":"Europe/Riga",
    "iso:country":"LV",
    "wof:name":"Cimdenieki",
    "wof:placetype":"locality"
},
  "geometry": {"coordinates":[21.09732,56.52585],"type":"Point"}
}