{
  "type": "Feature",
  "properties": {
    "gn:admin1_code":"E9",
    "gn:admin2_code":"681884.0",
    "gn:asciiname":"Pedelova",
    "gn:country_code":"LV",
    "gn:dem":141,
    "gn:feature_class":"P",
    "gn:feature_code":"PPL",
    "gn:name":"Pede\u013cova",
    "gn:population":0,
    "gn:timezone":"Europe/Riga",
    "iso:country":"LV",
    "name:und_x_variant":[
        "Pede\u013cova",
        "Pedeleva"
    ],
    "wof:name":"Pedelova",
    "wof:placetype":"locality"
},
  "geometry": {"coordinates":[28.14158,56.21761],"type":"Point"}
}