{
  "type": "Feature",
  "properties": {
    "gn:gn_country":"LV",
    "gn:gn_fcode":"PPL",
    "gn:gn_pop":1701,
    "gn:population":2412,
    "iso:country":"LV",
    "name:ara_x_preferred":[
        "\u0645\u0627\u0632\u0644\u0627\u0633\u0643\u0627"
    ],
    "name:bul_x_preferred":[
        "\u041c\u0430\u0437\u0441\u0430\u043b\u0430\u0446\u0430"
    ],
    "name:cat_x_preferred":[
        "Mazsalaca"
    ],
    "name:chi_x_preferred":[
        "\u99ac\u8332\u85a9\u62c9\u5bdf"
    ],
    "name:cze_x_preferred":[
        "Mazsalaca"
    ],
    "name:dan_x_preferred":[
        "Mazsalaca"
    ],
    "name:dut_x_preferred":[
        "Mazsalaca"
    ],
    "name:eng_x_preferred":[
        "Mazsalaca"
    ],
    "name:est_x_preferred":[
        "Mazsalaca"
    ],
    "name:fin_x_preferred":[
        "Mazsalaca"
    ],
    "name:fre_x_preferred":[
        "Mazsalaca"
    ],
    "name:ger_x_preferred":[
        "Mazsalaca"
    ],
    "name:hun_x_preferred":[
        "Mazsalaca"
    ],
    "name:jpn_x_preferred":[
        "\u30de\u30ba\u30b5\u30e9\u30c4\u30a1"
    ],
    "name:kaz_x_preferred":[
        "\u041c\u0430\u0437\u0441\u0430\u043b\u0430\u0446\u0430"
    ],
    "name:lav_x_preferred":[
        "Mazsalaca"
    ],
    "name:lit_x_preferred":[
        "Mazsalaca"
    ],
    "name:per_x_preferred":[
        "\u0645\u0627\u0632\u0633\u0627\u0644\u0627\u06a9\u0627"
    ],
    "name:pol_x_preferred":[
        "Mazsalaca"
    ],
    "name:rus_x_preferred":[
        "\u041c\u0430\u0437\u0441\u0430\u043b\u0430\u0446\u0430"
    ],
    "name:sgs_x_preferred":[
        "Mazsalaca"
    ],
    "name:swe_x_preferred":[
        "Mazsalaca"
    ],
    "name:ukr_x_preferred":[
        "\u041c\u0430\u0437\u0441\u0430\u043b\u0430\u0446\u0430"
    ],
    "name:unk_x_variant":[
        "Salisburg"
    ],
    "qs_pg:aaroncc":"LV",
    "qs_pg:gn_country":"LV",
    "qs_pg:gn_fcode":"PPL",
    "qs_pg:gn_pop":1701,
    "qs_pg:name":"Mazsalace",
    "qs_pg:name_adm0":"Latvija",
    "qs_pg:name_adm1":"Mazsalacas Novads",
    "qs_pg:photos_9k":1,
    "qs_pg:photos_9r":1,
    "qs_pg:photos_all":6,
    "qs_pg:photos_sr":0,
    "qs_pg:pop_sr":3,
    "qs_pg:qs_pg_placetype":"locality",
    "qs_pg:qs_pg_placetype_gp":"Town",
    "qs_pg:woe_adm0":23424874,
    "woe:adm0_id":23424874,
    "woe:name_adm0":"Latvija",
    "woe:name_adm1":"Mazsalacas Novads",
    "woe:placetype":"Town",
    "wof:name":"Mazsalace",
    "wof:placetype":"locality",
    "wof:population":2412
},
  "geometry": {"coordinates":[25.05475,57.86329],"type":"Point"}
}