{
  "type": "Feature",
  "properties": {
    "gn:admin1_code":"24",
    "gn:admin2_code":"780268.0",
    "gn:asciiname":"Skradeli",
    "gn:country_code":"LV",
    "gn:dem":167,
    "gn:feature_class":"P",
    "gn:feature_code":"PPL",
    "gn:name":"Skrade\u013ci",
    "gn:population":0,
    "gn:timezone":"Europe/Riga",
    "iso:country":"LV",
    "name:und_x_variant":[
        "Skryadili",
        "Skr\u0113de\u013ci",
        "Skrade\u013ci"
    ],
    "wof:name":"Skradeli",
    "wof:placetype":"locality"
},
  "geometry": {"coordinates":[27.20498,56.36573000000001],"type":"Point"}
}