{
  "type": "Feature",
  "properties": {
    "gn:admin1_code":"62",
    "gn:admin2_code":"905166.0",
    "gn:asciiname":"Caukciems",
    "gn:country_code":"LV",
    "gn:dem":4,
    "gn:feature_class":"P",
    "gn:feature_code":"PPL",
    "gn:name":"\u010caukciems",
    "gn:population":0,
    "gn:timezone":"Europe/Riga",
    "iso:country":"LV",
    "name:und_x_variant":[
        "Chauktsiyem",
        "Tsauktsiems",
        "\u010caukciems"
    ],
    "wof:name":"Caukciems",
    "wof:placetype":"locality"
},
  "geometry": {"coordinates":[23.41817,57.0035],"type":"Point"}
}